Workbook

Sheet Linhas Investimento
A1: AGÊNCIA DE FOMENTO DE GOIÁS S/A | AA1: 2 | AB1: 2
A2: IMPORTANTE: Os valores simulados podem variar e estão sujeitos à data de vencimento da parcela e da liberação do crédito; O financiamento e condições são sujeitas à aprovação final da análise de crédito; Valores calculados com base na taxa líquida para quando não há atraso nos pagamentos.
A3: LINHA DE INVESTIMENTO | AA3: TAC | AB3: IOF
A4: LINHA | J4: 7 | K4: 1 | N4: LINHA | O4: TAXA (a.m.) | P4: TAXA BONUS | Q4: CG1 (a.m.) | R4: CG2 (a.m.) | S4: PRAZO (meses) | T4: CARÊNCIA (até meses) | U4: LIMITE | V4: GARANTIA | AA4: Descontado | AB4: Descontado
N5: GoiásFomento Investimento | O5: 0.0217 | P5: 0.0174 | Q5: =P5 -> 0.0174 | R5: =Q5 -> 0.0174 | S5: 60 | T5: 12 | U5: 400000 | V5: Sim | AA5: Financiado | AB5: Financiado
C6: =IF(AND(J4=1,K4=1),Q5,IF(AND(J4=1,K4=2),R5,IF(AND(J4=1,K4=3),P5,"-"))) -> - | N6: GoiásFomento Investimento VIP | O6: 0.0213 | P6: 0.017 | Q6: =P6 -> 0.017 | R6: =Q6 -> 0.017 | S6: 60 | T6: 12 | U6: 400000 | V6: Não
C7: =IF(AND(J4=2,K4=1),Q6,IF(AND(J4=2,K4=2),R6,IF(AND(J4=2,K4=3),P6,"-"))) -> - | N7: GoiásFomento Investimento - IMCF | O7: 0.0209 | P7: 0.0167 | Q7: =P7 -> 0.0167 | R7: =Q7 -> 0.0167 | S7: 60 | T7: 12 | U7: 400000
C8: =IF(AND(J4=3,K4=1),Q7,IF(AND(J4=3,K4=2),R7,IF(AND(J4=3,K4=3),P7,"-"))) -> - | N8: Goiás Fomento Investimento - VIP IMCF | O8: 0.0206 | P8: 0.0165 | Q8: =P8 -> 0.0165 | R8: =Q8 -> 0.0165 | S8: 60 | T8: 12 | U8: 400000
C9: =IF(AND(J4=4,K4=1),Q8,IF(AND(J4=4,K4=2),R8,IF(AND(J4=4,K4=3),P8,"-"))) -> - | N9: GoiásFomento Eficiência Energética (fixo) | O9: 0.0206 | P9: 0.0165 | Q9: =P9 -> 0.0165 | R9: =Q9 -> 0.0165 | S9: 60 | T9: 6 | U9: 400000
C10: =IF(AND(J4=5,K4=1),Q9,IF(AND(J4=5,K4=2),R9,IF(AND(J4=5,K4=3),P9,"-"))) -> - | N10: GoiásFomento Eficiência Energética MEI (fixo) | O10: 0.0206 | P10: 0.0165 | Q10: =P10 -> 0.0165 | R10: =R9 -> 0.0165 | S10: 60 | T10: 6 | U10: 30000
C11: =IF(AND(J4=6,K4=1),Q10,IF(AND(J4=6,K4=2),R10,IF(AND(J4=6,K4=3),P10,"-"))) -> - | N11: GoiásFomento (INVESTIMENTO)Tecnologia/PQF-IEL/Turismo/FarmaDrogas/ Contabilistas / Mulher Empreendedora | O11: 0.0206 | P11: 0.0165 | Q11: =P11 -> 0.0165 | R11: =Q11 -> 0.0165 | S11: 60 | T11: 12 | U11: 400000
C12: =IF(AND(J4=7,K4=1),Q11,IF(AND(J4=7,K4=2),R11,IF(AND(J4=7,K4=3),P11,"-"))) -> 0.0165 | N12: GoiásFomento Microcrédito Produtivo - Investimento | O12: 0.0206 | P12: 0.0165 | Q12: =P12 -> 0.0165 | R12: =Q12 -> 0.0165 | S12: 36 | T12: 12 | U12: 21000
C13: =IF(AND(J4=8,K4=1),Q12,IF(AND(J4=8,K4=2),R12,IF(AND(J4=8,K4=3),P12,"-"))) -> -
A14: INFORMAÇÕES | AK14: TAC | AL14: =F15 -> 2000 | AM14: =AL14/AL16 -> 0.033591696
A15: VALOR FINANCIADO | B15: 100000 | C15: TAXA NOMINAL | D15: =IF(J4=1,O5,IF(J4=2,O6,IF(J4=3,O7,IF(J4=4,O8,IF(J4=5,O9,IF(J4=6,O10,IF(J4=7,O11,IF(J4=8,O12)))))))) -> 0.0206 | E15: =AJ22 -> 0.017859866 | F15: =IF(B15<=3000,50,IF(B15<=21000,IF(B15*0.03<=420,B15*0.03,420),IF(B15<=100000,B15*0.02,2000+B15*0.005))) -> 2000 | J15: 4 | AK15: JUROS | AL15: =C22 -> 57538.523 | AM15: =AL15/AL16 -> 0.9664083
A16: CARÊNCIA | B16: 6 | C16: TAXA COM BÔNUS | D16: =LARGE(C6:C13,1) -> 0.0165 | F16: =AF24 -> 1507.5 | J16: 2 | AK16: TOTAL | AL16: =SUM(AL14:AL15) -> 59538.523
A17: PRAZO TOTAL | B17: 60 | C17: DATA DA PROPOSTA | D17: =TODAY() -> 46240 | F17: =IF(J21=TRUE,IF(K4=1,(B15*E19*0.001*B17),IF(K4=2,(F19*0.001*B17),IF(K4=3,0,""))),0) -> 0 | J17: Descontado | L17: FALSE | AJ17: 100000
A18: OPÇÕES DE GARANTIA | J18: Financiado | AJ18: =AJ22 -> 0.017859866 | AL18: =PMT(AJ18,AJ19,-AJ17) -> 2729.6846
A19: RENDA PARA AVAL | B19: =IF(LARGE(F23:F241,1)*3<2424,2424,LARGE(F23:F241,1)*3) -> 10679.177 | C19: ALIENAÇÃO DE IMÓVEL | D19: =IF(J21=TRUE,(B15-F19)*1.5/0.7,B15*1.5/0.7) -> 214285.71 | E19: 0.8 | F19: =IF(J21=TRUE,IF(K4=1,(B15*E19),IF(K4=2,B15*E19,IF(K4=3,0,""))),0) -> 0 | J19: FINANCIADO | L19: TRUE | AJ19: =B17 -> 60
A20: SIMULAÇÃO DO VALOR DAS PARCELAS | J20: Financiado
A21: PARCELA | B21: AMORTIZAÇÃO | C21: JUROS | D21: VALOR AMORTIZAÇÃO | E21: SALDO DEVEDOR | F21: PARCELA COM BÔNUS | J21: FALSE | AB21: IOF - ACIMA ATÉ 365 DIAS | AJ21: TIR (PARCELA C/ BÔNUS) | AK21: TIR (PARCELA S/ BÔNUS)
A22: TOTAL | C22: =SUM(C23:C242) -> 57538.523 | D22: =SUM(D23:D242) -> 103117.78 | F22: =SUM(F23:F242) -> 160656.28 | AJ22: =IRR(AJ23:AJ107) -> 0.017859866 | AK22: =IRR(AK23:AK107) -> 0.022073317
A23: 0 | C23: =D16 -> 0.0165 | E23: =IF(AND(AA1=1,AB1=1,J16=1),B15,IF(AND(AA1=1,AB1=1,J16=2),B15+F17,IF(AND(AA1=1,AB1=2,J16=1),B15+F16,IF(AND(AA1=1,AB1=2,J16=3),B15+F16,IF(AND(AA1=2,AB1=1,J16=1),B15+F15,IF(AND(AA1=2,AB1=1,J16=2),B15+F15+F17,IF(AND(AA1=2,AB1=2,J16=2),B15+F17+F16+F15,IF(AND(AA1=2,AB1=2,J16=3),B15+F15+F16,IF(AND(AA1=2,AB1=2,J16=1),B15+F15+F16,IF(AND(AA1=1,AB1=2,J16=2),B15+F16+F17, IF(AND(AA1=1,AB1=1,J16=3),B15))))))))))) -> 103507.5 | AJ23: =-B15 -> -100000 | AK23: =AJ23 -> -100000
A24: =IF(A23<B$17,A23+1,"") -> 1 | B24: =IF(A24="","",IF(A24<=B$16,"carência","amortização")) -> carência | C24: =IF(B24="","",E23*$C$23) -> 1707.8737 | D24: =IF(C24="","",IF(A24<=B$16,0,B$15/(B$17-B$16))) -> 0 | E24: =IF(F24="","",E23-D24) -> 103507.5 | F24: =IF(D24="","",D24+C24) -> 1707.8737 | AB24: IOF | AC24: 0.0038 | AE24: =AC27*AC24 -> 380 | AF24: =IF(L19=FALSE,0,IF(AND(AH25=TRUE,B15<=30000),AE24+AE26,AE24+AE25)) -> 1507.5 | AJ24: =IF(A24<=$B$17,F24,0) -> 1707.8737 | AK24: =IF(A24<=$B$17,E23*$D$15+D24,0) -> 2132.2545
A25: =IF(A24<B$17,A24+1,"") -> 2 | B25: =IF(A25="","",IF(A25<=B$16,"carência","amortização")) -> carência | C25: =IF(B25="","",E24*$C$23) -> 1707.8737 | D25: =IF(C25="","",IF(A25<=B$16,0,B$15/(B$17-B$16))) -> 0 | E25: =IF(F25="","",E24-D25) -> 103507.5 | F25: =IF(D25="","",D25+C25) -> 1707.8737 | AB25: ALÍQUOTA | AC25: 4.1e-05 | AE25: =SUM(AG30:AG83) -> 1127.5 | AH25: FALSE | AJ25: =IF(A25<=$B$17,F25,0) -> 1707.8737 | AK25: =IF(A25<=$B$17,E24*$D$15+D25,0) -> 2132.2545
A26: =IF(A25<B$17,A25+1,"") -> 3 | B26: =IF(A26="","",IF(A26<=B$16,"carência","amortização")) -> carência | C26: =IF(B26="","",E25*$C$23) -> 1707.8737 | D26: =IF(C26="","",IF(A26<=B$16,0,B$15/(B$17-B$16))) -> 0 | E26: =IF(F26="","",E25-D26) -> 103507.5 | F26: =IF(D26="","",D26+C26) -> 1707.8737 | AB26: ALÍQUOTA SIMPLES | AC26: =0.00137/100 -> 1.37e-05 | AE26: =SUM(AH30:AH308) -> 376.75 | AJ26: =IF(A26<=$B$17,F26,0) -> 1707.8737 | AK26: =IF(A26<=$B$17,E25*$D$15+D26,0) -> 2132.2545
A27: =IF(A26<B$17,A26+1,"") -> 4 | B27: =IF(A27="","",IF(A27<=B$16,"carência","amortização")) -> carência | C27: =IF(B27="","",E26*$C$23) -> 1707.8737 | D27: =IF(C27="","",IF(A27<=B$16,0,B$15/(B$17-B$16))) -> 0 | E27: =IF(F27="","",E26-D27) -> 103507.5 | F27: =IF(D27="","",D27+C27) -> 1707.8737 | AB27: LIBERAÇÃO | AC27: =B15 -> 100000 | AJ27: =IF(A27<=$B$17,F27,0) -> 1707.8737 | AK27: =IF(A27<=$B$17,E26*$D$15+D27,0) -> 2132.2545
A28: =IF(A27<B$17,A27+1,"") -> 5 | B28: =IF(A28="","",IF(A28<=B$16,"carência","amortização")) -> carência | C28: =IF(B28="","",E27*$C$23) -> 1707.8737 | D28: =IF(C28="","",IF(A28<=B$16,0,B$15/(B$17-B$16))) -> 0 | E28: =IF(F28="","",E27-D28) -> 103507.5 | F28: =IF(D28="","",D28+C28) -> 1707.8737 | AG28: IOF NORMAL | AH28: IOF SIMPLES | AJ28: =IF(A28<=$B$17,F28,0) -> 1707.8737 | AK28: =IF(A28<=$B$17,E27*$D$15+D28,0) -> 2132.2545
A29: =IF(A28<B$17,A28+1,"") -> 6 | B29: =IF(A29="","",IF(A29<=B$16,"carência","amortização")) -> carência | C29: =IF(B29="","",E28*$C$23) -> 1707.8737 | D29: =IF(C29="","",IF(A29<=B$16,0,B$15/(B$17-B$16))) -> 0 | E29: =IF(F29="","",E28-D29) -> 103507.5 | F29: =IF(D29="","",D29+C29) -> 1707.8737 | AA29: 0 | AB29: =D17 -> 46240 | AC29: =IF(AB29="","",AC27) -> 100000 | AD29: =IF(AA29="","",IF(AA29<=B$16,0,B$15/(B$17-B$16))) -> 0 | AJ29: =IF(A29<=$B$17,F29,0) -> 1707.8737 | AK29: =IF(A29<=$B$17,E28*$D$15+D29,0) -> 2132.2545
A30: =IF(A29<B$17,A29+1,"") -> 7 | B30: =IF(A30="","",IF(A30<=B$16,"carência","amortização")) -> amortização | C30: =IF(B30="","",E29*$C$23) -> 1707.8737 | D30: =IF(C30="","",IF(A30<=B$16,0,B$15/(B$17-B$16))) -> 1851.8519 | E30: =IF(F30="","",E29-D30) -> 101655.65 | F30: =IF(D30="","",D30+C30) -> 3559.7256 | AA30: =IF(AA29<B$17,AA29+1,"") -> 1 | AB30: =IF(AA30="","",AB29+30) -> 46270 | AC30: =IF(AB30="","",IF(AA30<=B$16,AC29,AC29-AD30)) -> 100000 | AD30: =IF(AA30="","",IF(AA30<=B$16,0,B$15/(B$17-B$16))) -> 0 | AE30: =IF(AD30="","",AB30-AB29) -> 30 | AF30: =IF(AE30="","",AB30-AB$29) -> 30 | AG30: =IF(AF30="","",IF(AF30<365,AF30*AC$25*AD30,365*AD30*AC$25)) -> 0 | AH30: =IF(AF30="","",IF(AF30<365,AF30*AC$26*AD30,365*AD30*AC$26)) -> 0 | AJ30: =IF(A30<=$B$17,F30,0) -> 3559.7256 | AK30: =IF(A30<=$B$17,E29*$D$15+D30,0) -> 3984.1064
A31: =IF(A30<B$17,A30+1,"") -> 8 | B31: =IF(A31="","",IF(A31<=B$16,"carência","amortização")) -> amortização | C31: =IF(B31="","",E30*$C$23) -> 1677.3182 | D31: =IF(C31="","",IF(A31<=B$16,0,B$15/(B$17-B$16))) -> 1851.8519 | E31: =IF(F31="","",E30-D31) -> 99803.796 | F31: =IF(D31="","",D31+C31) -> 3529.17 | AA31: =IF(AA30<B$17,AA30+1,"") -> 2 | AB31: =IF(AA31="","",AB30+30) -> 46300 | AC31: =IF(AB31="","",IF(AA31<=B$16,AC30,AC30-AD31)) -> 100000 | AD31: =IF(AA31="","",IF(AA31<=B$16,0,B$15/(B$17-B$16))) -> 0 | AE31: =IF(AD31="","",AB31-AB30) -> 30 | AF31: =IF(AE31="","",AB31-AB$29) -> 60 | AG31: =IF(AF31="","",IF(AF31<365,AF31*AC$25*AD31,365*AD31*AC$25)) -> 0 | AH31: =IF(AF31="","",IF(AF31<365,AF31*AC$26*AD31,365*AD31*AC$26)) -> 0 | AJ31: =IF(A31<=$B$17,F31,0) -> 3529.17 | AK31: =IF(A31<=$B$17,E30*$D$15+D31,0) -> 3945.9582
A32: =IF(A31<B$17,A31+1,"") -> 9 | B32: =IF(A32="","",IF(A32<=B$16,"carência","amortização")) -> amortização | C32: =IF(B32="","",E31*$C$23) -> 1646.7626 | D32: =IF(C32="","",IF(A32<=B$16,0,B$15/(B$17-B$16))) -> 1851.8519 | E32: =IF(F32="","",E31-D32) -> 97951.944 | F32: =IF(D32="","",D32+C32) -> 3498.6145 | AA32: =IF(AA31<B$17,AA31+1,"") -> 3 | AB32: =IF(AA32="","",AB31+30) -> 46330 | AC32: =IF(AB32="","",IF(AA32<=B$16,AC31,AC31-AD32)) -> 100000 | AD32: =IF(AA32="","",IF(AA32<=B$16,0,B$15/(B$17-B$16))) -> 0 | AE32: =IF(AD32="","",AB32-AB31) -> 30 | AF32: =IF(AE32="","",AB32-AB$29) -> 90 | AG32: =IF(AF32="","",IF(AF32<365,AF32*AC$25*AD32,365*AD32*AC$25)) -> 0 | AH32: =IF(AF32="","",IF(AF32<365,AF32*AC$26*AD32,365*AD32*AC$26)) -> 0 | AJ32: =IF(A32<=$B$17,F32,0) -> 3498.6145 | AK32: =IF(A32<=$B$17,E31*$D$15+D32,0) -> 3907.8101
A33: =IF(A32<B$17,A32+1,"") -> 10 | B33: =IF(A33="","",IF(A33<=B$16,"carência","amortização")) -> amortização | C33: =IF(B33="","",E32*$C$23) -> 1616.2071 | D33: =IF(C33="","",IF(A33<=B$16,0,B$15/(B$17-B$16))) -> 1851.8519 | E33: =IF(F33="","",E32-D33) -> 96100.093 | F33: =IF(D33="","",D33+C33) -> 3468.0589 | AA33: =IF(AA32<B$17,AA32+1,"") -> 4 | AB33: =IF(AA33="","",AB32+30) -> 46360 | AC33: =IF(AB33="","",IF(AA33<=B$16,AC32,AC32-AD33)) -> 100000 | AD33: =IF(AA33="","",IF(AA33<=B$16,0,B$15/(B$17-B$16))) -> 0 | AE33: =IF(AD33="","",AB33-AB32) -> 30 | AF33: =IF(AE33="","",AB33-AB$29) -> 120 | AG33: =IF(AF33="","",IF(AF33<365,AF33*AC$25*AD33,365*AD33*AC$25)) -> 0 | AH33: =IF(AF33="","",IF(AF33<365,AF33*AC$26*AD33,365*AD33*AC$26)) -> 0 | AJ33: =IF(A33<=$B$17,F33,0) -> 3468.0589 | AK33: =IF(A33<=$B$17,E32*$D$15+D33,0) -> 3869.6619
A34: =IF(A33<B$17,A33+1,"") -> 11 | B34: =IF(A34="","",IF(A34<=B$16,"carência","amortização")) -> amortização | C34: =IF(B34="","",E33*$C$23) -> 1585.6515 | D34: =IF(C34="","",IF(A34<=B$16,0,B$15/(B$17-B$16))) -> 1851.8519 | E34: =IF(F34="","",E33-D34) -> 94248.241 | F34: =IF(D34="","",D34+C34) -> 3437.5034 | AA34: =IF(AA33<B$17,AA33+1,"") -> 5 | AB34: =IF(AA34="","",AB33+30) -> 46390 | AC34: =IF(AB34="","",IF(AA34<=B$16,AC33,AC33-AD34)) -> 100000 | AD34: =IF(AA34="","",IF(AA34<=B$16,0,B$15/(B$17-B$16))) -> 0 | AE34: =IF(AD34="","",AB34-AB33) -> 30 | AF34: =IF(AE34="","",AB34-AB$29) -> 150 | AG34: =IF(AF34="","",IF(AF34<365,AF34*AC$25*AD34,365*AD34*AC$25)) -> 0 | AH34: =IF(AF34="","",IF(AF34<365,AF34*AC$26*AD34,365*AD34*AC$26)) -> 0 | AJ34: =IF(A34<=$B$17,F34,0) -> 3437.5034 | AK34: =IF(A34<=$B$17,E33*$D$15+D34,0) -> 3831.5138
A35: =IF(A34<B$17,A34+1,"") -> 12 | B35: =IF(A35="","",IF(A35<=B$16,"carência","amortização")) -> amortização | C35: =IF(B35="","",E34*$C$23) -> 1555.096 | D35: =IF(C35="","",IF(A35<=B$16,0,B$15/(B$17-B$16))) -> 1851.8519 | E35: =IF(F35="","",E34-D35) -> 92396.389 | F35: =IF(D35="","",D35+C35) -> 3406.9478 | AA35: =IF(AA34<B$17,AA34+1,"") -> 6 | AB35: =IF(AA35="","",AB34+30) -> 46420 | AC35: =IF(AB35="","",IF(AA35<=B$16,AC34,AC34-AD35)) -> 100000 | AD35: =IF(AA35="","",IF(AA35<=B$16,0,B$15/(B$17-B$16))) -> 0 | AE35: =IF(AD35="","",AB35-AB34) -> 30 | AF35: =IF(AE35="","",AB35-AB$29) -> 180 | AG35: =IF(AF35="","",IF(AF35<365,AF35*AC$25*AD35,365*AD35*AC$25)) -> 0 | AH35: =IF(AF35="","",IF(AF35<365,AF35*AC$26*AD35,365*AD35*AC$26)) -> 0 | AJ35: =IF(A35<=$B$17,F35,0) -> 3406.9478 | AK35: =IF(A35<=$B$17,E34*$D$15+D35,0) -> 3793.3656
A36: =IF(A35<B$17,A35+1,"") -> 13 | B36: =IF(A36="","",IF(A36<=B$16,"carência","amortização")) -> amortização | C36: =IF(B36="","",E35*$C$23) -> 1524.5404 | D36: =IF(C36="","",IF(A36<=B$16,0,E$23/(B$17-B$16))) -> 1916.8056 | E36: =IF(F36="","",E35-D36) -> 90479.583 | F36: =IF(D36="","",D36+C36) -> 3441.346 | AA36: =IF(AA35<B$17,AA35+1,"") -> 7 | AB36: =IF(AA36="","",AB35+30) -> 46450 | AC36: =IF(AB36="","",IF(AA36<=B$16,AC35,AC35-AD36)) -> 98148.148 | AD36: =IF(AA36="","",IF(AA36<=B$16,0,B$15/(B$17-B$16))) -> 1851.8519 | AE36: =IF(AD36="","",AB36-AB35) -> 30 | AF36: =IF(AE36="","",AB36-AB$29) -> 210 | AG36: =IF(AF36="","",IF(AF36<365,AF36*AC$25*AD36,365*AD36*AC$25)) -> 15.944444 | AH36: =IF(AF36="","",IF(AF36<365,AF36*AC$26*AD36,365*AD36*AC$26)) -> 5.3277778 | AJ36: =IF(A36<=$B$17,F36,0) -> 3441.346 | AK36: =IF(A36<=$B$17,E35*$D$15+D36,0) -> 3820.1712
A37: =IF(A36<B$17,A36+1,"") -> 14 | B37: =IF(A37="","",IF(A37<=B$16,"carência","amortização")) -> amortização | C37: =IF(B37="","",E36*$C$23) -> 1492.9131 | D37: =IF(C37="","",IF(A37<=B$16,0,E$23/(B$17-B$16))) -> 1916.8056 | E37: =IF(F37="","",E36-D37) -> 88562.778 | F37: =IF(D37="","",D37+C37) -> 3409.7187 | AA37: =IF(AA36<B$17,AA36+1,"") -> 8 | AB37: =IF(AA37="","",AB36+30) -> 46480 | AC37: =IF(AB37="","",IF(AA37<=B$16,AC36,AC36-AD37)) -> 96296.296 | AD37: =IF(AA37="","",IF(AA37<=B$16,0,B$15/(B$17-B$16))) -> 1851.8519 | AE37: =IF(AD37="","",AB37-AB36) -> 30 | AF37: =IF(AE37="","",AB37-AB$29) -> 240 | AG37: =IF(AF37="","",IF(AF37<365,AF37*AC$25*AD37,365*AD37*AC$25)) -> 18.222222 | AH37: =IF(AF37="","",IF(AF37<365,AF37*AC$26*AD37,365*AD37*AC$26)) -> 6.0888889 | AJ37: =IF(A37<=$B$17,F37,0) -> 3409.7187 | AK37: =IF(A37<=$B$17,E36*$D$15+D37,0) -> 3780.685
A38: =IF(A37<B$17,A37+1,"") -> 15 | B38: =IF(A38="","",IF(A38<=B$16,"carência","amortização")) -> amortização | C38: =IF(B38="","",E37*$C$23) -> 1461.2858 | D38: =IF(C38="","",IF(A38<=B$16,0,E$23/(B$17-B$16))) -> 1916.8056 | E38: =IF(F38="","",E37-D38) -> 86645.972 | F38: =IF(D38="","",D38+C38) -> 3378.0914 | AA38: =IF(AA37<B$17,AA37+1,"") -> 9 | AB38: =IF(AA38="","",AB37+30) -> 46510 | AC38: =IF(AB38="","",IF(AA38<=B$16,AC37,AC37-AD38)) -> 94444.444 | AD38: =IF(AA38="","",IF(AA38<=B$16,0,B$15/(B$17-B$16))) -> 1851.8519 | AE38: =IF(AD38="","",AB38-AB37) -> 30 | AF38: =IF(AE38="","",AB38-AB$29) -> 270 | AG38: =IF(AF38="","",IF(AF38<365,AF38*AC$25*AD38,365*AD38*AC$25)) -> 20.5 | AH38: =IF(AF38="","",IF(AF38<365,AF38*AC$26*AD38,365*AD38*AC$26)) -> 6.85 | AJ38: =IF(A38<=$B$17,F38,0) -> 3378.0914 | AK38: =IF(A38<=$B$17,E37*$D$15+D38,0) -> 3741.1988
A39: =IF(A38<B$17,A38+1,"") -> 16 | B39: =IF(A39="","",IF(A39<=B$16,"carência","amortização")) -> amortização | C39: =IF(B39="","",E38*$C$23) -> 1429.6585 | D39: =IF(C39="","",IF(A39<=B$16,0,E$23/(B$17-B$16))) -> 1916.8056 | E39: =IF(F39="","",E38-D39) -> 84729.167 | F39: =IF(D39="","",D39+C39) -> 3346.4641 | AA39: =IF(AA38<B$17,AA38+1,"") -> 10 | AB39: =IF(AA39="","",AB38+30) -> 46540 | AC39: =IF(AB39="","",IF(AA39<=B$16,AC38,AC38-AD39)) -> 92592.593 | AD39: =IF(AA39="","",IF(AA39<=B$16,0,B$15/(B$17-B$16))) -> 1851.8519 | AE39: =IF(AD39="","",AB39-AB38) -> 30 | AF39: =IF(AE39="","",AB39-AB$29) -> 300 | AG39: =IF(AF39="","",IF(AF39<365,AF39*AC$25*AD39,365*AD39*AC$25)) -> 22.777778 | AH39: =IF(AF39="","",IF(AF39<365,AF39*AC$26*AD39,365*AD39*AC$26)) -> 7.6111111 | AJ39: =IF(A39<=$B$17,F39,0) -> 3346.4641 | AK39: =IF(A39<=$B$17,E38*$D$15+D39,0) -> 3701.7126
A40: =IF(A39<B$17,A39+1,"") -> 17 | B40: =IF(A40="","",IF(A40<=B$16,"carência","amortização")) -> amortização | C40: =IF(B40="","",E39*$C$23) -> 1398.0312 | D40: =IF(C40="","",IF(A40<=B$16,0,E$23/(B$17-B$16))) -> 1916.8056 | E40: =IF(F40="","",E39-D40) -> 82812.361 | F40: =IF(D40="","",D40+C40) -> 3314.8368 | AA40: =IF(AA39<B$17,AA39+1,"") -> 11 | AB40: =IF(AA40="","",AB39+30) -> 46570 | AC40: =IF(AB40="","",IF(AA40<=B$16,AC39,AC39-AD40)) -> 90740.741 | AD40: =IF(AA40="","",IF(AA40<=B$16,0,B$15/(B$17-B$16))) -> 1851.8519 | AE40: =IF(AD40="","",AB40-AB39) -> 30 | AF40: =IF(AE40="","",AB40-AB$29) -> 330 | AG40: =IF(AF40="","",IF(AF40<365,AF40*AC$25*AD40,365*AD40*AC$25)) -> 25.055556 | AH40: =IF(AF40="","",IF(AF40<365,AF40*AC$26*AD40,365*AD40*AC$26)) -> 8.3722222 | AJ40: =IF(A40<=$B$17,F40,0) -> 3314.8368 | AK40: =IF(A40<=$B$17,E39*$D$15+D40,0) -> 3662.2264
A41: =IF(A40<B$17,A40+1,"") -> 18 | B41: =IF(A41="","",IF(A41<=B$16,"carência","amortização")) -> amortização | C41: =IF(B41="","",E40*$C$23) -> 1366.404 | D41: =IF(C41="","",IF(A41<=B$16,0,E$23/(B$17-B$16))) -> 1916.8056 | E41: =IF(F41="","",E40-D41) -> 80895.556 | F41: =IF(D41="","",D41+C41) -> 3283.2095 | AA41: =IF(AA40<B$17,AA40+1,"") -> 12 | AB41: =IF(AA41="","",AB40+30) -> 46600 | AC41: =IF(AB41="","",IF(AA41<=B$16,AC40,AC40-AD41)) -> 88888.889 | AD41: =IF(AA41="","",IF(AA41<=B$16,0,B$15/(B$17-B$16))) -> 1851.8519 | AE41: =IF(AD41="","",AB41-AB40) -> 30 | AF41: =IF(AE41="","",AB41-AB$29) -> 360 | AG41: =IF(AF41="","",IF(AF41<365,AF41*AC$25*AD41,365*AD41*AC$25)) -> 27.333333 | AH41: =IF(AF41="","",IF(AF41<365,AF41*AC$26*AD41,365*AD41*AC$26)) -> 9.1333333 | AJ41: =IF(A41<=$B$17,F41,0) -> 3283.2095 | AK41: =IF(A41<=$B$17,E40*$D$15+D41,0) -> 3622.7402
A42: =IF(A41<B$17,A41+1,"") -> 19 | B42: =IF(A42="","",IF(A42<=B$16,"carência","amortização")) -> amortização | C42: =IF(B42="","",E41*$C$23) -> 1334.7767 | D42: =IF(C42="","",IF(A42<=B$16,0,E$23/(B$17-B$16))) -> 1916.8056 | E42: =IF(F42="","",E41-D42) -> 78978.75 | F42: =IF(D42="","",D42+C42) -> 3251.5822 | AA42: =IF(AA41<B$17,AA41+1,"") -> 13 | AB42: =IF(AA42="","",AB41+30) -> 46630 | AC42: =IF(AA42="","",IF(AB42<=B$16,AC27,AC41-AD42)) -> 87037.037 | AD42: =IF(AA42="","",IF(AA42<=B$16,0,B$15/(B$17-B$16))) -> 1851.8519 | AE42: =IF(AD42="","",AB42-AB41) -> 30 | AF42: =IF(AE42="","",AB42-AB$29) -> 390 | AG42: =IF(AF42="","",IF(AF42<365,AF42*AC$25*AD42,365*AD42*AC$25)) -> 27.712963 | AH42: =IF(AF42="","",IF(AF42<365,AF42*AC$26*AD42,365*AD42*AC$26)) -> 9.2601852 | AJ42: =IF(A42<=$B$17,F42,0) -> 3251.5822 | AK42: =IF(A42<=$B$17,E41*$D$15+D42,0) -> 3583.254
A43: =IF(A42<B$17,A42+1,"") -> 20 | B43: =IF(A43="","",IF(A43<=B$16,"carência","amortização")) -> amortização | C43: =IF(B43="","",E42*$C$23) -> 1303.1494 | D43: =IF(C43="","",IF(A43<=B$16,0,E$23/(B$17-B$16))) -> 1916.8056 | E43: =IF(F43="","",E42-D43) -> 77061.944 | F43: =IF(D43="","",D43+C43) -> 3219.9549 | AA43: =IF(AA42<B$17,AA42+1,"") -> 14 | AB43: =IF(AA43="","",AB42+30) -> 46660 | AC43: =IF(AB43="","",IF(AA43<=B$16,AC42,AC42-AD43)) -> 85185.185 | AD43: =IF(AA43="","",IF(AA43<=B$16,0,B$15/(B$17-B$16))) -> 1851.8519 | AE43: =IF(AD43="","",AB43-AB42) -> 30 | AF43: =IF(AE43="","",AB43-AB$29) -> 420 | AG43: =IF(AF43="","",IF(AF43<365,AF43*AC$25*AD43,365*AD43*AC$25)) -> 27.712963 | AH43: =IF(AF43="","",IF(AF43<365,AF43*AC$26*AD43,365*AD43*AC$26)) -> 9.2601852 | AJ43: =IF(A43<=$B$17,F43,0) -> 3219.9549 | AK43: =IF(A43<=$B$17,E42*$D$15+D43,0) -> 3543.7678
A44: =IF(A43<B$17,A43+1,"") -> 21 | B44: =IF(A44="","",IF(A44<=B$16,"carência","amortização")) -> amortização | C44: =IF(B44="","",E43*$C$23) -> 1271.5221 | D44: =IF(C44="","",IF(A44<=B$16,0,E$23/(B$17-B$16))) -> 1916.8056 | E44: =IF(F44="","",E43-D44) -> 75145.139 | F44: =IF(D44="","",D44+C44) -> 3188.3276 | AA44: =IF(AA43<B$17,AA43+1,"") -> 15 | AB44: =IF(AA44="","",AB43+30) -> 46690 | AC44: =IF(AB44="","",IF(AA44<=B$16,AC43,AC43-AD44)) -> 83333.333 | AD44: =IF(AA44="","",IF(AA44<=B$16,0,B$15/(B$17-B$16))) -> 1851.8519 | AE44: =IF(AD44="","",AB44-AB43) -> 30 | AF44: =IF(AE44="","",AB44-AB$29) -> 450 | AG44: =IF(AF44="","",IF(AF44<365,AF44*AC$25*AD44,365*AD44*AC$25)) -> 27.712963 | AH44: =IF(AF44="","",IF(AF44<365,AF44*AC$26*AD44,365*AD44*AC$26)) -> 9.2601852 | AJ44: =IF(A44<=$B$17,F44,0) -> 3188.3276 | AK44: =IF(A44<=$B$17,E43*$D$15+D44,0) -> 3504.2816
A45: =IF(A44<B$17,A44+1,"") -> 22 | B45: =IF(A45="","",IF(A45<=B$16,"carência","amortização")) -> amortização | C45: =IF(B45="","",E44*$C$23) -> 1239.8948 | D45: =IF(C45="","",IF(A45<=B$16,0,E$23/(B$17-B$16))) -> 1916.8056 | E45: =IF(F45="","",E44-D45) -> 73228.333 | F45: =IF(D45="","",D45+C45) -> 3156.7003 | AA45: =IF(AA44<B$17,AA44+1,"") -> 16 | AB45: =IF(AA45="","",AB44+30) -> 46720 | AC45: =IF(AB45="","",IF(AA45<=B$16,AC44,AC44-AD45)) -> 81481.481 | AD45: =IF(AA45="","",IF(AA45<=B$16,0,B$15/(B$17-B$16))) -> 1851.8519 | AE45: =IF(AD45="","",AB45-AB44) -> 30 | AF45: =IF(AE45="","",AB45-AB$29) -> 480 | AG45: =IF(AF45="","",IF(AF45<365,AF45*AC$25*AD45,365*AD45*AC$25)) -> 27.712963 | AH45: =IF(AF45="","",IF(AF45<365,AF45*AC$26*AD45,365*AD45*AC$26)) -> 9.2601852 | AJ45: =IF(A45<=$B$17,F45,0) -> 3156.7003 | AK45: =IF(A45<=$B$17,E44*$D$15+D45,0) -> 3464.7954
A46: =IF(A45<B$17,A45+1,"") -> 23 | B46: =IF(A46="","",IF(A46<=B$16,"carência","amortização")) -> amortização | C46: =IF(B46="","",E45*$C$23) -> 1208.2675 | D46: =IF(C46="","",IF(A46<=B$16,0,E$23/(B$17-B$16))) -> 1916.8056 | E46: =IF(F46="","",E45-D46) -> 71311.528 | F46: =IF(D46="","",D46+C46) -> 3125.0731 | AA46: =IF(AA45<B$17,AA45+1,"") -> 17 | AB46: =IF(AA46="","",AB45+30) -> 46750 | AC46: =IF(AB46="","",IF(AA46<=B$16,AC45,AC45-AD46)) -> 79629.63 | AD46: =IF(AA46="","",IF(AA46<=B$16,0,B$15/(B$17-B$16))) -> 1851.8519 | AE46: =IF(AD46="","",AB46-AB45) -> 30 | AF46: =IF(AE46="","",AB46-AB$29) -> 510 | AG46: =IF(AF46="","",IF(AF46<365,AF46*AC$25*AD46,365*AD46*AC$25)) -> 27.712963 | AH46: =IF(AF46="","",IF(AF46<365,AF46*AC$26*AD46,365*AD46*AC$26)) -> 9.2601852 | AJ46: =IF(A46<=$B$17,F46,0) -> 3125.0731 | AK46: =IF(A46<=$B$17,E45*$D$15+D46,0) -> 3425.3092
A47: =IF(A46<B$17,A46+1,"") -> 24 | B47: =IF(A47="","",IF(A47<=B$16,"carência","amortização")) -> amortização | C47: =IF(B47="","",E46*$C$23) -> 1176.6402 | D47: =IF(C47="","",IF(A47<=B$16,0,E$23/(B$17-B$16))) -> 1916.8056 | E47: =IF(F47="","",E46-D47) -> 69394.722 | F47: =IF(D47="","",D47+C47) -> 3093.4458 | AA47: =IF(AA46<B$17,AA46+1,"") -> 18 | AB47: =IF(AA47="","",AB46+30) -> 46780 | AC47: =IF(AB47="","",IF(AA47<=B$16,AC46,AC46-AD47)) -> 77777.778 | AD47: =IF(AA47="","",IF(AA47<=B$16,0,B$15/(B$17-B$16))) -> 1851.8519 | AE47: =IF(AD47="","",AB47-AB46) -> 30 | AF47: =IF(AE47="","",AB47-AB$29) -> 540 | AG47: =IF(AF47="","",IF(AF47<365,AF47*AC$25*AD47,365*AD47*AC$25)) -> 27.712963 | AH47: =IF(AF47="","",IF(AF47<365,AF47*AC$26*AD47,365*AD47*AC$26)) -> 9.2601852 | AJ47: =IF(A47<=$B$17,F47,0) -> 3093.4458 | AK47: =IF(A47<=$B$17,E46*$D$15+D47,0) -> 3385.823
A48: =IF(A47<B$17,A47+1,"") -> 25 | B48: =IF(A48="","",IF(A48<=B$16,"carência","amortização")) -> amortização | C48: =IF(B48="","",E47*$C$23) -> 1145.0129 | D48: =IF(C48="","",IF(A48<=B$16,0,E$23/(B$17-B$16))) -> 1916.8056 | E48: =IF(F48="","",E47-D48) -> 67477.917 | F48: =IF(D48="","",D48+C48) -> 3061.8185 | AA48: =IF(AA47<B$17,AA47+1,"") -> 19 | AB48: =IF(AA48="","",AB47+30) -> 46810 | AC48: =IF(AB48="","",IF(AA48<=B$16,AC47,AC47-AD48)) -> 75925.926 | AD48: =IF(AA48="","",IF(AA48<=B$16,0,B$15/(B$17-B$16))) -> 1851.8519 | AE48: =IF(AD48="","",AB48-AB47) -> 30 | AF48: =IF(AE48="","",AB48-AB$29) -> 570 | AG48: =IF(AF48="","",IF(AF48<365,AF48*AC$25*AD48,365*AD48*AC$25)) -> 27.712963 | AH48: =IF(AF48="","",IF(AF48<365,AF48*AC$26*AD48,365*AD48*AC$26)) -> 9.2601852 | AJ48: =IF(A48<=$B$17,F48,0) -> 3061.8185 | AK48: =IF(A48<=$B$17,E47*$D$15+D48,0) -> 3346.3368
A49: =IF(A48<B$17,A48+1,"") -> 26 | B49: =IF(A49="","",IF(A49<=B$16,"carência","amortização")) -> amortização | C49: =IF(B49="","",E48*$C$23) -> 1113.3856 | D49: =IF(C49="","",IF(A49<=B$16,0,E$23/(B$17-B$16))) -> 1916.8056 | E49: =IF(F49="","",E48-D49) -> 65561.111 | F49: =IF(D49="","",D49+C49) -> 3030.1912 | AA49: =IF(AA48<B$17,AA48+1,"") -> 20 | AB49: =IF(AA49="","",AB48+30) -> 46840 | AC49: =IF(AB49="","",IF(AA49<=B$16,AC48,AC48-AD49)) -> 74074.074 | AD49: =IF(AA49="","",IF(AA49<=B$16,0,B$15/(B$17-B$16))) -> 1851.8519 | AE49: =IF(AD49="","",AB49-AB48) -> 30 | AF49: =IF(AE49="","",AB49-AB$29) -> 600 | AG49: =IF(AF49="","",IF(AF49<365,AF49*AC$25*AD49,365*AD49*AC$25)) -> 27.712963 | AH49: =IF(AF49="","",IF(AF49<365,AF49*AC$26*AD49,365*AD49*AC$26)) -> 9.2601852 | AJ49: =IF(A49<=$B$17,F49,0) -> 3030.1912 | AK49: =IF(A49<=$B$17,E48*$D$15+D49,0) -> 3306.8506
A50: =IF(A49<B$17,A49+1,"") -> 27 | B50: =IF(A50="","",IF(A50<=B$16,"carência","amortização")) -> amortização | C50: =IF(B50="","",E49*$C$23) -> 1081.7583 | D50: =IF(C50="","",IF(A50<=B$16,0,E$23/(B$17-B$16))) -> 1916.8056 | E50: =IF(F50="","",E49-D50) -> 63644.306 | F50: =IF(D50="","",D50+C50) -> 2998.5639 | AA50: =IF(AA49<B$17,AA49+1,"") -> 21 | AB50: =IF(AA50="","",AB49+30) -> 46870 | AC50: =IF(AB50="","",IF(AA50<=B$16,AC49,AC49-AD50)) -> 72222.222 | AD50: =IF(AA50="","",IF(AA50<=B$16,0,B$15/(B$17-B$16))) -> 1851.8519 | AE50: =IF(AD50="","",AB50-AB49) -> 30 | AF50: =IF(AE50="","",AB50-AB$29) -> 630 | AG50: =IF(AF50="","",IF(AF50<365,AF50*AC$25*AD50,365*AD50*AC$25)) -> 27.712963 | AH50: =IF(AF50="","",IF(AF50<365,AF50*AC$26*AD50,365*AD50*AC$26)) -> 9.2601852 | AJ50: =IF(A50<=$B$17,F50,0) -> 2998.5639 | AK50: =IF(A50<=$B$17,E49*$D$15+D50,0) -> 3267.3644
A51: =IF(A50<B$17,A50+1,"") -> 28 | B51: =IF(A51="","",IF(A51<=B$16,"carência","amortização")) -> amortização | C51: =IF(B51="","",E50*$C$23) -> 1050.131 | D51: =IF(C51="","",IF(A51<=B$16,0,E$23/(B$17-B$16))) -> 1916.8056 | E51: =IF(F51="","",E50-D51) -> 61727.5 | F51: =IF(D51="","",D51+C51) -> 2966.9366 | AA51: =IF(AA50<B$17,AA50+1,"") -> 22 | AB51: =IF(AA51="","",AB50+30) -> 46900 | AC51: =IF(AB51="","",IF(AA51<=B$16,AC50,AC50-AD51)) -> 70370.37 | AD51: =IF(AA51="","",IF(AA51<=B$16,0,B$15/(B$17-B$16))) -> 1851.8519 | AE51: =IF(AD51="","",AB51-AB50) -> 30 | AF51: =IF(AE51="","",AB51-AB$29) -> 660 | AG51: =IF(AF51="","",IF(AF51<365,AF51*AC$25*AD51,365*AD51*AC$25)) -> 27.712963 | AH51: =IF(AF51="","",IF(AF51<365,AF51*AC$26*AD51,365*AD51*AC$26)) -> 9.2601852 | AJ51: =IF(A51<=$B$17,F51,0) -> 2966.9366 | AK51: =IF(A51<=$B$17,E50*$D$15+D51,0) -> 3227.8782
A52: =IF(A51<B$17,A51+1,"") -> 29 | B52: =IF(A52="","",IF(A52<=B$16,"carência","amortização")) -> amortização | C52: =IF(B52="","",E51*$C$23) -> 1018.5037 | D52: =IF(C52="","",IF(A52<=B$16,0,E$23/(B$17-B$16))) -> 1916.8056 | E52: =IF(F52="","",E51-D52) -> 59810.694 | F52: =IF(D52="","",D52+C52) -> 2935.3093 | AA52: =IF(AA51<B$17,AA51+1,"") -> 23 | AB52: =IF(AA52="","",AB51+30) -> 46930 | AC52: =IF(AB52="","",IF(AA52<=B$16,AC51,AC51-AD52)) -> 68518.519 | AD52: =IF(AA52="","",IF(AA52<=B$16,0,B$15/(B$17-B$16))) -> 1851.8519 | AE52: =IF(AD52="","",AB52-AB51) -> 30 | AF52: =IF(AE52="","",AB52-AB$29) -> 690 | AG52: =IF(AF52="","",IF(AF52<365,AF52*AC$25*AD52,365*AD52*AC$25)) -> 27.712963 | AH52: =IF(AF52="","",IF(AF52<365,AF52*AC$26*AD52,365*AD52*AC$26)) -> 9.2601852 | AJ52: =IF(A52<=$B$17,F52,0) -> 2935.3093 | AK52: =IF(A52<=$B$17,E51*$D$15+D52,0) -> 3188.3921
A53: =IF(A52<B$17,A52+1,"") -> 30 | B53: =IF(A53="","",IF(A53<=B$16,"carência","amortização")) -> amortização | C53: =IF(B53="","",E52*$C$23) -> 986.87646 | D53: =IF(C53="","",IF(A53<=B$16,0,E$23/(B$17-B$16))) -> 1916.8056 | E53: =IF(F53="","",E52-D53) -> 57893.889 | F53: =IF(D53="","",D53+C53) -> 2903.682 | AA53: =IF(AA52<B$17,AA52+1,"") -> 24 | AB53: =IF(AA53="","",AB52+30) -> 46960 | AC53: =IF(AB53="","",IF(AA53<=B$16,AC52,AC52-AD53)) -> 66666.667 | AD53: =IF(AA53="","",IF(AA53<=B$16,0,B$15/(B$17-B$16))) -> 1851.8519 | AE53: =IF(AD53="","",AB53-AB52) -> 30 | AF53: =IF(AE53="","",AB53-AB$29) -> 720 | AG53: =IF(AF53="","",IF(AF53<365,AF53*AC$25*AD53,365*AD53*AC$25)) -> 27.712963 | AH53: =IF(AF53="","",IF(AF53<365,AF53*AC$26*AD53,365*AD53*AC$26)) -> 9.2601852 | AJ53: =IF(A53<=$B$17,F53,0) -> 2903.682 | AK53: =IF(A53<=$B$17,E52*$D$15+D53,0) -> 3148.9059
A54: =IF(A53<B$17,A53+1,"") -> 31 | B54: =IF(A54="","",IF(A54<=B$16,"carência","amortização")) -> amortização | C54: =IF(B54="","",E53*$C$23) -> 955.24917 | D54: =IF(C54="","",IF(A54<=B$16,0,E$23/(B$17-B$16))) -> 1916.8056 | E54: =IF(F54="","",E53-D54) -> 55977.083 | F54: =IF(D54="","",D54+C54) -> 2872.0547 | AA54: =IF(AA53<B$17,AA53+1,"") -> 25 | AB54: =IF(AA54="","",AB53+30) -> 46990 | AC54: =IF(AB54="","",IF(AA54<=B$16,AC53,AC53-AD54)) -> 64814.815 | AD54: =IF(AA54="","",IF(AA54<=B$16,0,B$15/(B$17-B$16))) -> 1851.8519 | AE54: =IF(AD54="","",AB54-AB53) -> 30 | AF54: =IF(AE54="","",AB54-AB$29) -> 750 | AG54: =IF(AF54="","",IF(AF54<365,AF54*AC$25*AD54,365*AD54*AC$25)) -> 27.712963 | AH54: =IF(AF54="","",IF(AF54<365,AF54*AC$26*AD54,365*AD54*AC$26)) -> 9.2601852 | AJ54: =IF(A54<=$B$17,F54,0) -> 2872.0547 | AK54: =IF(A54<=$B$17,E53*$D$15+D54,0) -> 3109.4197
... A77: =IF(A76<B$17,A76+1,"") -> 54 | B77: =IF(A77="","",IF(A77<=B$16,"carência","amortização")) -> amortização | C77: =IF(B77="","",E76*$C$23) -> 227.82146 | D77: =IF(C77="","",IF(A77<=B$16,0,E$23/(B$17-B$16))) -> 1916.8056 | E77: =IF(F77="","",E76-D77) -> 11890.556 | F77: =IF(D77="","",D77+C77) -> 2144.627 | AA77: =IF(AA76<B$17,AA76+1,"") -> 48 | AB77: =IF(AA77="","",AB76+30) -> 47680 | AC77: =IF(AB77="","",IF(AA77<=B$16,AC76,AC76-AD77)) -> 22222.222 | AD77: =IF(AA77="","",IF(AA77<=B$16,0,B$15/(B$17-B$16))) -> 1851.8519 | AE77: =IF(AD77="","",AB77-AB76) -> 30 | AF77: =IF(AE77="","",AB77-AB$29) -> 1440 | AG77: =IF(AF77="","",IF(AF77<365,AF77*AC$25*AD77,365*AD77*AC$25)) -> 27.712963 | AH77: =IF(AF77="","",IF(AF77<365,AF77*AC$26*AD77,365*AD77*AC$26)) -> 9.2601852 | AJ77: =IF(A77<=$B$17,F77,0) -> 2144.627 | AK77: =IF(A77<=$B$17,E76*$D$15+D77,0) -> 2201.2372
A78: =IF(A77<B$17,A77+1,"") -> 55 | B78: =IF(A78="","",IF(A78<=B$16,"carência","amortização")) -> amortização | C78: =IF(B78="","",E77*$C$23) -> 196.19417 | D78: =IF(C78="","",IF(A78<=B$16,0,E$23/(B$17-B$16))) -> 1916.8056 | E78: =IF(F78="","",E77-D78) -> 9973.75 | F78: =IF(D78="","",D78+C78) -> 2112.9997 | AA78: =IF(AA77<B$17,AA77+1,"") -> 49 | AC78: =IF(AB78="","",IF(AA78<=B$16,AC77,AC77-AD78)) | AD78: =IF(AA78="","",IF(AA78<=B$16,0,B$15/(B$17-B$16))) -> 1851.8519 | AF78: =IF(AE78="","",AB78-AB$29) | AG78: =IF(AF78="","",IF(AF78<365,AF78*AC$25*AD78,365*AD78*AC$25)) | AH78: =IF(AF78="","",IF(AF78<365,AF78*AC$26*AD78,365*AD78*AC$26)) | AJ78: =IF(A78<=$B$17,F78,0) -> 2112.9997 | AK78: =IF(A78<=$B$17,E77*$D$15+D78,0) -> 2161.751
A79: =IF(A78<B$17,A78+1,"") -> 56 | B79: =IF(A79="","",IF(A79<=B$16,"carência","amortização")) -> amortização | C79: =IF(B79="","",E78*$C$23) -> 164.56687 | D79: =IF(C79="","",IF(A79<=B$16,0,E$23/(B$17-B$16))) -> 1916.8056 | E79: =IF(F79="","",E78-D79) -> 8056.9444 | F79: =IF(D79="","",D79+C79) -> 2081.3724 | AA79: =IF(AA78<B$17,AA78+1,"") -> 50 | AC79: =IF(AB79="","",IF(AA79<=B$16,AC78,AC78-AD79)) | AD79: =IF(AA79="","",IF(AA79<=B$16,0,B$15/(B$17-B$16))) -> 1851.8519 | AF79: =IF(AE79="","",AB79-AB$29) | AG79: =IF(AF79="","",IF(AF79<365,AF79*AC$25*AD79,365*AD79*AC$25)) | AH79: =IF(AF79="","",IF(AF79<365,AF79*AC$26*AD79,365*AD79*AC$26)) | AJ79: =IF(A79<=$B$17,F79,0) -> 2081.3724 | AK79: =IF(A79<=$B$17,E78*$D$15+D79,0) -> 2122.2648
A80: =IF(A79<B$17,A79+1,"") -> 57 | B80: =IF(A80="","",IF(A80<=B$16,"carência","amortização")) -> amortização | C80: =IF(B80="","",E79*$C$23) -> 132.93958 | D80: =IF(C80="","",IF(A80<=B$16,0,E$23/(B$17-B$16))) -> 1916.8056 | E80: =IF(F80="","",E79-D80) -> 6140.1389 | F80: =IF(D80="","",D80+C80) -> 2049.7451 | AA80: =IF(AA79<B$17,AA79+1,"") -> 51 | AC80: =IF(AB80="","",IF(AA80<=B$16,AC79,AC79-AD80)) | AD80: =IF(AA80="","",IF(AA80<=B$16,0,B$15/(B$17-B$16))) -> 1851.8519 | AF80: =IF(AE80="","",AB80-AB$29) | AG80: =IF(AF80="","",IF(AF80<365,AF80*AC$25*AD80,365*AD80*AC$25)) | AH80: =IF(AF80="","",IF(AF80<365,AF80*AC$26*AD80,365*AD80*AC$26)) | AJ80: =IF(A80<=$B$17,F80,0) -> 2049.7451 | AK80: =IF(A80<=$B$17,E79*$D$15+D80,0) -> 2082.7786
A81: =IF(A80<B$17,A80+1,"") -> 58 | B81: =IF(A81="","",IF(A81<=B$16,"carência","amortização")) -> amortização | C81: =IF(B81="","",E80*$C$23) -> 101.31229 | D81: =IF(C81="","",IF(A81<=B$16,0,E$23/(B$17-B$16))) -> 1916.8056 | E81: =IF(F81="","",E80-D81) -> 4223.3333 | F81: =IF(D81="","",D81+C81) -> 2018.1178 | AA81: =IF(AA80<B$17,AA80+1,"") -> 52 | AC81: =IF(AB81="","",IF(AA81<=B$16,AC80,AC80-AD81)) | AD81: =IF(AA81="","",IF(AA81<=B$16,0,B$15/(B$17-B$16))) -> 1851.8519 | AF81: =IF(AE81="","",AB81-AB$29) | AG81: =IF(AF81="","",IF(AF81<365,AF81*AC$25*AD81,365*AD81*AC$25)) | AH81: =IF(AF81="","",IF(AF81<365,AF81*AC$26*AD81,365*AD81*AC$26)) | AJ81: =IF(A81<=$B$17,F81,0) -> 2018.1178 | AK81: =IF(A81<=$B$17,E80*$D$15+D81,0) -> 2043.2924
A82: =IF(A81<B$17,A81+1,"") -> 59 | B82: =IF(A82="","",IF(A82<=B$16,"carência","amortização")) -> amortização | C82: =IF(B82="","",E81*$C$23) -> 69.685 | D82: =IF(C82="","",IF(A82<=B$16,0,E$23/(B$17-B$16))) -> 1916.8056 | E82: =IF(F82="","",E81-D82) -> 2306.5278 | F82: =IF(D82="","",D82+C82) -> 1986.4906 | AA82: =IF(AA81<B$17,AA81+1,"") -> 53 | AC82: =IF(AB82="","",IF(AA82<=B$16,AC81,AC81-AD82)) | AD82: =IF(AA82="","",IF(AA82<=B$16,0,B$15/(B$17-B$16))) -> 1851.8519 | AF82: =IF(AE82="","",AB82-AB$29) | AG82: =IF(AF82="","",IF(AF82<365,AF82*AC$25*AD82,365*AD82*AC$25)) | AH82: =IF(AF82="","",IF(AF82<365,AF82*AC$26*AD82,365*AD82*AC$26)) | AJ82: =IF(A82<=$B$17,F82,0) -> 1986.4906 | AK82: =IF(A82<=$B$17,E81*$D$15+D82,0) -> 2003.8062
A83: =IF(A82<B$17,A82+1,"") -> 60 | B83: =IF(A83="","",IF(A83<=B$16,"carência","amortização")) -> amortização | C83: =IF(B83="","",E82*$C$23) -> 38.057708 | D83: =IF(C83="","",IF(A83<=B$16,0,E$23/(B$17-B$16))) -> 1916.8056 | E83: =IF(F83="","",E82-D83) -> 389.72222 | F83: =IF(D83="","",D83+C83) -> 1954.8633 | AA83: =IF(AA82<B$17,AA82+1,"") -> 54 | AC83: =IF(AB83="","",IF(AA83<=B$16,AC82,AC82-AD83)) | AD83: =IF(AA83="","",IF(AA83<=B$16,0,B$15/(B$17-B$16))) -> 1851.8519 | AF83: =IF(AE83="","",AB83-AB$29) | AG83: =IF(AF83="","",IF(AF83<365,AF83*AC$25*AD83,365*AD83*AC$25)) | AH83: =IF(AF83="","",IF(AF83<365,AF83*AC$26*AD83,365*AD83*AC$26)) | AJ83: =IF(A83<=$B$17,F83,0) -> 1954.8633 | AK83: =IF(A83<=$B$17,E82*$D$15+D83,0) -> 1964.32
A84: =IF(A83<B$17,A83+1,"") | B84: =IF(A84="","",IF(A84<=B$16,"carência","amortização")) | C84: =IF(B84="","",E83*$C$23) | D84: =IF(C84="","",IF(A84<=B$16,0,E$23/(B$17-B$16))) | E84: =IF(F84="","",E83-D84) | F84: =IF(D84="","",D84+C84) | AA84: =IF(AA83<B$17,AA83+1,"") -> 55 | AC84: =IF(AB84="","",IF(AA84<=B$16,AC83,AC83-AD84)) | AD84: =IF(AA84="","",IF(AA84<=B$16,0,B$15/(B$17-B$16))) -> 1851.8519 | AF84: =IF(AE84="","",AB84-AB$29) | AG84: =IF(AF84="","",IF(AF84<365,AF84*AC$25*AD84,365*AD84*AC$25)) | AH84: =IF(AF84="","",IF(AF84<365,AF84*AC$26*AD84,365*AD84*AC$26)) | AJ84: =IF(A84<=$B$17,F84,0) -> 0 | AK84: =IF(A84<=$B$17,E83*$D$15+D84,0) -> 0
A85: =IF(A84<B$17,A84+1,"") | B85: =IF(A85="","",IF(A85<=B$16,"carência","amortização")) | C85: =IF(B85="","",E84*$C$23) | D85: =IF(C85="","",IF(A85<=B$16,0,E$23/(B$17-B$16))) | E85: =IF(F85="","",E84-D85) | F85: =IF(D85="","",D85+C85) | AA85: =IF(AA84<B$17,AA84+1,"") -> 56 | AC85: =IF(AB85="","",IF(AA85<=B$16,AC84,AC84-AD85)) | AD85: =IF(AA85="","",IF(AA85<=B$16,0,B$15/(B$17-B$16))) -> 1851.8519 | AF85: =IF(AE85="","",AB85-AB$29) | AG85: =IF(AF85="","",IF(AF85<365,AF85*AC$25*AD85,365*AD85*AC$25)) | AH85: =IF(AF85="","",IF(AF85<365,AF85*AC$26*AD85,365*AD85*AC$26)) | AJ85: =IF(A85<=$B$17,F85,0) -> 0 | AK85: =IF(A85<=$B$17,E84*$D$15+D85,0) -> 0
A86: =IF(A85<B$17,A85+1,"") | B86: =IF(A86="","",IF(A86<=B$16,"carência","amortização")) | C86: =IF(B86="","",E85*$C$23) | D86: =IF(C86="","",IF(A86<=B$16,0,E$23/(B$17-B$16))) | E86: =IF(F86="","",E85-D86) | F86: =IF(D86="","",D86+C86) | AA86: =IF(AA85<B$17,AA85+1,"") -> 57 | AC86: =IF(AB86="","",IF(AA86<=B$16,AC85,AC85-AD86)) | AD86: =IF(AA86="","",IF(AA86<=B$16,0,B$15/(B$17-B$16))) -> 1851.8519 | AF86: =IF(AE86="","",AB86-AB$29) | AG86: =IF(AF86="","",IF(AF86<365,AF86*AC$25*AD86,365*AD86*AC$25)) | AH86: =IF(AF86="","",IF(AF86<365,AF86*AC$26*AD86,365*AD86*AC$26)) | AJ86: =IF(A86<=$B$17,F86,0) -> 0 | AK86: =IF(A86<=$B$17,E85*$D$15+D86,0) -> 0
AA87: =IF(AA86<B$17,AA86+1,"") -> 58 | AC87: =IF(AB87="","",IF(AA87<=B$16,AC86,AC86-AD87)) | AD87: =IF(AA87="","",IF(AA87<=B$16,0,B$15/(B$17-B$16))) -> 1851.8519 | AF87: =IF(AE87="","",AB87-AB$29) | AG87: =IF(AF87="","",IF(AF87<365,AF87*AC$25*AD87,365*AD87*AC$25)) | AH87: =IF(AF87="","",IF(AF87<365,AF87*AC$26*AD87,365*AD87*AC$26)) | AJ87: =IF(A87<=$B$17,F87,0) -> 0 | AK87: 0
AA88: =IF(AA87<B$17,AA87+1,"") -> 59 | AC88: =IF(AB88="","",IF(AA88<=B$16,AC87,AC87-AD88)) | AD88: =IF(AA88="","",IF(AA88<=B$16,0,B$15/(B$17-B$16))) -> 1851.8519 | AF88: =IF(AE88="","",AB88-AB$29) | AG88: =IF(AF88="","",IF(AF88<365,AF88*AC$25*AD88,365*AD88*AC$25)) | AH88: =IF(AF88="","",IF(AF88<365,AF88*AC$26*AD88,365*AD88*AC$26)) | AJ88: =IF(A88<=$B$17,F88,0) -> 0 | AK88: =IF(A88<=$B$17,E87*$D$15+D88,0) -> 0
AA89: =IF(AA88<B$17,AA88+1,"") -> 60 | AC89: =IF(AB89="","",IF(AA89<=B$16,AC88,AC88-AD89)) | AD89: =IF(AA89="","",IF(AA89<=B$16,0,B$15/(B$17-B$16))) -> 1851.8519 | AF89: =IF(AE89="","",AB89-AB$29) | AG89: =IF(AF89="","",IF(AF89<365,AF89*AC$25*AD89,365*AD89*AC$25)) | AH89: =IF(AF89="","",IF(AF89<365,AF89*AC$26*AD89,365*AD89*AC$26)) | AJ89: =IF(A89<=$B$17,F89,0) -> 0 | AK89: =IF(A89<=$B$17,E88*$D$15+D89,0) -> 0
AA90: =IF(AA89<B$17,AA89+1,"") | AC90: =IF(AB90="","",IF(AA90<=B$16,AC89,AC89-AD90)) | AD90: =IF(AA90="","",IF(AA90<=B$16,0,B$15/(B$17-B$16))) | AF90: =IF(AE90="","",AB90-AB$29) | AG90: =IF(AF90="","",IF(AF90<365,AF90*AC$25*AD90,365*AD90*AC$25)) | AH90: =IF(AF90="","",IF(AF90<365,AF90*AC$26*AD90,365*AD90*AC$26)) | AJ90: =IF(A90<=$B$17,F90,0) -> 0 | AK90: =IF(A90<=$B$17,E89*$D$15+D90,0) -> 0
AA91: =IF(AA90<B$17,AA90+1,"") | AC91: =IF(AB91="","",IF(AA91<=B$16,AC90,AC90-AD91)) | AD91: =IF(AA91="","",IF(AA91<=B$16,0,B$15/(B$17-B$16))) | AF91: =IF(AE91="","",AB91-AB$29) | AG91: =IF(AF91="","",IF(AF91<365,AF91*AC$25*AD91,365*AD91*AC$25)) | AH91: =IF(AF91="","",IF(AF91<365,AF91*AC$26*AD91,365*AD91*AC$26)) | AJ91: =IF(A91<=$B$17,F91,0) -> 0 | AK91: =IF(A91<=$B$17,E90*$D$15+D91,0) -> 0
AA92: =IF(AA91<B$17,AA91+1,"") | AC92: =IF(AB92="","",IF(AA92<=B$16,AC91,AC91-AD92)) | AD92: =IF(AA92="","",IF(AA92<=B$16,0,B$15/(B$17-B$16))) | AF92: =IF(AE92="","",AB92-AB$29) | AG92: =IF(AF92="","",IF(AF92<365,AF92*AC$25*AD92,365*AD92*AC$25)) | AH92: =IF(AF92="","",IF(AF92<365,AF92*AC$26*AD92,365*AD92*AC$26)) | AJ92: =IF(A92<=$B$17,F92,0) -> 0 | AK92: =IF(A92<=$B$17,E91*$D$15+D92,0) -> 0
AA93: =IF(AA92<B$17,AA92+1,"") | AC93: =IF(AB93="","",IF(AA93<=B$16,AC92,AC92-AD93)) | AD93: =IF(AA93="","",IF(AA93<=B$16,0,B$15/(B$17-B$16))) | AF93: =IF(AE93="","",AB93-AB$29) | AG93: =IF(AF93="","",IF(AF93<365,AF93*AC$25*AD93,365*AD93*AC$25)) | AH93: =IF(AF93="","",IF(AF93<365,AF93*AC$26*AD93,365*AD93*AC$26)) | AJ93: =IF(A93<=$B$17,F93,0) -> 0 | AK93: =IF(A93<=$B$17,E92*$D$15+D93,0) -> 0
AA94: =IF(AA93<B$17,AA93+1,"") | AC94: =IF(AB94="","",IF(AA94<=B$16,AC93,AC93-AD94)) | AD94: =IF(AA94="","",IF(AA94<=B$16,0,B$15/(B$17-B$16))) | AF94: =IF(AE94="","",AB94-AB$29) | AG94: =IF(AF94="","",IF(AF94<365,AF94*AC$25*AD94,365*AD94*AC$25)) | AH94: =IF(AF94="","",IF(AF94<365,AF94*AC$26*AD94,365*AD94*AC$26)) | AJ94: =IF(A94<=$B$17,F94,0) -> 0 | AK94: =IF(A94<=$B$17,E93*$D$15+D94,0) -> 0
AA95: =IF(AA94<B$17,AA94+1,"") | AC95: =IF(AB95="","",IF(AA95<=B$16,AC94,AC94-AD95)) | AD95: =IF(AA95="","",IF(AA95<=B$16,0,B$15/(B$17-B$16))) | AF95: =IF(AE95="","",AB95-AB$29) | AG95: =IF(AF95="","",IF(AF95<365,AF95*AC$25*AD95,365*AD95*AC$25)) | AH95: =IF(AF95="","",IF(AF95<365,AF95*AC$26*AD95,365*AD95*AC$26)) | AJ95: =IF(A95<=$B$17,F95,0) -> 0 | AK95: =IF(A95<=$B$17,E94*$D$15+D95,0) -> 0
AA96: =IF(AA95<B$17,AA95+1,"") | AC96: =IF(AB96="","",IF(AA96<=B$16,AC95,AC95-AD96)) | AD96: =IF(AA96="","",IF(AA96<=B$16,0,B$15/(B$17-B$16))) | AF96: =IF(AE96="","",AB96-AB$29) | AG96: =IF(AF96="","",IF(AF96<365,AF96*AC$25*AD96,365*AD96*AC$25)) | AH96: =IF(AF96="","",IF(AF96<365,AF96*AC$26*AD96,365*AD96*AC$26)) | AJ96: =IF(A96<=$B$17,F96,0) -> 0 | AK96: =IF(A96<=$B$17,E95*$D$15+D96,0) -> 0
AA97: =IF(AA96<B$17,AA96+1,"") | AC97: =IF(AB97="","",IF(AA97<=B$16,AC96,AC96-AD97)) | AD97: =IF(AA97="","",IF(AA97<=B$16,0,B$15/(B$17-B$16))) | AF97: =IF(AE97="","",AB97-AB$29) | AG97: =IF(AF97="","",IF(AF97<365,AF97*AC$25*AD97,365*AD97*AC$25)) | AH97: =IF(AF97="","",IF(AF97<365,AF97*AC$26*AD97,365*AD97*AC$26)) | AJ97: =IF(A97<=$B$17,F97,0) -> 0 | AK97: =IF(A97<=$B$17,E96*$D$15+D97,0) -> 0
AA98: =IF(AA97<B$17,AA97+1,"") | AC98: =IF(AB98="","",IF(AA98<=B$16,AC97,AC97-AD98)) | AD98: =IF(AA98="","",IF(AA98<=B$16,0,B$15/(B$17-B$16))) | AF98: =IF(AE98="","",AB98-AB$29) | AG98: =IF(AF98="","",IF(AF98<365,AF98*AC$25*AD98,365*AD98*AC$25)) | AH98: =IF(AF98="","",IF(AF98<365,AF98*AC$26*AD98,365*AD98*AC$26)) | AJ98: =IF(A98<=$B$17,F98,0) -> 0 | AK98: =IF(A98<=$B$17,E97*$D$15+D98,0) -> 0
AA99: =IF(AA98<B$17,AA98+1,"") | AC99: =IF(AB99="","",IF(AA99<=B$16,AC98,AC98-AD99)) | AD99: =IF(AA99="","",IF(AA99<=B$16,0,B$15/(B$17-B$16))) | AF99: =IF(AE99="","",AB99-AB$29) | AG99: =IF(AF99="","",IF(AF99<365,AF99*AC$25*AD99,365*AD99*AC$25)) | AH99: =IF(AF99="","",IF(AF99<365,AF99*AC$26*AD99,365*AD99*AC$26)) | AJ99: =IF(A99<=$B$17,F99,0) -> 0 | AK99: =IF(A99<=$B$17,E98*$D$15+D99,0) -> 0
... AA107: =IF(AA106<B$17,AA106+1,"") | AC107: =IF(AB107="","",IF(AA107<=B$16,AC106,AC106-AD107)) | AD107: =IF(AA107="","",IF(AA107<=B$16,0,B$15/(B$17-B$16))) | AF107: =IF(AE107="","",AB107-AB$29) | AG107: =IF(AF107="","",IF(AF107<365,AF107*AC$25*AD107,365*AD107*AC$25)) | AH107: =IF(AF107="","",IF(AF107<365,AF107*AC$26*AD107,365*AD107*AC$26)) | AJ107: =IF(A107<=$B$17,F107,0) -> 0 | AK107: =IF(A107<=$B$17,E106*$D$15+D107,0) -> 0
AA108: =IF(AA107<B$17,AA107+1,"") | AC108: =IF(AB108="","",IF(AA108<=B$16,AC107,AC107-AD108)) | AD108: =IF(AA108="","",IF(AA108<=B$16,0,B$15/(B$17-B$16))) | AF108: =IF(AE108="","",AB108-AB$29) | AG108: =IF(AF108="","",IF(AF108<365,AF108*AC$25*AD108,365*AD108*AC$25)) | AH108: =IF(AF108="","",IF(AF108<365,AF108*AC$26*AD108,365*AD108*AC$26))
AA109: =IF(AA108<B$17,AA108+1,"") | AC109: =IF(AB109="","",IF(AA109<=B$16,AC108,AC108-AD109)) | AD109: =IF(AA109="","",IF(AA109<=B$16,0,B$15/(B$17-B$16))) | AF109: =IF(AE109="","",AB109-AB$29) | AG109: =IF(AF109="","",IF(AF109<365,AF109*AC$25*AD109,365*AD109*AC$25)) | AH109: =IF(AF109="","",IF(AF109<365,AF109*AC$26*AD109,365*AD109*AC$26))
AA110: =IF(AA109<B$17,AA109+1,"") | AC110: =IF(AB110="","",IF(AA110<=B$16,AC109,AC109-AD110)) | AD110: =IF(AA110="","",IF(AA110<=B$16,0,B$15/(B$17-B$16))) | AF110: =IF(AE110="","",AB110-AB$29) | AG110: =IF(AF110="","",IF(AF110<365,AF110*AC$25*AD110,365*AD110*AC$25)) | AH110: =IF(AF110="","",IF(AF110<365,AF110*AC$26*AD110,365*AD110*AC$26))
AA111: =IF(AA110<B$17,AA110+1,"") | AC111: =IF(AB111="","",IF(AA111<=B$16,AC110,AC110-AD111)) | AD111: =IF(AA111="","",IF(AA111<=B$16,0,B$15/(B$17-B$16))) | AF111: =IF(AE111="","",AB111-AB$29) | AG111: =IF(AF111="","",IF(AF111<365,AF111*AC$25*AD111,365*AD111*AC$25)) | AH111: =IF(AF111="","",IF(AF111<365,AF111*AC$26*AD111,365*AD111*AC$26))
AA112: =IF(AA111<B$17,AA111+1,"") | AC112: =IF(AB112="","",IF(AA112<=B$16,AC111,AC111-AD112)) | AD112: =IF(AA112="","",IF(AA112<=B$16,0,B$15/(B$17-B$16))) | AF112: =IF(AE112="","",AB112-AB$29) | AG112: =IF(AF112="","",IF(AF112<365,AF112*AC$25*AD112,365*AD112*AC$25)) | AH112: =IF(AF112="","",IF(AF112<365,AF112*AC$26*AD112,365*AD112*AC$26))
AA113: =IF(AA112<B$17,AA112+1,"") | AC113: =IF(AB113="","",IF(AA113<=B$16,AC112,AC112-AD113)) | AD113: =IF(AA113="","",IF(AA113<=B$16,0,B$15/(B$17-B$16))) | AF113: =IF(AE113="","",AB113-AB$29) | AG113: =IF(AF113="","",IF(AF113<365,AF113*AC$25*AD113,365*AD113*AC$25)) | AH113: =IF(AF113="","",IF(AF113<365,AF113*AC$26*AD113,365*AD113*AC$26))
AA114: =IF(AA113<B$17,AA113+1,"") | AC114: =IF(AB114="","",IF(AA114<=B$16,AC113,AC113-AD114)) | AD114: =IF(AA114="","",IF(AA114<=B$16,0,B$15/(B$17-B$16))) | AF114: =IF(AE114="","",AB114-AB$29) | AG114: =IF(AF114="","",IF(AF114<365,AF114*AC$25*AD114,365*AD114*AC$25)) | AH114: =IF(AF114="","",IF(AF114<365,AF114*AC$26*AD114,365*AD114*AC$26))
AA115: =IF(AA114<B$17,AA114+1,"") | AC115: =IF(AB115="","",IF(AA115<=B$16,AC114,AC114-AD115)) | AD115: =IF(AA115="","",IF(AA115<=B$16,0,B$15/(B$17-B$16))) | AF115: =IF(AE115="","",AB115-AB$29) | AG115: =IF(AF115="","",IF(AF115<365,AF115*AC$25*AD115,365*AD115*AC$25)) | AH115: =IF(AF115="","",IF(AF115<365,AF115*AC$26*AD115,365*AD115*AC$26))
AA116: =IF(AA115<B$17,AA115+1,"") | AC116: =IF(AB116="","",IF(AA116<=B$16,AC115,AC115-AD116)) | AD116: =IF(AA116="","",IF(AA116<=B$16,0,B$15/(B$17-B$16))) | AF116: =IF(AE116="","",AB116-AB$29) | AG116: =IF(AF116="","",IF(AF116<365,AF116*AC$25*AD116,365*AD116*AC$25)) | AH116: =IF(AF116="","",IF(AF116<365,AF116*AC$26*AD116,365*AD116*AC$26))
AA117: =IF(AA116<B$17,AA116+1,"") | AC117: =IF(AB117="","",IF(AA117<=B$16,AC116,AC116-AD117)) | AD117: =IF(AA117="","",IF(AA117<=B$16,0,B$15/(B$17-B$16))) | AF117: =IF(AE117="","",AB117-AB$29) | AG117: =IF(AF117="","",IF(AF117<365,AF117*AC$25*AD117,365*AD117*AC$25)) | AH117: =IF(AF117="","",IF(AF117<365,AF117*AC$26*AD117,365*AD117*AC$26))
AA118: =IF(AA117<B$17,AA117+1,"") | AC118: =IF(AB118="","",IF(AA118<=B$16,AC117,AC117-AD118)) | AD118: =IF(AA118="","",IF(AA118<=B$16,0,B$15/(B$17-B$16))) | AF118: =IF(AE118="","",AB118-AB$29) | AG118: =IF(AF118="","",IF(AF118<365,AF118*AC$25*AD118,365*AD118*AC$25)) | AH118: =IF(AF118="","",IF(AF118<365,AF118*AC$26*AD118,365*AD118*AC$26))
AA119: =IF(AA118<B$17,AA118+1,"") | AC119: =IF(AB119="","",IF(AA119<=B$16,AC118,AC118-AD119)) | AD119: =IF(AA119="","",IF(AA119<=B$16,0,B$15/(B$17-B$16))) | AF119: =IF(AE119="","",AB119-AB$29) | AG119: =IF(AF119="","",IF(AF119<365,AF119*AC$25*AD119,365*AD119*AC$25)) | AH119: =IF(AF119="","",IF(AF119<365,AF119*AC$26*AD119,365*AD119*AC$26))
... AA229: =IF(AA228<B$17,AA228+1,"") | AC229: =IF(AB229="","",IF(AA229<=B$16,AC228,AC228-AD229)) | AD229: =IF(AA229="","",IF(AA229<=B$16,0,B$15/(B$17-B$16))) | AF229: =IF(AE229="","",AB229-AB$29) | AG229: =IF(AF229="","",IF(AF229<365,AF229*AC$25*AD229,365*AD229*AC$25)) | AH229: =IF(AF229="","",IF(AF229<365,AF229*AC$26*AD229,365*AD229*AC$26))
AA230: =IF(AA229<B$17,AA229+1,"") | AC230: =IF(AB230="","",IF(AA230<=B$16,AC229,AC229-AD230)) | AD230: =IF(AA230="","",IF(AA230<=B$16,0,B$15/(B$17-B$16))) | AG230: =IF(AF230="","",IF(AF230<365,AF230*AC$25*AD230,365*AD230*AC$25)) | AH230: =IF(AF230="","",IF(AF230<365,AF230*AC$26*AD230,365*AD230*AC$26))
AA231: =IF(AA230<B$17,AA230+1,"") | AC231: =IF(AB231="","",IF(AA231<=B$16,AC230,AC230-AD231)) | AD231: =IF(AA231="","",IF(AA231<=B$16,0,B$15/(B$17-B$16))) | AG231: =IF(AF231="","",IF(AF231<365,AF231*AC$25*AD231,365*AD231*AC$25)) | AH231: =IF(AF231="","",IF(AF231<365,AF231*AC$26*AD231,365*AD231*AC$26))
AA232: =IF(AA231<B$17,AA231+1,"") | AC232: =IF(AB232="","",IF(AA232<=B$16,AC231,AC231-AD232)) | AD232: =IF(AA232="","",IF(AA232<=B$16,0,B$15/(B$17-B$16))) | AG232: =IF(AF232="","",IF(AF232<365,AF232*AC$25*AD232,365*AD232*AC$25)) | AH232: =IF(AF232="","",IF(AF232<365,AF232*AC$26*AD232,365*AD232*AC$26))
AA233: =IF(AA232<B$17,AA232+1,"") | AC233: =IF(AB233="","",IF(AA233<=B$16,AC232,AC232-AD233)) | AD233: =IF(AA233="","",IF(AA233<=B$16,0,B$15/(B$17-B$16))) | AG233: =IF(AF233="","",IF(AF233<365,AF233*AC$25*AD233,365*AD233*AC$25)) | AH233: =IF(AF233="","",IF(AF233<365,AF233*AC$26*AD233,365*AD233*AC$26))
AA234: =IF(AA233<B$17,AA233+1,"") | AC234: =IF(AB234="","",IF(AA234<=B$16,AC233,AC233-AD234)) | AD234: =IF(AA234="","",IF(AA234<=B$16,0,B$15/(B$17-B$16))) | AG234: =IF(AF234="","",IF(AF234<365,AF234*AC$25*AD234,365*AD234*AC$25)) | AH234: =IF(AF234="","",IF(AF234<365,AF234*AC$26*AD234,365*AD234*AC$26))
AA235: =IF(AA234<B$17,AA234+1,"") | AC235: =IF(AB235="","",E229) | AD235: =IF(AA235="","",IF(AA235<=B$16,0,B$15/(B$17-B$16))) | AG235: =IF(AF235="","",IF(AF235<365,AF235*AC$25*AD235,365*AD235*AC$25)) | AH235: =IF(AF235="","",IF(AF235<365,AF235*AC$26*AD235,365*AD235*AC$26))
AA236: =IF(AA235<B$17,AA235+1,"") | AC236: =IF(AB236="","",E230) | AD236: =IF(AA236="","",IF(AA236<=B$16,0,B$15/(B$17-B$16))) | AG236: =IF(AF236="","",IF(AF236<365,AF236*AC$25*AD236,365*AD236*AC$25)) | AH236: =IF(AF236="","",IF(AF236<365,AF236*AC$26*AD236,365*AD236*AC$26))
AA237: =IF(AA236<B$17,AA236+1,"") | AC237: =IF(AB237="","",E231) | AD237: =IF(AA237="","",IF(AA237<=B$16,0,B$15/(B$17-B$16))) | AG237: =IF(AF237="","",IF(AF237<365,AF237*AC$25*AD237,365*AD237*AC$25)) | AH237: =IF(AF237="","",IF(AF237<365,AF237*AC$26*AD237,365*AD237*AC$26))
AA238: =IF(AA237<B$17,AA237+1,"") | AC238: =IF(AB238="","",E232) | AD238: =IF(AA238="","",IF(AA238<=B$16,0,B$15/(B$17-B$16))) | AG238: =IF(AF238="","",IF(AF238<365,AF238*AC$25*AD238,365*AD238*AC$25)) | AH238: =IF(AF238="","",IF(AF238<365,AF238*AC$26*AD238,365*AD238*AC$26))
...

Sheet Linhas Giro Puro
A1: AGÊNCIA DE FOMENTO DE GOIÁS S/A | AA1: 2 | AB1: 2
A2: IMPORTANTE: Os valores simulados não possuem valor comercial. Diversos fatores interferem no cáculo final como taxas e serviços contratados. O financiamento e condições são sujeitas à aprovação final da análise de crédito; Valores calculados com base na taxa líquida (incluso o bônus por adimplência) quando não há atraso nos pagamentos.
A3: LINHA DE CAPITAL DE GIRO | AA3: TAC | AB3: IOF
A4: LINHA | J4: 6 | K4: 1 | N4: LINHA | O4: TAXA (a.m.) | P4: TAXA BONUS | Q4: CG1 (a.m.) | R4: CG2 (a.m.) | S4: PRAZO (meses) | T4: CARÊNCIA (até meses) | U4: LIMITE | V4: GARANTIA | AA4: Descontado | AB4: Descontado
N5: GoiásFomento Giro | O5: 2.27 | P5: 0 | Q5: 1.81 | R5: =Q5 -> 1.81 | S5: 24 | T5: 3 | U5: 300000 | V5: CG1 | AA5: Financiado | AB5: Financiado
C6: =IF(AND(J4=1,K4=1),Q5,IF(AND(J4=1,K4=2),R5,IF(AND(J4=1,K4=3),P5,"-"))) -> - | N6: GoiásFomento Giro VIP | O6: 2.19 | P6: 0 | Q6: 1.75 | R6: =Q6 -> 1.75 | S6: 36 | T6: 3 | U6: 300000 | V6: CG2
C7: =IF(AND(J4=2,K4=1),Q6,IF(AND(J4=2,K4=2),R6,IF(AND(J4=2,K4=3),P6,"-"))) -> - | N7: GoiásFomento Giro - IMCF | O7: 2.17 | P7: 0 | Q7: 1.74 | R7: =Q7 -> 1.74 | S7: 24 | T7: 3 | U7: 300000 | V7: NÃO
C8: =IF(AND(J4=3,K4=1),Q7,IF(AND(J4=3,K4=2),R7,IF(AND(J4=3,K4=3),P7,"-"))) -> - | N8: GoiásFomento Giro - VIP IMCF | O8: 2.16 | P8: 0 | Q8: 1.72 | R8: =Q8 -> 1.72 | S8: 36 | T8: 3 | U8: 300000
C9: =IF(AND(J4=4,K4=1),Q8,IF(AND(J4=4,K4=2),R8,IF(AND(J4=4,K4=3),P8,"-"))) -> - | N9: GoiásFomento Giro Consorciado | O9: =O8 -> 2.16 | P9: 0 | Q9: =Q8 -> 1.72 | R9: =R8 -> 1.72 | S9: 36 | T9: 3 | U9: 300000
C10: =IF(AND(J4=5,K4=1),Q9,IF(AND(J4=5,K4=2),R9,IF(AND(J4=5,K4=3),P9,"-"))) -> - | N10: GoiásFomento (GIRO)Tecnologia/PQF-IEL/Turismo/FarmaDrogas/ Contabilistas / Mulher Empreendedora | O10: 2.21 | P10: 0 | Q10: 1.77 | R10: =Q10 -> 1.77 | S10: 36 | T10: 3 | U10: 300000
C11: =IF(AND(J4=6,K4=1),Q10,IF(AND(J4=6,K4=2),R10,IF(AND(J4=6,K4=3),P10,"-"))) -> 1.77 | N11: GoiásFomento Microcrédito Produtivo | O11: 2.06 | P11: 1.65 | Q11: =P11 -> 1.65 | R11: =Q11 -> 1.65 | S11: 36 | T11: 3 | U11: 21000
C12: =IF(AND(J4=7,K4=1),Q11,IF(AND(J4=7,K4=2),R11,IF(AND(J4=7,K4=3),P11,"-"))) -> -
A14: INFORMAÇÕES
A15: VALOR FINANCIADO | B15: 60000 | C15: TAXA NOMINAL | E15: =AJ22 -> -0.0010961245 | F15: =IF(AA1=1,IF(B15<=3000,50,IF(B15<=21000,IF(B15*0.03<=420,B15*1.015*0.03,420),IF(B15<=100000,B15*0.02,2000+B15*0.005))),IF(B15*1.015<=3000,50,IF(B15*1.015<=21000,IF(B15*1.015*0.03<=420,B15*1.015*0.03,420),IF(B15<=100000,B15*1.015*0.02,2000+B15*1.015*0.005)))) -> 1218 | I15: =IF(B15<=3000,50,IF(B15<=21000,IF(B15*0.03<=420,B15*0.03,420),IF(B15<=100000,B15*0.02,2000+B15*0.005))) -> 1200 | J15: 4
A16: CARÊNCIA | B16: 6 | C16: TAXA COM BÔNUS | D16: 0.005 | F16: =IF(AB1=1,AF24,AF24*1.03) -> 931.635 | I16: =IF(B15*0.03<=420,B15*0.03,420) -> 420 | J16: 1
A17: PRAZO TOTAL | B17: 60 | C17: DATA DA PROPOSTA | D17: =TODAY() -> 46240 | F17: =IF(J16=1,IF(J21=TRUE,M24,0),IF(J21=TRUE,M24*1.001,0)) -> 0 | J17: Descontado | L17: FALSE | AL17: Receitas Totais | AM17: =SUM(AM18:AM19) -> #VALUE! | AN17: Despesas | AO17: PDD AD | AP17: Resultado | AQ17: =AQ18-AQ19 -> #VALUE! | AR17: =AQ17/D22 -> #VALUE!
A18: OPÇÕES DE GARANTIA | J18: Financiado | AL18: TAC | AM18: =F15 -> 1218 | AN18: Provisão Adicional | AO18: =D22*0.014 -> #VALUE! | AP18: Receitas | AQ18: =AM17 -> #VALUE!
A19: RENDA PARA AVAL | B19: =IF(LARGE(F23:F241,1)*3<2424,2424,LARGE(F23:F241,1)*3) -> 4385.002 | C19: ALIENAÇÃO DE IMÓVEL | D19: =IF(J21=TRUE,(B15-F19)*1.5/0.7,B15*1.5/0.7) -> 128571.43 | E19: 0.8 | F19: =IF(J21=TRUE,E19*B15,0) -> 0 | J19: FINANCIADO | L19: TRUE | AL19: JUROS | AM19: =C22 -> #VALUE! | AN19: Avaliação | AO19: 300 | AP19: Despesas | AQ19: =AO20 -> #VALUE!
A20: SIMULAÇÃO DO VALOR DAS PARCELAS | J20: Financiado | AO20: =SUM(AO18:AO19) -> #VALUE! | AW20: 16681310
A21: PARCELA | B21: AMORTIZAÇÃO | C21: JUROS | D21: VALOR AMORTIZAÇÃO | E21: SALDO DEVEDOR | F21: PARCELA COM BÔNUS | J21: FALSE | K21: TCA | L21: FAMPE | M21: =B15*E19*0.001*B17 -> 2880 | AB21: IOF - ACIMA ATÉ 365 DIAS | AJ21: TIR (PARCELA C/ BÔNUS) | AK21: TIR (PARCELA S/ BÔNUS) | AW21: 8540394.5 | AX21: =AW21*12 -> 1.0248473e+08
A22: TOTAL | C22: =SUM(C23:C242) -> #VALUE! | D22: =SUM(D23:D242) -> #VALUE! | F22: =SUM(F23:F242) -> 58299.81 | K22: ECG | L22: FGI | M22: ='Fator K - FGI'!I30 -> 3133.595 | AJ22: =IRR(AJ23:AJ107) -> -0.0010961245 | AK22: =IRR(AK23:AK107) -> #VALUE! | AW22: 86881821 | BL22: =F22-B15 -> -1700.1896
A23: 0 | C23: =D16 -> 0.005 | E23: =IF(AND(AA1=1,AB1=1,J16=1),B15,IF(AND(AA1=1,AB1=1,J16=2),B15+F17,IF(AND(AA1=1,AB1=2,J16=1),B15+F16,IF(AND(AA1=1,AB1=2,J16=3),B15+F16,IF(AND(AA1=2,AB1=1,J16=1),B15+F15,IF(AND(AA1=2,AB1=1,J16=2),B15+F15+F17,IF(AND(AA1=2,AB1=2,J16=2),B15+F17+F16+F15,IF(AND(AA1=2,AB1=2,J16=3),B15+F15+F16,IF(AND(AA1=2,AB1=2,J16=1),B15+F15+F16,IF(AND(AA1=1,AB1=2,J16=2),B15+F16+F17, IF(AND(AA1=1,AB1=1,J16=3),B15))))))))))) -> 62149.635 | K23: TCA | L23: FUNDEQ | M23: =B15*E19*0.001*B17 -> 2880 | AJ23: =-B15 -> -60000 | AK23: =AJ23 -> -60000 | AN23: 5881 | AO23: =AN23/AN24 -> 0.04216496
A24: =IF(A23<B$17,A23+1,"") -> 1 | B24: =IF(A24="","",IF(A24<=B$16,"carência","amortização")) -> carência | C24: =IF(B24="","",E23*$C$23) -> 310.74818 | D24: =IF(C24="","",IF(A24<=B$16,0,$E$23/(B$17-B$16))) -> 0 | E24: =IF(F24="","",E23-D24) -> 62149.635 | F24: =IF(D24="","",D24+C24) -> 310.74818 | I24: =B15+F15+F16+F17 -> 62149.635 | L24: 1 | M24: =IF(L24=1,M21,IF(L24=2,M22,M23)) -> 2880 | AB24: IOF | AC24: 0.0038 | AE24: =AC27*AC24 -> 228 | AF24: =IF(L19=FALSE,0,IF(AND(AH25=TRUE,B15<=30000),AE24+AE26,AE24+AE25)) -> 904.5 | AJ24: =IF(A24<=$B$17,F24,0) -> 310.74818 | AK24: =IF(A24<=$B$17,E23*$D$15+D24,0) -> 0 | AN24: 139476 | AW24: =SUM(E23:E34) -> 728531.83
A25: =IF(A24<B$17,A24+1,"") -> 2 | B25: =IF(A25="","",IF(A25<=B$16,"carência","amortização")) -> carência | C25: =IF(B25="","",E24*$C$23) -> 310.74818 | D25: =IF(C25="","",IF(A25<=B$16,0,$E$23/(B$17-B$16))) -> 0 | E25: =IF(F25="","",E24-D25) -> 62149.635 | F25: =IF(D25="","",D25+C25) -> 310.74818 | AB25: ALÍQUOTA | AC25: 4.1e-05 | AE25: =SUM(AG30:AG83) -> 676.5 | AH25: TRUE | AJ25: =IF(A25<=$B$17,F25,0) -> 310.74818 | AK25: =IF(A25<=$B$17,E24*$D$15+D25,0) -> 0
A26: =IF(A25<B$17,A25+1,"") -> 3 | B26: =IF(A26="","",IF(A26<=B$16,"carência","amortização")) -> carência | C26: =IF(B26="","",E25*$C$23) -> 310.74818 | D26: =IF(C26="","",IF(A26<=B$16,0,$E$23/(B$17-B$16))) -> 0 | E26: =IF(F26="","",E25-D26) -> 62149.635 | F26: =IF(D26="","",D26+C26) -> 310.74818 | AB26: ALÍQUOTA SIMPLES | AC26: =0.00137/100 -> 1.37e-05 | AE26: =SUM(AH30:AH308) -> 226.05 | AJ26: =IF(A26<=$B$17,F26,0) -> 310.74818 | AK26: =IF(A26<=$B$17,E25*$D$15+D26,0) -> 0 | AW26: =SUM(C24:C35) -> 3642.6592
A27: =IF(A26<B$17,A26+1,"") -> 4 | B27: =IF(A27="","",IF(A27<=B$16,"carência","amortização")) -> carência | C27: =IF(B27="","",E26*$C$23) -> 310.74818 | D27: =IF(C27="","",IF(A27<=B$16,0,$E$23/(B$17-B$16))) -> 0 | E27: =IF(F27="","",E26-D27) -> 62149.635 | F27: =IF(D27="","",D27+C27) -> 310.74818 | AB27: LIBERAÇÃO | AC27: =B15 -> 60000 | AJ27: =IF(A27<=$B$17,F27,0) -> 310.74818 | AK27: =IF(A27<=$B$17,E26*$D$15+D27,0) -> 0
A28: =IF(A27<B$17,A27+1,"") -> 5 | B28: =IF(A28="","",IF(A28<=B$16,"carência","amortização")) -> carência | C28: =IF(B28="","",E27*$C$23) -> 310.74818 | D28: =IF(C28="","",IF(A28<=B$16,0,$E$23/(B$17-B$16))) -> 0 | E28: =IF(F28="","",E27-D28) -> 62149.635 | F28: =IF(D28="","",D28+C28) -> 310.74818 | AG28: IOF NORMAL | AH28: IOF SIMPLES | AJ28: =IF(A28<=$B$17,F28,0) -> 310.74818 | AK28: =IF(A28<=$B$17,E27*$D$15+D28,0) -> 0
A29: =IF(A28<B$17,A28+1,"") -> 6 | B29: =IF(A29="","",IF(A29<=B$16,"carência","amortização")) -> carência | C29: =IF(B29="","",E28*$C$23) -> 310.74818 | D29: =IF(C29="","",IF(A29<=B$16,0,$E$23/(B$17-B$16))) -> 0 | E29: =IF(F29="","",E28-D29) -> 62149.635 | F29: =IF(D29="","",D29+C29) -> 310.74818 | AA29: 0 | AB29: =D17 -> 46240 | AC29: =IF(AB29="","",AC27) -> 60000 | AD29: =IF(AA29="","",IF(AA29<=B$16,0,B$15/(B$17-B$16))) -> 0 | AJ29: =IF(A29<=$B$17,F29,0) -> 310.74818 | AK29: =IF(A29<=$B$17,E28*$D$15+D29,0) -> 0 | AW29: =E23 -> 62149.635
A30: =IF(A29<B$17,A29+1,"") -> 7 | B30: =IF(A30="","",IF(A30<=B$16,"carência","amortização")) -> amortização | C30: =IF(B30="","",E29*$C$23) -> 310.74818 | D30: =IF(C30="","",IF(A30<=B$16,0,$E$23/(B$17-B$16))) -> 1150.9192 | E30: =IF(F30="","",E29-D30) -> 60998.716 | F30: =IF(D30="","",D30+C30) -> 1461.6673 | AA30: =IF(AA29<B$17,AA29+1,"") -> 1 | AB30: =IF(AA30="","",AB29+30) -> 46270 | AC30: =IF(AB30="","",IF(AA30<=B$16,AC29,AC29-AD30)) -> 60000 | AD30: =IF(AA30="","",IF(AA30<=B$16,0,B$15/(B$17-B$16))) -> 0 | AE30: =IF(AD30="","",AB30-AB29) -> 30 | AF30: =IF(AE30="","",AB30-AB$29) -> 30 | AG30: =IF(AF30="","",IF(AF30<365,AF30*AC$25*AD30,365*AD30*AC$25)) -> 0 | AH30: =IF(AF30="","",IF(AF30<365,AF30*AC$26*AD30,365*AD30*AC$26)) -> 0 | AJ30: =IF(A30<=$B$17,F30,0) -> 1461.6673 | AK30: =IF(A30<=$B$17,E29*$D$15+D30,0) -> 1150.9192 | AW30: =AW29*0.016 -> 994.39416
A31: =IF(A30<B$17,A30+1,"") -> 8 | B31: =IF(A31="","",IF(A31<=B$16,"carência","amortização")) -> amortização | C31: =IF(B31="","",E30*$C$23) -> 304.99358 | D31: =IF(C31="","",IF(A31<=B$16,0,$E$23/(B$17-B$16))) -> 1150.9192 | E31: =IF(F31="","",E30-D31) -> 59847.797 | F31: =IF(D31="","",D31+C31) -> 1455.9127 | AA31: =IF(AA30<B$17,AA30+1,"") -> 2 | AB31: =IF(AA31="","",AB30+30) -> 46300 | AC31: =IF(AB31="","",IF(AA31<=B$16,AC30,AC30-AD31)) -> 60000 | AD31: =IF(AA31="","",IF(AA31<=B$16,0,B$15/(B$17-B$16))) -> 0 | AE31: =IF(AD31="","",AB31-AB30) -> 30 | AF31: =IF(AE31="","",AB31-AB$29) -> 60 | AG31: =IF(AF31="","",IF(AF31<365,AF31*AC$25*AD31,365*AD31*AC$25)) -> 0 | AH31: =IF(AF31="","",IF(AF31<365,AF31*AC$26*AD31,365*AD31*AC$26)) -> 0 | AJ31: =IF(A31<=$B$17,F31,0) -> 1455.9127 | AK31: =IF(A31<=$B$17,E30*$D$15+D31,0) -> 1150.9192
A32: =IF(A31<B$17,A31+1,"") -> 9 | B32: =IF(A32="","",IF(A32<=B$16,"carência","amortização")) -> amortização | C32: =IF(B32="","",E31*$C$23) -> 299.23898 | D32: =IF(C32="","",IF(A32<=B$16,0,$E$23/(B$17-B$16))) -> 1150.9192 | E32: =IF(F32="","",E31-D32) -> 58696.878 | F32: =IF(D32="","",D32+C32) -> 1450.1582 | AA32: =IF(AA31<B$17,AA31+1,"") -> 3 | AB32: =IF(AA32="","",AB31+30) -> 46330 | AC32: =IF(AB32="","",IF(AA32<=B$16,AC31,AC31-AD32)) -> 60000 | AD32: =IF(AA32="","",IF(AA32<=B$16,0,B$15/(B$17-B$16))) -> 0 | AE32: =IF(AD32="","",AB32-AB31) -> 30 | AF32: =IF(AE32="","",AB32-AB$29) -> 90 | AG32: =IF(AF32="","",IF(AF32<365,AF32*AC$25*AD32,365*AD32*AC$25)) -> 0 | AH32: =IF(AF32="","",IF(AF32<365,AF32*AC$26*AD32,365*AD32*AC$26)) -> 0 | AJ32: =IF(A32<=$B$17,F32,0) -> 1450.1582 | AK32: =IF(A32<=$B$17,E31*$D$15+D32,0) -> 1150.9192 | AW32: GFG VIP | AX32: Fungetur Giro
A33: =IF(A32<B$17,A32+1,"") -> 10 | B33: =IF(A33="","",IF(A33<=B$16,"carência","amortização")) -> amortização | C33: =IF(B33="","",E32*$C$23) -> 293.48439 | D33: =IF(C33="","",IF(A33<=B$16,0,$E$23/(B$17-B$16))) -> 1150.9192 | E33: =IF(F33="","",E32-D33) -> 57545.958 | F33: =IF(D33="","",D33+C33) -> 1444.4036 | AA33: =IF(AA32<B$17,AA32+1,"") -> 4 | AB33: =IF(AA33="","",AB32+30) -> 46360 | AC33: =IF(AB33="","",IF(AA33<=B$16,AC32,AC32-AD33)) -> 60000 | AD33: =IF(AA33="","",IF(AA33<=B$16,0,B$15/(B$17-B$16))) -> 0 | AE33: =IF(AD33="","",AB33-AB32) -> 30 | AF33: =IF(AE33="","",AB33-AB$29) -> 120 | AG33: =IF(AF33="","",IF(AF33<365,AF33*AC$25*AD33,365*AD33*AC$25)) -> 0 | AH33: =IF(AF33="","",IF(AF33<365,AF33*AC$26*AD33,365*AD33*AC$26)) -> 0 | AJ33: =IF(A33<=$B$17,F33,0) -> 1444.4036 | AK33: =IF(A33<=$B$17,E32*$D$15+D33,0) -> 1150.9192 | AV33: Valor Financiado | AW33: 100000 | AX33: 100000
A34: =IF(A33<B$17,A33+1,"") -> 11 | B34: =IF(A34="","",IF(A34<=B$16,"carência","amortização")) -> amortização | C34: =IF(B34="","",E33*$C$23) -> 287.72979 | D34: =IF(C34="","",IF(A34<=B$16,0,$E$23/(B$17-B$16))) -> 1150.9192 | E34: =IF(F34="","",E33-D34) -> 56395.039 | F34: =IF(D34="","",D34+C34) -> 1438.649 | AA34: =IF(AA33<B$17,AA33+1,"") -> 5 | AB34: =IF(AA34="","",AB33+30) -> 46390 | AC34: =IF(AB34="","",IF(AA34<=B$16,AC33,AC33-AD34)) -> 60000 | AD34: =IF(AA34="","",IF(AA34<=B$16,0,B$15/(B$17-B$16))) -> 0 | AE34: =IF(AD34="","",AB34-AB33) -> 30 | AF34: =IF(AE34="","",AB34-AB$29) -> 150 | AG34: =IF(AF34="","",IF(AF34<365,AF34*AC$25*AD34,365*AD34*AC$25)) -> 0 | AH34: =IF(AF34="","",IF(AF34<365,AF34*AC$26*AD34,365*AD34*AC$26)) -> 0 | AJ34: =IF(A34<=$B$17,F34,0) -> 1438.649 | AK34: =IF(A34<=$B$17,E33*$D$15+D34,0) -> 1150.9192 | AV34: Prazo | AW34: 36 | AX34: 48
A35: =IF(A34<B$17,A34+1,"") -> 12 | B35: =IF(A35="","",IF(A35<=B$16,"carência","amortização")) -> amortização | C35: =IF(B35="","",E34*$C$23) -> 281.9752 | D35: =IF(C35="","",IF(A35<=B$16,0,$E$23/(B$17-B$16))) -> 1150.9192 | E35: =IF(F35="","",E34-D35) -> 55244.12 | F35: =IF(D35="","",D35+C35) -> 1432.8944 | AA35: =IF(AA34<B$17,AA34+1,"") -> 6 | AB35: =IF(AA35="","",AB34+30) -> 46420 | AC35: =IF(AB35="","",IF(AA35<=B$16,AC34,AC34-AD35)) -> 60000 | AD35: =IF(AA35="","",IF(AA35<=B$16,0,B$15/(B$17-B$16))) -> 0 | AE35: =IF(AD35="","",AB35-AB34) -> 30 | AF35: =IF(AE35="","",AB35-AB$29) -> 180 | AG35: =IF(AF35="","",IF(AF35<365,AF35*AC$25*AD35,365*AD35*AC$25)) -> 0 | AH35: =IF(AF35="","",IF(AF35<365,AF35*AC$26*AD35,365*AD35*AC$26)) -> 0 | AJ35: =IF(A35<=$B$17,F35,0) -> 1432.8944 | AK35: =IF(A35<=$B$17,E34*$D$15+D35,0) -> 1150.9192 | AV35: Carência | AW35: 6 | AX35: 6
A36: =IF(A35<B$17,A35+1,"") -> 13 | B36: =IF(A36="","",IF(A36<=B$16,"carência","amortização")) -> amortização | C36: =IF(B36="","",E35*$C$23) -> 276.2206 | D36: =IF(C36="","",IF(A36<=B$16,0,$E$23/(B$17-B$16))) -> 1150.9192 | E36: =IF(F36="","",E35-D36) -> 54093.201 | F36: =IF(D36="","",D36+C36) -> 1427.1398 | AA36: =IF(AA35<B$17,AA35+1,"") -> 7 | AB36: =IF(AA36="","",AB35+30) -> 46450 | AC36: =IF(AB36="","",IF(AA36<=B$16,AC35,AC35-AD36)) -> 58888.889 | AD36: =IF(AA36="","",IF(AA36<=B$16,0,B$15/(B$17-B$16))) -> 1111.1111 | AE36: =IF(AD36="","",AB36-AB35) -> 30 | AF36: =IF(AE36="","",AB36-AB$29) -> 210 | AG36: =IF(AF36="","",IF(AF36<365,AF36*AC$25*AD36,365*AD36*AC$25)) -> 9.5666667 | AH36: =IF(AF36="","",IF(AF36<365,AF36*AC$26*AD36,365*AD36*AC$26)) -> 3.1966667 | AJ36: =IF(A36<=$B$17,F36,0) -> 1427.1398 | AK36: =IF(A36<=$B$17,E35*$D$15+D36,0) -> 1150.9192 | AV36: Juros | AW36: 0.0155 | AX36: =(1.05)^(1/12)-1 -> 0.0040741238
A37: =IF(A36<B$17,A36+1,"") -> 14 | B37: =IF(A37="","",IF(A37<=B$16,"carência","amortização")) -> amortização | C37: =IF(B37="","",E36*$C$23) -> 270.466 | D37: =IF(C37="","",IF(A37<=B$16,0,$E$23/(B$17-B$16))) -> 1150.9192 | E37: =IF(F37="","",E36-D37) -> 52942.282 | F37: =IF(D37="","",D37+C37) -> 1421.3852 | AA37: =IF(AA36<B$17,AA36+1,"") -> 8 | AB37: =IF(AA37="","",AB36+30) -> 46480 | AC37: =IF(AB37="","",IF(AA37<=B$16,AC36,AC36-AD37)) -> 57777.778 | AD37: =IF(AA37="","",IF(AA37<=B$16,0,B$15/(B$17-B$16))) -> 1111.1111 | AE37: =IF(AD37="","",AB37-AB36) -> 30 | AF37: =IF(AE37="","",AB37-AB$29) -> 240 | AG37: =IF(AF37="","",IF(AF37<365,AF37*AC$25*AD37,365*AD37*AC$25)) -> 10.933333 | AH37: =IF(AF37="","",IF(AF37<365,AF37*AC$26*AD37,365*AD37*AC$26)) -> 3.6533333 | AJ37: =IF(A37<=$B$17,F37,0) -> 1421.3852 | AK37: =IF(A37<=$B$17,E36*$D$15+D37,0) -> 1150.9192 | AV37: Receita Juros | AW37: 18519.324 | AX37: 5090.838 | AY37: =AW37/AX37-1 -> 2.6377752
A38: =IF(A37<B$17,A37+1,"") -> 15 | B38: =IF(A38="","",IF(A38<=B$16,"carência","amortização")) -> amortização | C38: =IF(B38="","",E37*$C$23) -> 264.71141 | D38: =IF(C38="","",IF(A38<=B$16,0,$E$23/(B$17-B$16))) -> 1150.9192 | E38: =IF(F38="","",E37-D38) -> 51791.363 | F38: =IF(D38="","",D38+C38) -> 1415.6306 | AA38: =IF(AA37<B$17,AA37+1,"") -> 9 | AB38: =IF(AA38="","",AB37+30) -> 46510 | AC38: =IF(AB38="","",IF(AA38<=B$16,AC37,AC37-AD38)) -> 56666.667 | AD38: =IF(AA38="","",IF(AA38<=B$16,0,B$15/(B$17-B$16))) -> 1111.1111 | AE38: =IF(AD38="","",AB38-AB37) -> 30 | AF38: =IF(AE38="","",AB38-AB$29) -> 270 | AG38: =IF(AF38="","",IF(AF38<365,AF38*AC$25*AD38,365*AD38*AC$25)) -> 12.3 | AH38: =IF(AF38="","",IF(AF38<365,AF38*AC$26*AD38,365*AD38*AC$26)) -> 4.11 | AJ38: =IF(A38<=$B$17,F38,0) -> 1415.6306 | AK38: =IF(A38<=$B$17,E37*$D$15+D38,0) -> 1150.9192 | AV38: Rentabilidade (12 meses) | AW38: =AW37/AW33 -> 0.18519324 | AX38: =AX37/AX33 -> 0.05090838 | AY38: =AW38/AX38-1 -> 2.6377752
A39: =IF(A38<B$17,A38+1,"") -> 16 | B39: =IF(A39="","",IF(A39<=B$16,"carência","amortização")) -> amortização | C39: =IF(B39="","",E38*$C$23) -> 258.95681 | D39: =IF(C39="","",IF(A39<=B$16,0,$E$23/(B$17-B$16))) -> 1150.9192 | E39: =IF(F39="","",E38-D39) -> 50640.443 | F39: =IF(D39="","",D39+C39) -> 1409.876 | AA39: =IF(AA38<B$17,AA38+1,"") -> 10 | AB39: =IF(AA39="","",AB38+30) -> 46540 | AC39: =IF(AB39="","",IF(AA39<=B$16,AC38,AC38-AD39)) -> 55555.556 | AD39: =IF(AA39="","",IF(AA39<=B$16,0,B$15/(B$17-B$16))) -> 1111.1111 | AE39: =IF(AD39="","",AB39-AB38) -> 30 | AF39: =IF(AE39="","",AB39-AB$29) -> 300 | AG39: =IF(AF39="","",IF(AF39<365,AF39*AC$25*AD39,365*AD39*AC$25)) -> 13.666667 | AH39: =IF(AF39="","",IF(AF39<365,AF39*AC$26*AD39,365*AD39*AC$26)) -> 4.5666667 | AJ39: =IF(A39<=$B$17,F39,0) -> 1409.876 | AK39: =IF(A39<=$B$17,E38*$D$15+D39,0) -> 1150.9192
A40: =IF(A39<B$17,A39+1,"") -> 17 | B40: =IF(A40="","",IF(A40<=B$16,"carência","amortização")) -> amortização | C40: =IF(B40="","",E39*$C$23) -> 253.20222 | D40: =IF(C40="","",IF(A40<=B$16,0,$E$23/(B$17-B$16))) -> 1150.9192 | E40: =IF(F40="","",E39-D40) -> 49489.524 | F40: =IF(D40="","",D40+C40) -> 1404.1214 | AA40: =IF(AA39<B$17,AA39+1,"") -> 11 | AB40: =IF(AA40="","",AB39+30) -> 46570 | AC40: =IF(AB40="","",IF(AA40<=B$16,AC39,AC39-AD40)) -> 54444.444 | AD40: =IF(AA40="","",IF(AA40<=B$16,0,B$15/(B$17-B$16))) -> 1111.1111 | AE40: =IF(AD40="","",AB40-AB39) -> 30 | AF40: =IF(AE40="","",AB40-AB$29) -> 330 | AG40: =IF(AF40="","",IF(AF40<365,AF40*AC$25*AD40,365*AD40*AC$25)) -> 15.033333 | AH40: =IF(AF40="","",IF(AF40<365,AF40*AC$26*AD40,365*AD40*AC$26)) -> 5.0233333 | AJ40: =IF(A40<=$B$17,F40,0) -> 1404.1214 | AK40: =IF(A40<=$B$17,E39*$D$15+D40,0) -> 1150.9192
A41: =IF(A40<B$17,A40+1,"") -> 18 | B41: =IF(A41="","",IF(A41<=B$16,"carência","amortização")) -> amortização | C41: =IF(B41="","",E40*$C$23) -> 247.44762 | D41: =IF(C41="","",IF(A41<=B$16,0,$E$23/(B$17-B$16))) -> 1150.9192 | E41: =IF(F41="","",E40-D41) -> 48338.605 | F41: =IF(D41="","",D41+C41) -> 1398.3668 | AA41: =IF(AA40<B$17,AA40+1,"") -> 12 | AB41: =IF(AA41="","",AB40+30) -> 46600 | AC41: =IF(AB41="","",IF(AA41<=B$16,AC40,AC40-AD41)) -> 53333.333 | AD41: =IF(AA41="","",IF(AA41<=B$16,0,B$15/(B$17-B$16))) -> 1111.1111 | AE41: =IF(AD41="","",AB41-AB40) -> 30 | AF41: =IF(AE41="","",AB41-AB$29) -> 360 | AG41: =IF(AF41="","",IF(AF41<365,AF41*AC$25*AD41,365*AD41*AC$25)) -> 16.4 | AH41: =IF(AF41="","",IF(AF41<365,AF41*AC$26*AD41,365*AD41*AC$26)) -> 5.48 | AJ41: =IF(A41<=$B$17,F41,0) -> 1398.3668 | AK41: =IF(A41<=$B$17,E40*$D$15+D41,0) -> 1150.9192
A42: =IF(A41<B$17,A41+1,"") -> 19 | B42: =IF(A42="","",IF(A42<=B$16,"carência","amortização")) -> amortização | C42: =IF(B42="","",E41*$C$23) -> 241.69303 | D42: =IF(C42="","",IF(A42<=B$16,0,$E$23/(B$17-B$16))) -> 1150.9192 | E42: =IF(F42="","",E41-D42) -> 47187.686 | F42: =IF(D42="","",D42+C42) -> 1392.6122 | AA42: =IF(AA41<B$17,AA41+1,"") -> 13 | AB42: =IF(AA42="","",AB41+30) -> 46630 | AC42: =IF(AA42="","",IF(AB42<=B$16,AC27,AC41-AD42)) -> 52222.222 | AD42: =IF(AA42="","",IF(AA42<=B$16,0,B$15/(B$17-B$16))) -> 1111.1111 | AE42: =IF(AD42="","",AB42-AB41) -> 30 | AF42: =IF(AE42="","",AB42-AB$29) -> 390 | AG42: =IF(AF42="","",IF(AF42<365,AF42*AC$25*AD42,365*AD42*AC$25)) -> 16.627778 | AH42: =IF(AF42="","",IF(AF42<365,AF42*AC$26*AD42,365*AD42*AC$26)) -> 5.5561111 | AJ42: =IF(A42<=$B$17,F42,0) -> 1392.6122 | AK42: =IF(A42<=$B$17,E41*$D$15+D42,0) -> 1150.9192
A43: =IF(A42<B$17,A42+1,"") -> 20 | B43: =IF(A43="","",IF(A43<=B$16,"carência","amortização")) -> amortização | C43: =IF(B43="","",E42*$C$23) -> 235.93843 | D43: =IF(C43="","",IF(A43<=B$16,0,$E$23/(B$17-B$16))) -> 1150.9192 | E43: =IF(F43="","",E42-D43) -> 46036.767 | F43: =IF(D43="","",D43+C43) -> 1386.8576 | AA43: =IF(AA42<B$17,AA42+1,"") -> 14 | AB43: =IF(AA43="","",AB42+30) -> 46660 | AC43: =IF(AB43="","",IF(AA43<=B$16,AC42,AC42-AD43)) -> 51111.111 | AD43: =IF(AA43="","",IF(AA43<=B$16,0,B$15/(B$17-B$16))) -> 1111.1111 | AE43: =IF(AD43="","",AB43-AB42) -> 30 | AF43: =IF(AE43="","",AB43-AB$29) -> 420 | AG43: =IF(AF43="","",IF(AF43<365,AF43*AC$25*AD43,365*AD43*AC$25)) -> 16.627778 | AH43: =IF(AF43="","",IF(AF43<365,AF43*AC$26*AD43,365*AD43*AC$26)) -> 5.5561111 | AJ43: =IF(A43<=$B$17,F43,0) -> 1386.8576 | AK43: =IF(A43<=$B$17,E42*$D$15+D43,0) -> 1150.9192
A44: =IF(A43<B$17,A43+1,"") -> 21 | B44: =IF(A44="","",IF(A44<=B$16,"carência","amortização")) -> amortização | C44: =IF(B44="","",E43*$C$23) -> 230.18383 | D44: =IF(C44="","",IF(A44<=B$16,0,$E$23/(B$17-B$16))) -> 1150.9192 | E44: =IF(F44="","",E43-D44) -> 44885.848 | F44: =IF(D44="","",D44+C44) -> 1381.103 | AA44: =IF(AA43<B$17,AA43+1,"") -> 15 | AB44: =IF(AA44="","",AB43+30) -> 46690 | AC44: =IF(AB44="","",IF(AA44<=B$16,AC43,AC43-AD44)) -> 50000 | AD44: =IF(AA44="","",IF(AA44<=B$16,0,B$15/(B$17-B$16))) -> 1111.1111 | AE44: =IF(AD44="","",AB44-AB43) -> 30 | AF44: =IF(AE44="","",AB44-AB$29) -> 450 | AG44: =IF(AF44="","",IF(AF44<365,AF44*AC$25*AD44,365*AD44*AC$25)) -> 16.627778 | AH44: =IF(AF44="","",IF(AF44<365,AF44*AC$26*AD44,365*AD44*AC$26)) -> 5.5561111 | AJ44: =IF(A44<=$B$17,F44,0) -> 1381.103 | AK44: =IF(A44<=$B$17,E43*$D$15+D44,0) -> 1150.9192
A45: =IF(A44<B$17,A44+1,"") -> 22 | B45: =IF(A45="","",IF(A45<=B$16,"carência","amortização")) -> amortização | C45: =IF(B45="","",E44*$C$23) -> 224.42924 | D45: =IF(C45="","",IF(A45<=B$16,0,$E$23/(B$17-B$16))) -> 1150.9192 | E45: =IF(F45="","",E44-D45) -> 43734.928 | F45: =IF(D45="","",D45+C45) -> 1375.3484 | AA45: =IF(AA44<B$17,AA44+1,"") -> 16 | AB45: =IF(AA45="","",AB44+30) -> 46720 | AC45: =IF(AB45="","",IF(AA45<=B$16,AC44,AC44-AD45)) -> 48888.889 | AD45: =IF(AA45="","",IF(AA45<=B$16,0,B$15/(B$17-B$16))) -> 1111.1111 | AE45: =IF(AD45="","",AB45-AB44) -> 30 | AF45: =IF(AE45="","",AB45-AB$29) -> 480 | AG45: =IF(AF45="","",IF(AF45<365,AF45*AC$25*AD45,365*AD45*AC$25)) -> 16.627778 | AH45: =IF(AF45="","",IF(AF45<365,AF45*AC$26*AD45,365*AD45*AC$26)) -> 5.5561111 | AJ45: =IF(A45<=$B$17,F45,0) -> 1375.3484 | AK45: =IF(A45<=$B$17,E44*$D$15+D45,0) -> 1150.9192
A46: =IF(A45<B$17,A45+1,"") -> 23 | B46: =IF(A46="","",IF(A46<=B$16,"carência","amortização")) -> amortização | C46: =IF(B46="","",E45*$C$23) -> 218.67464 | D46: =IF(C46="","",IF(A46<=B$16,0,$E$23/(B$17-B$16))) -> 1150.9192 | E46: =IF(F46="","",E45-D46) -> 42584.009 | F46: =IF(D46="","",D46+C46) -> 1369.5938 | AA46: =IF(AA45<B$17,AA45+1,"") -> 17 | AB46: =IF(AA46="","",AB45+30) -> 46750 | AC46: =IF(AB46="","",IF(AA46<=B$16,AC45,AC45-AD46)) -> 47777.778 | AD46: =IF(AA46="","",IF(AA46<=B$16,0,B$15/(B$17-B$16))) -> 1111.1111 | AE46: =IF(AD46="","",AB46-AB45) -> 30 | AF46: =IF(AE46="","",AB46-AB$29) -> 510 | AG46: =IF(AF46="","",IF(AF46<365,AF46*AC$25*AD46,365*AD46*AC$25)) -> 16.627778 | AH46: =IF(AF46="","",IF(AF46<365,AF46*AC$26*AD46,365*AD46*AC$26)) -> 5.5561111 | AJ46: =IF(A46<=$B$17,F46,0) -> 1369.5938 | AK46: =IF(A46<=$B$17,E45*$D$15+D46,0) -> 1150.9192
A47: =IF(A46<B$17,A46+1,"") -> 24 | B47: =IF(A47="","",IF(A47<=B$16,"carência","amortização")) -> amortização | C47: =IF(B47="","",E46*$C$23) -> 212.92005 | D47: =IF(C47="","",IF(A47<=B$16,0,$E$23/(B$17-B$16))) -> 1150.9192 | E47: =IF(F47="","",E46-D47) -> 41433.09 | F47: =IF(D47="","",D47+C47) -> 1363.8392 | AA47: =IF(AA46<B$17,AA46+1,"") -> 18 | AB47: =IF(AA47="","",AB46+30) -> 46780 | AC47: =IF(AB47="","",IF(AA47<=B$16,AC46,AC46-AD47)) -> 46666.667 | AD47: =IF(AA47="","",IF(AA47<=B$16,0,B$15/(B$17-B$16))) -> 1111.1111 | AE47: =IF(AD47="","",AB47-AB46) -> 30 | AF47: =IF(AE47="","",AB47-AB$29) -> 540 | AG47: =IF(AF47="","",IF(AF47<365,AF47*AC$25*AD47,365*AD47*AC$25)) -> 16.627778 | AH47: =IF(AF47="","",IF(AF47<365,AF47*AC$26*AD47,365*AD47*AC$26)) -> 5.5561111 | AJ47: =IF(A47<=$B$17,F47,0) -> 1363.8392 | AK47: =IF(A47<=$B$17,E46*$D$15+D47,0) -> 1150.9192
A48: =IF(A47<B$17,A47+1,"") -> 25 | B48: =IF(A48="","",IF(A48<=B$16,"carência","amortização")) -> amortização | C48: =IF(B48="","",E47*$C$23) -> 207.16545 | D48: =IF(C48="","",IF(A48<=B$16,0,$E$23/(B$17-B$16))) -> 1150.9192 | E48: =IF(F48="","",E47-D48) -> 40282.171 | F48: =IF(D48="","",D48+C48) -> 1358.0846 | AA48: =IF(AA47<B$17,AA47+1,"") -> 19 | AB48: =IF(AA48="","",AB47+30) -> 46810 | AC48: =IF(AB48="","",IF(AA48<=B$16,AC47,AC47-AD48)) -> 45555.556 | AD48: =IF(AA48="","",IF(AA48<=B$16,0,B$15/(B$17-B$16))) -> 1111.1111 | AE48: =IF(AD48="","",AB48-AB47) -> 30 | AF48: =IF(AE48="","",AB48-AB$29) -> 570 | AG48: =IF(AF48="","",IF(AF48<365,AF48*AC$25*AD48,365*AD48*AC$25)) -> 16.627778 | AH48: =IF(AF48="","",IF(AF48<365,AF48*AC$26*AD48,365*AD48*AC$26)) -> 5.5561111 | AJ48: =IF(A48<=$B$17,F48,0) -> 1358.0846 | AK48: =IF(A48<=$B$17,E47*$D$15+D48,0) -> 1150.9192
A49: =IF(A48<B$17,A48+1,"") -> 26 | B49: =IF(A49="","",IF(A49<=B$16,"carência","amortização")) -> amortização | C49: =IF(B49="","",E48*$C$23) -> 201.41085 | D49: =IF(C49="","",IF(A49<=B$16,0,$E$23/(B$17-B$16))) -> 1150.9192 | E49: =IF(F49="","",E48-D49) -> 39131.252 | F49: =IF(D49="","",D49+C49) -> 1352.33 | AA49: =IF(AA48<B$17,AA48+1,"") -> 20 | AB49: =IF(AA49="","",AB48+30) -> 46840 | AC49: =IF(AB49="","",IF(AA49<=B$16,AC48,AC48-AD49)) -> 44444.444 | AD49: =IF(AA49="","",IF(AA49<=B$16,0,B$15/(B$17-B$16))) -> 1111.1111 | AE49: =IF(AD49="","",AB49-AB48) -> 30 | AF49: =IF(AE49="","",AB49-AB$29) -> 600 | AG49: =IF(AF49="","",IF(AF49<365,AF49*AC$25*AD49,365*AD49*AC$25)) -> 16.627778 | AH49: =IF(AF49="","",IF(AF49<365,AF49*AC$26*AD49,365*AD49*AC$26)) -> 5.5561111 | AJ49: =IF(A49<=$B$17,F49,0) -> 1352.33 | AK49: =IF(A49<=$B$17,E48*$D$15+D49,0) -> 1150.9192
A50: =IF(A49<B$17,A49+1,"") -> 27 | B50: =IF(A50="","",IF(A50<=B$16,"carência","amortização")) -> amortização | C50: =IF(B50="","",E49*$C$23) -> 195.65626 | D50: =IF(C50="","",IF(A50<=B$16,0,$E$23/(B$17-B$16))) -> 1150.9192 | E50: =IF(F50="","",E49-D50) -> 37980.333 | F50: =IF(D50="","",D50+C50) -> 1346.5754 | AA50: =IF(AA49<B$17,AA49+1,"") -> 21 | AB50: =IF(AA50="","",AB49+30) -> 46870 | AC50: =IF(AB50="","",IF(AA50<=B$16,AC49,AC49-AD50)) -> 43333.333 | AD50: =IF(AA50="","",IF(AA50<=B$16,0,B$15/(B$17-B$16))) -> 1111.1111 | AE50: =IF(AD50="","",AB50-AB49) -> 30 | AF50: =IF(AE50="","",AB50-AB$29) -> 630 | AG50: =IF(AF50="","",IF(AF50<365,AF50*AC$25*AD50,365*AD50*AC$25)) -> 16.627778 | AH50: =IF(AF50="","",IF(AF50<365,AF50*AC$26*AD50,365*AD50*AC$26)) -> 5.5561111 | AJ50: =IF(A50<=$B$17,F50,0) -> 1346.5754 | AK50: =IF(A50<=$B$17,E49*$D$15+D50,0) -> 1150.9192
A51: =IF(A50<B$17,A50+1,"") -> 28 | B51: =IF(A51="","",IF(A51<=B$16,"carência","amortização")) -> amortização | C51: =IF(B51="","",E50*$C$23) -> 189.90166 | D51: =IF(C51="","",IF(A51<=B$16,0,$E$23/(B$17-B$16))) -> 1150.9192 | E51: =IF(F51="","",E50-D51) -> 36829.413 | F51: =IF(D51="","",D51+C51) -> 1340.8208 | AA51: =IF(AA50<B$17,AA50+1,"") -> 22 | AB51: =IF(AA51="","",AB50+30) -> 46900 | AC51: =IF(AB51="","",IF(AA51<=B$16,AC50,AC50-AD51)) -> 42222.222 | AD51: =IF(AA51="","",IF(AA51<=B$16,0,B$15/(B$17-B$16))) -> 1111.1111 | AE51: =IF(AD51="","",AB51-AB50) -> 30 | AF51: =IF(AE51="","",AB51-AB$29) -> 660 | AG51: =IF(AF51="","",IF(AF51<365,AF51*AC$25*AD51,365*AD51*AC$25)) -> 16.627778 | AH51: =IF(AF51="","",IF(AF51<365,AF51*AC$26*AD51,365*AD51*AC$26)) -> 5.5561111 | AJ51: =IF(A51<=$B$17,F51,0) -> 1340.8208 | AK51: =IF(A51<=$B$17,E50*$D$15+D51,0) -> 1150.9192
A52: =IF(A51<B$17,A51+1,"") -> 29 | B52: =IF(A52="","",IF(A52<=B$16,"carência","amortização")) -> amortização | C52: =IF(B52="","",E51*$C$23) -> 184.14707 | D52: =IF(C52="","",IF(A52<=B$16,0,$E$23/(B$17-B$16))) -> 1150.9192 | E52: =IF(F52="","",E51-D52) -> 35678.494 | F52: =IF(D52="","",D52+C52) -> 1335.0662 | AA52: =IF(AA51<B$17,AA51+1,"") -> 23 | AB52: =IF(AA52="","",AB51+30) -> 46930 | AC52: =IF(AB52="","",IF(AA52<=B$16,AC51,AC51-AD52)) -> 41111.111 | AD52: =IF(AA52="","",IF(AA52<=B$16,0,B$15/(B$17-B$16))) -> 1111.1111 | AE52: =IF(AD52="","",AB52-AB51) -> 30 | AF52: =IF(AE52="","",AB52-AB$29) -> 690 | AG52: =IF(AF52="","",IF(AF52<365,AF52*AC$25*AD52,365*AD52*AC$25)) -> 16.627778 | AH52: =IF(AF52="","",IF(AF52<365,AF52*AC$26*AD52,365*AD52*AC$26)) -> 5.5561111 | AJ52: =IF(A52<=$B$17,F52,0) -> 1335.0662 | AK52: =IF(A52<=$B$17,E51*$D$15+D52,0) -> 1150.9192
A53: =IF(A52<B$17,A52+1,"") -> 30 | B53: =IF(A53="","",IF(A53<=B$16,"carência","amortização")) -> amortização | C53: =IF(B53="","",E52*$C$23) -> 178.39247 | D53: =IF(C53="","",IF(A53<=B$16,0,$E$23/(B$17-B$16))) -> 1150.9192 | E53: =IF(F53="","",E52-D53) -> 34527.575 | F53: =IF(D53="","",D53+C53) -> 1329.3116 | AA53: =IF(AA52<B$17,AA52+1,"") -> 24 | AB53: =IF(AA53="","",AB52+30) -> 46960 | AC53: =IF(AB53="","",IF(AA53<=B$16,AC52,AC52-AD53)) -> 40000 | AD53: =IF(AA53="","",IF(AA53<=B$16,0,B$15/(B$17-B$16))) -> 1111.1111 | AE53: =IF(AD53="","",AB53-AB52) -> 30 | AF53: =IF(AE53="","",AB53-AB$29) -> 720 | AG53: =IF(AF53="","",IF(AF53<365,AF53*AC$25*AD53,365*AD53*AC$25)) -> 16.627778 | AH53: =IF(AF53="","",IF(AF53<365,AF53*AC$26*AD53,365*AD53*AC$26)) -> 5.5561111 | AJ53: =IF(A53<=$B$17,F53,0) -> 1329.3116 | AK53: =IF(A53<=$B$17,E52*$D$15+D53,0) -> 1150.9192
A54: =IF(A53<B$17,A53+1,"") -> 31 | B54: =IF(A54="","",IF(A54<=B$16,"carência","amortização")) -> amortização | C54: =IF(B54="","",E53*$C$23) -> 172.63788 | D54: =IF(C54="","",IF(A54<=B$16,0,$E$23/(B$17-B$16))) -> 1150.9192 | E54: =IF(F54="","",E53-D54) -> 33376.656 | F54: =IF(D54="","",D54+C54) -> 1323.557 | AA54: =IF(AA53<B$17,AA53+1,"") -> 25 | AB54: =IF(AA54="","",AB53+30) -> 46990 | AC54: =IF(AB54="","",IF(AA54<=B$16,AC53,AC53-AD54)) -> 38888.889 | AD54: =IF(AA54="","",IF(AA54<=B$16,0,B$15/(B$17-B$16))) -> 1111.1111 | AE54: =IF(AD54="","",AB54-AB53) -> 30 | AF54: =IF(AE54="","",AB54-AB$29) -> 750 | AG54: =IF(AF54="","",IF(AF54<365,AF54*AC$25*AD54,365*AD54*AC$25)) -> 16.627778 | AH54: =IF(AF54="","",IF(AF54<365,AF54*AC$26*AD54,365*AD54*AC$26)) -> 5.5561111 | AJ54: =IF(A54<=$B$17,F54,0) -> 1323.557 | AK54: =IF(A54<=$B$17,E53*$D$15+D54,0) -> 1150.9192
... A71: =IF(A70<B$17,A70+1,"") -> 48 | B71: =IF(A71="","",IF(A71<=B$16,"carência","amortização")) -> amortização | C71: =IF(B71="","",E70*$C$23) -> 74.809746 | D71: =IF(C71="","",IF(A71<=B$16,0,$E$23/(B$17-B$16))) -> 1150.9192 | E71: =IF(F71="","",E70-D71) -> 13811.03 | F71: =IF(D71="","",D71+C71) -> 1225.7289 | AA71: =IF(AA70<B$17,AA70+1,"") -> 42 | AB71: =IF(AA71="","",AB70+30) -> 47500 | AC71: =IF(AB71="","",IF(AA71<=B$16,AC70,AC70-AD71)) -> 20000 | AD71: =IF(AA71="","",IF(AA71<=B$16,0,B$15/(B$17-B$16))) -> 1111.1111 | AE71: =IF(AD71="","",AB71-AB70) -> 30 | AF71: =IF(AE71="","",AB71-AB$29) -> 1260 | AG71: =IF(AF71="","",IF(AF71<365,AF71*AC$25*AD71,365*AD71*AC$25)) -> 16.627778 | AH71: =IF(AF71="","",IF(AF71<365,AF71*AC$26*AD71,365*AD71*AC$26)) -> 5.5561111 | AJ71: =IF(A71<=$B$17,F71,0) -> 1225.7289 | AK71: =IF(A71<=$B$17,E70*$D$15+D71,0) -> 1150.9192
A72: =IF(A71<B$17,A71+1,"") -> 49 | B72: =IF(A72="","",IF(A72<=B$16,"carência","amortização")) -> amortização | C72: =IF(B72="","",E71*$C$23) -> 69.05515 | D72: =IF(C72="","",IF(A72<=B$16,0,$E$23/(B$17-B$16))) -> 1150.9192 | E72: =IF(F72="","",E71-D72) | AA72: =IF(AA71<B$17,AA71+1,"") -> 43 | AB72: =IF(AA72="","",AB71+30) -> 47530 | AC72: =IF(AB72="","",IF(AA72<=B$16,AC71,AC71-AD72)) -> 18888.889 | AD72: =IF(AA72="","",IF(AA72<=B$16,0,B$15/(B$17-B$16))) -> 1111.1111 | AE72: =IF(AD72="","",AB72-AB71) -> 30 | AF72: =IF(AE72="","",AB72-AB$29) -> 1290 | AG72: =IF(AF72="","",IF(AF72<365,AF72*AC$25*AD72,365*AD72*AC$25)) -> 16.627778 | AH72: =IF(AF72="","",IF(AF72<365,AF72*AC$26*AD72,365*AD72*AC$26)) -> 5.5561111 | AJ72: =IF(A72<=$B$17,F72,0) -> 0 | AK72: =IF(A72<=$B$17,E71*$D$15+D72,0) -> 1150.9192
A73: =IF(A72<B$17,A72+1,"") -> 50 | B73: =IF(A73="","",IF(A73<=B$16,"carência","amortização")) -> amortização | C73: =IF(B73="","",E72*$C$23) -> #VALUE! | D73: =IF(C73="","",IF(A73<=B$16,0,$E$23/(B$17-B$16))) -> #VALUE! | E73: =IF(F73="","",E72-D73) | AA73: =IF(AA72<B$17,AA72+1,"") -> 44 | AB73: =IF(AA73="","",AB72+30) -> 47560 | AC73: =IF(AB73="","",IF(AA73<=B$16,AC72,AC72-AD73)) -> 17777.778 | AD73: =IF(AA73="","",IF(AA73<=B$16,0,B$15/(B$17-B$16))) -> 1111.1111 | AE73: =IF(AD73="","",AB73-AB72) -> 30 | AF73: =IF(AE73="","",AB73-AB$29) -> 1320 | AG73: =IF(AF73="","",IF(AF73<365,AF73*AC$25*AD73,365*AD73*AC$25)) -> 16.627778 | AH73: =IF(AF73="","",IF(AF73<365,AF73*AC$26*AD73,365*AD73*AC$26)) -> 5.5561111 | AJ73: =IF(A73<=$B$17,F73,0) -> 0 | AK73: =IF(A73<=$B$17,E72*$D$15+D73,0) -> #VALUE!
A74: =IF(A73<B$17,A73+1,"") -> 51 | B74: =IF(A74="","",IF(A74<=B$16,"carência","amortização")) -> amortização | C74: =IF(B74="","",E73*$C$23) -> #VALUE! | D74: =IF(C74="","",IF(A74<=B$16,0,$E$23/(B$17-B$16))) -> #VALUE! | E74: =IF(F74="","",E73-D74) | AA74: =IF(AA73<B$17,AA73+1,"") -> 45 | AB74: =IF(AA74="","",AB73+30) -> 47590 | AC74: =IF(AB74="","",IF(AA74<=B$16,AC73,AC73-AD74)) -> 16666.667 | AD74: =IF(AA74="","",IF(AA74<=B$16,0,B$15/(B$17-B$16))) -> 1111.1111 | AE74: =IF(AD74="","",AB74-AB73) -> 30 | AF74: =IF(AE74="","",AB74-AB$29) -> 1350 | AG74: =IF(AF74="","",IF(AF74<365,AF74*AC$25*AD74,365*AD74*AC$25)) -> 16.627778 | AH74: =IF(AF74="","",IF(AF74<365,AF74*AC$26*AD74,365*AD74*AC$26)) -> 5.5561111 | AJ74: =IF(A74<=$B$17,F74,0) -> 0 | AK74: =IF(A74<=$B$17,E73*$D$15+D74,0) -> #VALUE!
A75: =IF(A74<B$17,A74+1,"") -> 52 | B75: =IF(A75="","",IF(A75<=B$16,"carência","amortização")) -> amortização | C75: =IF(B75="","",E74*$C$23) -> #VALUE! | D75: =IF(C75="","",IF(A75<=B$16,0,$E$23/(B$17-B$16))) -> #VALUE! | E75: =IF(F75="","",E74-D75) | AA75: =IF(AA74<B$17,AA74+1,"") -> 46 | AB75: =IF(AA75="","",AB74+30) -> 47620 | AC75: =IF(AB75="","",IF(AA75<=B$16,AC74,AC74-AD75)) -> 15555.556 | AD75: =IF(AA75="","",IF(AA75<=B$16,0,B$15/(B$17-B$16))) -> 1111.1111 | AE75: =IF(AD75="","",AB75-AB74) -> 30 | AF75: =IF(AE75="","",AB75-AB$29) -> 1380 | AG75: =IF(AF75="","",IF(AF75<365,AF75*AC$25*AD75,365*AD75*AC$25)) -> 16.627778 | AH75: =IF(AF75="","",IF(AF75<365,AF75*AC$26*AD75,365*AD75*AC$26)) -> 5.5561111 | AJ75: =IF(A75<=$B$17,F75,0) -> 0 | AK75: =IF(A75<=$B$17,E74*$D$15+D75,0) -> #VALUE!
A76: =IF(A75<B$17,A75+1,"") -> 53 | B76: =IF(A76="","",IF(A76<=B$16,"carência","amortização")) -> amortização | C76: =IF(B76="","",E75*$C$23) -> #VALUE! | D76: =IF(C76="","",IF(A76<=B$16,0,$E$23/(B$17-B$16))) -> #VALUE! | E76: =IF(F76="","",E75-D76) | AA76: =IF(AA75<B$17,AA75+1,"") -> 47 | AB76: =IF(AA76="","",AB75+30) -> 47650 | AC76: =IF(AB76="","",IF(AA76<=B$16,AC75,AC75-AD76)) -> 14444.444 | AD76: =IF(AA76="","",IF(AA76<=B$16,0,B$15/(B$17-B$16))) -> 1111.1111 | AE76: =IF(AD76="","",AB76-AB75) -> 30 | AF76: =IF(AE76="","",AB76-AB$29) -> 1410 | AG76: =IF(AF76="","",IF(AF76<365,AF76*AC$25*AD76,365*AD76*AC$25)) -> 16.627778 | AH76: =IF(AF76="","",IF(AF76<365,AF76*AC$26*AD76,365*AD76*AC$26)) -> 5.5561111 | AJ76: =IF(A76<=$B$17,F76,0) -> 0 | AK76: =IF(A76<=$B$17,E75*$D$15+D76,0) -> #VALUE!
A77: =IF(A76<B$17,A76+1,"") -> 54 | B77: =IF(A77="","",IF(A77<=B$16,"carência","amortização")) -> amortização | C77: =IF(B77="","",E76*$C$23) -> #VALUE! | D77: =IF(C77="","",IF(A77<=B$16,0,$E$23/(B$17-B$16))) -> #VALUE! | E77: =IF(F77="","",E76-D77) | AA77: =IF(AA76<B$17,AA76+1,"") -> 48 | AB77: =IF(AA77="","",AB76+30) -> 47680 | AC77: =IF(AB77="","",IF(AA77<=B$16,AC76,AC76-AD77)) -> 13333.333 | AD77: =IF(AA77="","",IF(AA77<=B$16,0,B$15/(B$17-B$16))) -> 1111.1111 | AE77: =IF(AD77="","",AB77-AB76) -> 30 | AF77: =IF(AE77="","",AB77-AB$29) -> 1440 | AG77: =IF(AF77="","",IF(AF77<365,AF77*AC$25*AD77,365*AD77*AC$25)) -> 16.627778 | AH77: =IF(AF77="","",IF(AF77<365,AF77*AC$26*AD77,365*AD77*AC$26)) -> 5.5561111 | AJ77: =IF(A77<=$B$17,F77,0) -> 0 | AK77: =IF(A77<=$B$17,E76*$D$15+D77,0) -> #VALUE!
A78: =IF(A77<B$17,A77+1,"") -> 55 | B78: =IF(A78="","",IF(A78<=B$16,"carência","amortização")) -> amortização | C78: =IF(B78="","",E77*$C$23) -> #VALUE! | D78: =IF(C78="","",IF(A78<=B$16,0,$E$23/(B$17-B$16))) -> #VALUE! | AA78: =IF(AA77<B$17,AA77+1,"") -> 49 | AC78: =IF(AB78="","",IF(AA78<=B$16,AC77,AC77-AD78)) | AD78: =IF(AA78="","",IF(AA78<=B$16,0,B$15/(B$17-B$16))) -> 1111.1111 | AF78: =IF(AE78="","",AB78-AB$29) | AG78: =IF(AF78="","",IF(AF78<365,AF78*AC$25*AD78,365*AD78*AC$25)) | AH78: =IF(AF78="","",IF(AF78<365,AF78*AC$26*AD78,365*AD78*AC$26)) | AJ78: =IF(A78<=$B$17,F78,0) -> 0 | AK78: =IF(A78<=$B$17,E77*$D$15+D78,0) -> #VALUE!
A79: =IF(A78<B$17,A78+1,"") -> 56 | B79: =IF(A79="","",IF(A79<=B$16,"carência","amortização")) -> amortização | C79: =IF(B79="","",E78*$C$23) -> 0 | AA79: =IF(AA78<B$17,AA78+1,"") -> 50 | AC79: =IF(AB79="","",IF(AA79<=B$16,AC78,AC78-AD79)) | AD79: =IF(AA79="","",IF(AA79<=B$16,0,B$15/(B$17-B$16))) -> 1111.1111 | AF79: =IF(AE79="","",AB79-AB$29) | AG79: =IF(AF79="","",IF(AF79<365,AF79*AC$25*AD79,365*AD79*AC$25)) | AH79: =IF(AF79="","",IF(AF79<365,AF79*AC$26*AD79,365*AD79*AC$26)) | AJ79: =IF(A79<=$B$17,F79,0) -> 0 | AK79: =IF(A79<=$B$17,E78*$D$15+D79,0) -> 0
A80: =IF(A79<B$17,A79+1,"") -> 57 | B80: =IF(A80="","",IF(A80<=B$16,"carência","amortização")) -> amortização | C80: =IF(B80="","",E79*$C$23) -> 0 | AA80: =IF(AA79<B$17,AA79+1,"") -> 51 | AC80: =IF(AB80="","",IF(AA80<=B$16,AC79,AC79-AD80)) | AD80: =IF(AA80="","",IF(AA80<=B$16,0,B$15/(B$17-B$16))) -> 1111.1111 | AF80: =IF(AE80="","",AB80-AB$29) | AG80: =IF(AF80="","",IF(AF80<365,AF80*AC$25*AD80,365*AD80*AC$25)) | AH80: =IF(AF80="","",IF(AF80<365,AF80*AC$26*AD80,365*AD80*AC$26)) | AJ80: =IF(A80<=$B$17,F80,0) -> 0 | AK80: =IF(A80<=$B$17,E79*$D$15+D80,0) -> 0
AA81: =IF(AA80<B$17,AA80+1,"") -> 52 | AC81: =IF(AB81="","",IF(AA81<=B$16,AC80,AC80-AD81)) | AD81: =IF(AA81="","",IF(AA81<=B$16,0,B$15/(B$17-B$16))) -> 1111.1111 | AF81: =IF(AE81="","",AB81-AB$29) | AG81: =IF(AF81="","",IF(AF81<365,AF81*AC$25*AD81,365*AD81*AC$25)) | AH81: =IF(AF81="","",IF(AF81<365,AF81*AC$26*AD81,365*AD81*AC$26)) | AJ81: =IF(A81<=$B$17,F81,0) -> 0 | AK81: =IF(A81<=$B$17,E80*$D$15+D81,0) -> 0
AA82: =IF(AA81<B$17,AA81+1,"") -> 53 | AC82: =IF(AB82="","",IF(AA82<=B$16,AC81,AC81-AD82)) | AD82: =IF(AA82="","",IF(AA82<=B$16,0,B$15/(B$17-B$16))) -> 1111.1111 | AF82: =IF(AE82="","",AB82-AB$29) | AG82: =IF(AF82="","",IF(AF82<365,AF82*AC$25*AD82,365*AD82*AC$25)) | AH82: =IF(AF82="","",IF(AF82<365,AF82*AC$26*AD82,365*AD82*AC$26)) | AJ82: =IF(A82<=$B$17,F82,0) -> 0 | AK82: =IF(A82<=$B$17,E81*$D$15+D82,0) -> 0
AA83: =IF(AA82<B$17,AA82+1,"") -> 54 | AC83: =IF(AB83="","",IF(AA83<=B$16,AC82,AC82-AD83)) | AD83: =IF(AA83="","",IF(AA83<=B$16,0,B$15/(B$17-B$16))) -> 1111.1111 | AF83: =IF(AE83="","",AB83-AB$29) | AG83: =IF(AF83="","",IF(AF83<365,AF83*AC$25*AD83,365*AD83*AC$25)) | AH83: =IF(AF83="","",IF(AF83<365,AF83*AC$26*AD83,365*AD83*AC$26)) | AJ83: =IF(A83<=$B$17,F83,0) -> 0 | AK83: =IF(A83<=$B$17,E82*$D$15+D83,0) -> 0
AA84: =IF(AA83<B$17,AA83+1,"") -> 55 | AC84: =IF(AB84="","",IF(AA84<=B$16,AC83,AC83-AD84)) | AD84: =IF(AA84="","",IF(AA84<=B$16,0,B$15/(B$17-B$16))) -> 1111.1111 | AF84: =IF(AE84="","",AB84-AB$29) | AG84: =IF(AF84="","",IF(AF84<365,AF84*AC$25*AD84,365*AD84*AC$25)) | AH84: =IF(AF84="","",IF(AF84<365,AF84*AC$26*AD84,365*AD84*AC$26)) | AJ84: =IF(A84<=$B$17,F84,0) -> 0 | AK84: =IF(A84<=$B$17,E83*$D$15+D84,0) -> 0
AA85: =IF(AA84<B$17,AA84+1,"") -> 56 | AC85: =IF(AB85="","",IF(AA85<=B$16,AC84,AC84-AD85)) | AD85: =IF(AA85="","",IF(AA85<=B$16,0,B$15/(B$17-B$16))) -> 1111.1111 | AF85: =IF(AE85="","",AB85-AB$29) | AG85: =IF(AF85="","",IF(AF85<365,AF85*AC$25*AD85,365*AD85*AC$25)) | AH85: =IF(AF85="","",IF(AF85<365,AF85*AC$26*AD85,365*AD85*AC$26)) | AJ85: =IF(A85<=$B$17,F85,0) -> 0 | AK85: =IF(A85<=$B$17,E84*$D$15+D85,0) -> 0
AA86: =IF(AA85<B$17,AA85+1,"") -> 57 | AC86: =IF(AB86="","",IF(AA86<=B$16,AC85,AC85-AD86)) | AD86: =IF(AA86="","",IF(AA86<=B$16,0,B$15/(B$17-B$16))) -> 1111.1111 | AF86: =IF(AE86="","",AB86-AB$29) | AG86: =IF(AF86="","",IF(AF86<365,AF86*AC$25*AD86,365*AD86*AC$25)) | AH86: =IF(AF86="","",IF(AF86<365,AF86*AC$26*AD86,365*AD86*AC$26)) | AJ86: =IF(A86<=$B$17,F86,0) -> 0 | AK86: =IF(A86<=$B$17,E85*$D$15+D86,0) -> 0
AA87: =IF(AA86<B$17,AA86+1,"") -> 58 | AC87: =IF(AB87="","",IF(AA87<=B$16,AC86,AC86-AD87)) | AD87: =IF(AA87="","",IF(AA87<=B$16,0,B$15/(B$17-B$16))) -> 1111.1111 | AF87: =IF(AE87="","",AB87-AB$29) | AG87: =IF(AF87="","",IF(AF87<365,AF87*AC$25*AD87,365*AD87*AC$25)) | AH87: =IF(AF87="","",IF(AF87<365,AF87*AC$26*AD87,365*AD87*AC$26)) | AJ87: =IF(A87<=$B$17,F87,0) -> 0 | AK87: =IF(A87<=$B$17,E86*$D$15+D87,0) -> 0
AA88: =IF(AA87<B$17,AA87+1,"") -> 59 | AC88: =IF(AB88="","",IF(AA88<=B$16,AC87,AC87-AD88)) | AD88: =IF(AA88="","",IF(AA88<=B$16,0,B$15/(B$17-B$16))) -> 1111.1111 | AF88: =IF(AE88="","",AB88-AB$29) | AG88: =IF(AF88="","",IF(AF88<365,AF88*AC$25*AD88,365*AD88*AC$25)) | AH88: =IF(AF88="","",IF(AF88<365,AF88*AC$26*AD88,365*AD88*AC$26)) | AJ88: =IF(A88<=$B$17,F88,0) -> 0 | AK88: =IF(A88<=$B$17,E87*$D$15+D88,0) -> 0
AA89: =IF(AA88<B$17,AA88+1,"") -> 60 | AC89: =IF(AB89="","",IF(AA89<=B$16,AC88,AC88-AD89)) | AD89: =IF(AA89="","",IF(AA89<=B$16,0,B$15/(B$17-B$16))) -> 1111.1111 | AF89: =IF(AE89="","",AB89-AB$29) | AG89: =IF(AF89="","",IF(AF89<365,AF89*AC$25*AD89,365*AD89*AC$25)) | AH89: =IF(AF89="","",IF(AF89<365,AF89*AC$26*AD89,365*AD89*AC$26)) | AJ89: =IF(A89<=$B$17,F89,0) -> 0 | AK89: =IF(A89<=$B$17,E88*$D$15+D89,0) -> 0
AA90: =IF(AA89<B$17,AA89+1,"") | AC90: =IF(AB90="","",IF(AA90<=B$16,AC89,AC89-AD90)) | AD90: =IF(AA90="","",IF(AA90<=B$16,0,B$15/(B$17-B$16))) | AF90: =IF(AE90="","",AB90-AB$29) | AG90: =IF(AF90="","",IF(AF90<365,AF90*AC$25*AD90,365*AD90*AC$25)) | AH90: =IF(AF90="","",IF(AF90<365,AF90*AC$26*AD90,365*AD90*AC$26)) | AJ90: =IF(A90<=$B$17,F90,0) -> 0 | AK90: =IF(A90<=$B$17,E89*$D$15+D90,0) -> 0
AA91: =IF(AA90<B$17,AA90+1,"") | AC91: =IF(AB91="","",IF(AA91<=B$16,AC90,AC90-AD91)) | AD91: =IF(AA91="","",IF(AA91<=B$16,0,B$15/(B$17-B$16))) | AF91: =IF(AE91="","",AB91-AB$29) | AG91: =IF(AF91="","",IF(AF91<365,AF91*AC$25*AD91,365*AD91*AC$25)) | AH91: =IF(AF91="","",IF(AF91<365,AF91*AC$26*AD91,365*AD91*AC$26)) | AJ91: =IF(A91<=$B$17,F91,0) -> 0 | AK91: =IF(A91<=$B$17,E90*$D$15+D91,0) -> 0
AA92: =IF(AA91<B$17,AA91+1,"") | AC92: =IF(AB92="","",IF(AA92<=B$16,AC91,AC91-AD92)) | AD92: =IF(AA92="","",IF(AA92<=B$16,0,B$15/(B$17-B$16))) | AF92: =IF(AE92="","",AB92-AB$29) | AG92: =IF(AF92="","",IF(AF92<365,AF92*AC$25*AD92,365*AD92*AC$25)) | AH92: =IF(AF92="","",IF(AF92<365,AF92*AC$26*AD92,365*AD92*AC$26)) | AJ92: =IF(A92<=$B$17,F92,0) -> 0 | AK92: =IF(A92<=$B$17,E91*$D$15+D92,0) -> 0
... AA107: =IF(AA106<B$17,AA106+1,"") | AC107: =IF(AB107="","",IF(AA107<=B$16,AC106,AC106-AD107)) | AD107: =IF(AA107="","",IF(AA107<=B$16,0,B$15/(B$17-B$16))) | AF107: =IF(AE107="","",AB107-AB$29) | AG107: =IF(AF107="","",IF(AF107<365,AF107*AC$25*AD107,365*AD107*AC$25)) | AH107: =IF(AF107="","",IF(AF107<365,AF107*AC$26*AD107,365*AD107*AC$26)) | AJ107: =IF(A107<=$B$17,F107,0) -> 0 | AK107: =IF(A107<=$B$17,E106*$D$15+D107,0) -> 0
AA108: =IF(AA107<B$17,AA107+1,"") | AC108: =IF(AB108="","",IF(AA108<=B$16,AC107,AC107-AD108)) | AD108: =IF(AA108="","",IF(AA108<=B$16,0,B$15/(B$17-B$16))) | AF108: =IF(AE108="","",AB108-AB$29) | AG108: =IF(AF108="","",IF(AF108<365,AF108*AC$25*AD108,365*AD108*AC$25)) | AH108: =IF(AF108="","",IF(AF108<365,AF108*AC$26*AD108,365*AD108*AC$26))
AA109: =IF(AA108<B$17,AA108+1,"") | AC109: =IF(AB109="","",IF(AA109<=B$16,AC108,AC108-AD109)) | AD109: =IF(AA109="","",IF(AA109<=B$16,0,B$15/(B$17-B$16))) | AF109: =IF(AE109="","",AB109-AB$29) | AG109: =IF(AF109="","",IF(AF109<365,AF109*AC$25*AD109,365*AD109*AC$25)) | AH109: =IF(AF109="","",IF(AF109<365,AF109*AC$26*AD109,365*AD109*AC$26))
AA110: =IF(AA109<B$17,AA109+1,"") | AC110: =IF(AB110="","",IF(AA110<=B$16,AC109,AC109-AD110)) | AD110: =IF(AA110="","",IF(AA110<=B$16,0,B$15/(B$17-B$16))) | AF110: =IF(AE110="","",AB110-AB$29) | AG110: =IF(AF110="","",IF(AF110<365,AF110*AC$25*AD110,365*AD110*AC$25)) | AH110: =IF(AF110="","",IF(AF110<365,AF110*AC$26*AD110,365*AD110*AC$26))
AA111: =IF(AA110<B$17,AA110+1,"") | AC111: =IF(AB111="","",IF(AA111<=B$16,AC110,AC110-AD111)) | AD111: =IF(AA111="","",IF(AA111<=B$16,0,B$15/(B$17-B$16))) | AF111: =IF(AE111="","",AB111-AB$29) | AG111: =IF(AF111="","",IF(AF111<365,AF111*AC$25*AD111,365*AD111*AC$25)) | AH111: =IF(AF111="","",IF(AF111<365,AF111*AC$26*AD111,365*AD111*AC$26))
AA112: =IF(AA111<B$17,AA111+1,"") | AC112: =IF(AB112="","",IF(AA112<=B$16,AC111,AC111-AD112)) | AD112: =IF(AA112="","",IF(AA112<=B$16,0,B$15/(B$17-B$16))) | AF112: =IF(AE112="","",AB112-AB$29) | AG112: =IF(AF112="","",IF(AF112<365,AF112*AC$25*AD112,365*AD112*AC$25)) | AH112: =IF(AF112="","",IF(AF112<365,AF112*AC$26*AD112,365*AD112*AC$26))
AA113: =IF(AA112<B$17,AA112+1,"") | AC113: =IF(AB113="","",IF(AA113<=B$16,AC112,AC112-AD113)) | AD113: =IF(AA113="","",IF(AA113<=B$16,0,B$15/(B$17-B$16))) | AF113: =IF(AE113="","",AB113-AB$29) | AG113: =IF(AF113="","",IF(AF113<365,AF113*AC$25*AD113,365*AD113*AC$25)) | AH113: =IF(AF113="","",IF(AF113<365,AF113*AC$26*AD113,365*AD113*AC$26))
AA114: =IF(AA113<B$17,AA113+1,"") | AC114: =IF(AB114="","",IF(AA114<=B$16,AC113,AC113-AD114)) | AD114: =IF(AA114="","",IF(AA114<=B$16,0,B$15/(B$17-B$16))) | AF114: =IF(AE114="","",AB114-AB$29) | AG114: =IF(AF114="","",IF(AF114<365,AF114*AC$25*AD114,365*AD114*AC$25)) | AH114: =IF(AF114="","",IF(AF114<365,AF114*AC$26*AD114,365*AD114*AC$26))
AA115: =IF(AA114<B$17,AA114+1,"") | AC115: =IF(AB115="","",IF(AA115<=B$16,AC114,AC114-AD115)) | AD115: =IF(AA115="","",IF(AA115<=B$16,0,B$15/(B$17-B$16))) | AF115: =IF(AE115="","",AB115-AB$29) | AG115: =IF(AF115="","",IF(AF115<365,AF115*AC$25*AD115,365*AD115*AC$25)) | AH115: =IF(AF115="","",IF(AF115<365,AF115*AC$26*AD115,365*AD115*AC$26))
AA116: =IF(AA115<B$17,AA115+1,"") | AC116: =IF(AB116="","",IF(AA116<=B$16,AC115,AC115-AD116)) | AD116: =IF(AA116="","",IF(AA116<=B$16,0,B$15/(B$17-B$16))) | AF116: =IF(AE116="","",AB116-AB$29) | AG116: =IF(AF116="","",IF(AF116<365,AF116*AC$25*AD116,365*AD116*AC$25)) | AH116: =IF(AF116="","",IF(AF116<365,AF116*AC$26*AD116,365*AD116*AC$26))
AA117: =IF(AA116<B$17,AA116+1,"") | AC117: =IF(AB117="","",IF(AA117<=B$16,AC116,AC116-AD117)) | AD117: =IF(AA117="","",IF(AA117<=B$16,0,B$15/(B$17-B$16))) | AF117: =IF(AE117="","",AB117-AB$29) | AG117: =IF(AF117="","",IF(AF117<365,AF117*AC$25*AD117,365*AD117*AC$25)) | AH117: =IF(AF117="","",IF(AF117<365,AF117*AC$26*AD117,365*AD117*AC$26))
AA118: =IF(AA117<B$17,AA117+1,"") | AC118: =IF(AB118="","",IF(AA118<=B$16,AC117,AC117-AD118)) | AD118: =IF(AA118="","",IF(AA118<=B$16,0,B$15/(B$17-B$16))) | AF118: =IF(AE118="","",AB118-AB$29) | AG118: =IF(AF118="","",IF(AF118<365,AF118*AC$25*AD118,365*AD118*AC$25)) | AH118: =IF(AF118="","",IF(AF118<365,AF118*AC$26*AD118,365*AD118*AC$26))
AA119: =IF(AA118<B$17,AA118+1,"") | AC119: =IF(AB119="","",IF(AA119<=B$16,AC118,AC118-AD119)) | AD119: =IF(AA119="","",IF(AA119<=B$16,0,B$15/(B$17-B$16))) | AF119: =IF(AE119="","",AB119-AB$29) | AG119: =IF(AF119="","",IF(AF119<365,AF119*AC$25*AD119,365*AD119*AC$25)) | AH119: =IF(AF119="","",IF(AF119<365,AF119*AC$26*AD119,365*AD119*AC$26))
... AA229: =IF(AA228<B$17,AA228+1,"") | AC229: =IF(AB229="","",IF(AA229<=B$16,AC228,AC228-AD229)) | AD229: =IF(AA229="","",IF(AA229<=B$16,0,B$15/(B$17-B$16))) | AF229: =IF(AE229="","",AB229-AB$29) | AG229: =IF(AF229="","",IF(AF229<365,AF229*AC$25*AD229,365*AD229*AC$25)) | AH229: =IF(AF229="","",IF(AF229<365,AF229*AC$26*AD229,365*AD229*AC$26))
AA230: =IF(AA229<B$17,AA229+1,"") | AC230: =IF(AB230="","",IF(AA230<=B$16,AC229,AC229-AD230)) | AD230: =IF(AA230="","",IF(AA230<=B$16,0,B$15/(B$17-B$16))) | AG230: =IF(AF230="","",IF(AF230<365,AF230*AC$25*AD230,365*AD230*AC$25)) | AH230: =IF(AF230="","",IF(AF230<365,AF230*AC$26*AD230,365*AD230*AC$26))
AA231: =IF(AA230<B$17,AA230+1,"") | AC231: =IF(AB231="","",IF(AA231<=B$16,AC230,AC230-AD231)) | AD231: =IF(AA231="","",IF(AA231<=B$16,0,B$15/(B$17-B$16))) | AG231: =IF(AF231="","",IF(AF231<365,AF231*AC$25*AD231,365*AD231*AC$25)) | AH231: =IF(AF231="","",IF(AF231<365,AF231*AC$26*AD231,365*AD231*AC$26))
AA232: =IF(AA231<B$17,AA231+1,"") | AC232: =IF(AB232="","",IF(AA232<=B$16,AC231,AC231-AD232)) | AD232: =IF(AA232="","",IF(AA232<=B$16,0,B$15/(B$17-B$16))) | AG232: =IF(AF232="","",IF(AF232<365,AF232*AC$25*AD232,365*AD232*AC$25)) | AH232: =IF(AF232="","",IF(AF232<365,AF232*AC$26*AD232,365*AD232*AC$26))
AA233: =IF(AA232<B$17,AA232+1,"") | AC233: =IF(AB233="","",IF(AA233<=B$16,AC232,AC232-AD233)) | AD233: =IF(AA233="","",IF(AA233<=B$16,0,B$15/(B$17-B$16))) | AG233: =IF(AF233="","",IF(AF233<365,AF233*AC$25*AD233,365*AD233*AC$25)) | AH233: =IF(AF233="","",IF(AF233<365,AF233*AC$26*AD233,365*AD233*AC$26))
AA234: =IF(AA233<B$17,AA233+1,"") | AC234: =IF(AB234="","",IF(AA234<=B$16,AC233,AC233-AD234)) | AD234: =IF(AA234="","",IF(AA234<=B$16,0,B$15/(B$17-B$16))) | AG234: =IF(AF234="","",IF(AF234<365,AF234*AC$25*AD234,365*AD234*AC$25)) | AH234: =IF(AF234="","",IF(AF234<365,AF234*AC$26*AD234,365*AD234*AC$26))
AA235: =IF(AA234<B$17,AA234+1,"") | AC235: =IF(AB235="","",E229) | AD235: =IF(AA235="","",IF(AA235<=B$16,0,B$15/(B$17-B$16))) | AG235: =IF(AF235="","",IF(AF235<365,AF235*AC$25*AD235,365*AD235*AC$25)) | AH235: =IF(AF235="","",IF(AF235<365,AF235*AC$26*AD235,365*AD235*AC$26))
AA236: =IF(AA235<B$17,AA235+1,"") | AC236: =IF(AB236="","",E230) | AD236: =IF(AA236="","",IF(AA236<=B$16,0,B$15/(B$17-B$16))) | AG236: =IF(AF236="","",IF(AF236<365,AF236*AC$25*AD236,365*AD236*AC$25)) | AH236: =IF(AF236="","",IF(AF236<365,AF236*AC$26*AD236,365*AD236*AC$26))
AA237: =IF(AA236<B$17,AA236+1,"") | AC237: =IF(AB237="","",E231) | AD237: =IF(AA237="","",IF(AA237<=B$16,0,B$15/(B$17-B$16))) | AG237: =IF(AF237="","",IF(AF237<365,AF237*AC$25*AD237,365*AD237*AC$25)) | AH237: =IF(AF237="","",IF(AF237<365,AF237*AC$26*AD237,365*AD237*AC$26))
AA238: =IF(AA237<B$17,AA237+1,"") | AC238: =IF(AB238="","",E232) | AD238: =IF(AA238="","",IF(AA238<=B$16,0,B$15/(B$17-B$16))) | AG238: =IF(AF238="","",IF(AF238<365,AF238*AC$25*AD238,365*AD238*AC$25)) | AH238: =IF(AF238="","",IF(AF238<365,AF238*AC$26*AD238,365*AD238*AC$26))
AA239: =IF(AA238<B$17,AA238+1,"") | AC239: =IF(AB239="","",E233) | AD239: =IF(AA239="","",IF(AA239<=B$16,0,B$15/(B$17-B$16))) | AG239: =IF(AF239="","",IF(AF239<365,AF239*AC$25*AD239,365*AD239*AC$25)) | AH239: =IF(AF239="","",IF(AF239<365,AF239*AC$26*AD239,365*AD239*AC$26))
AA240: =IF(AA239<B$17,AA239+1,"") | AC240: =IF(AB240="","",E234) | AD240: =IF(AA240="","",IF(AA240<=B$16,0,B$15/(B$17-B$16))) | AG240: =IF(AF240="","",IF(AF240<365,AF240*AC$25*AD240,365*AD240*AC$25)) | AH240: =IF(AF240="","",IF(AF240<365,AF240*AC$26*AD240,365*AD240*AC$26))
...

Sheet Fator K - FGI
B4: Contrato: | C4: 46055-000-4 | F4: Prazo | G4: ='Linhas Giro Puro'!B17 -> 60
B5: Ninja Moto Peças Ltda | F5: Valor Financiado | G5: ='Linhas Giro Puro'!B15 -> 60000
B8: IOF | C8: 945.25 | F8: Prazo Total da Operação | G8: Valor Fator K
B9: TAC | C9: 1039.92 | F9: 3 | G9: 0.0142
B10: FGI | C10: 2347.16 | F10: 4 | G10: 0.0062
B11: Total | C11: =SUM(C8:C10) -> 4332.33 | F11: 5 | G11: 0.0062
B12: Líquido | C12: 50000 | F12: 6 | G12: 0.0062
B13: Financiado | C13: =C12+C11 -> 54332.33 | F13: 7 | G13: 0.0042
F14: 8 | G14: 0.0042
F15: 9 | G15: 0.0042
F16: 10 | G16: 0.0031
F17: 11 | G17: 0.0031
F18: 12 | G18: 0.0031
F19: 13 | G19: 0.0027
F20: 14 | G20: 0.0027
F21: 15 | G21: 0.0027
F22: 16 | G22: 0.0024
F23: 17 | G23: 0.0024
F24: 18 | G24: 0.0024
F25: 19 | G25: 0.0022 | H25: K = | I25: =_xlfn.XLOOKUP(I28,F9:F110,G9:G110) -> 0.001
F26: 20 | G26: 0.0022 | H26: VL | I26: =G5+'Linhas Giro Puro'!F15+'Linhas Giro Puro'!F16 -> 62149.635
F27: 21 | G27: 0.0022 | H27: %G | I27: 0.8
F28: 22 | G28: 0.002 | H28: P | I28: =G4 -> 60
F29: 23 | G29: 0.002
F30: 24 | G30: 0.002 | H30: ECG = | I30: =(I25*(I26*I27)*I28)/(1-(I25*I27*I28)) -> 3133.595
F31: 25 | G31: 0.0018
F32: 26 | G32: 0.0018
F33: 27 | G33: 0.0018
F34: 28 | G34: 0.0017
F35: 29 | G35: 0.0017
F36: 30 | G36: 0.0017
F37: 31 | G37: 0.0016
F38: 32 | G38: 0.0016
F39: 33 | G39: 0.0016
F40: 34 | G40: 0.0015
F41: 35 | G41: 0.0015
F42: 36 | G42: 0.0015
... F110: 103 | G110: 0.0005

Sheet Mais Crédito
A1: AGÊNCIA DE FOMENTO DE GOIÁS S/A | AA1: 1 | AB1: 1
A2: IMPORTANTE: Os valores simulados podem variar e estão sujeitos à data de vencimento da parcela e da liberação do crédito; O financiamento e condições são sujeitas à aprovação final da análise de crédito; Valores calculados com base na taxa líquida para quando não há atraso nos pagamentos.
A3: LINHA DE CAPITAL DE GIRO/INVESTIMENTO | AA3: TAC | AB3: IOF
A4: LINHA | J4: 1 | K4: 1 | N4: LINHA | O4: TAXA (a.m.) | P4: TAXA BONUS | Q4: CG1 (a.m.) | R4: CG2 (a.m.) | S4: PRAZO (meses) | T4: CARÊNCIA (até meses) | U4: LIMITE | V4: GARANTIA | AA4: Descontado | AB4: Descontado
N5: Mais Crédito Aval do FUNDEQ | O5: 1.69 | P5: 0 | Q5: 1.69 | R5: =Q5 -> 1.69 | S5: 24 | T5: 3 | U5: 21000 | V5: CG1 | AA5: Financiado | AB5: Financiado
C6: =IF(AND(J4=1,K4=1),Q5,IF(AND(J4=1,K4=2),R5,IF(AND(J4=1,K4=3),P5,"-"))) -> 1.69 | N6: Mais CrédIto com parceria - Juro Zero e Aval | O6: 1.69 | P6: 0 | Q6: 0 | R6: 0 | S6: 24 | T6: 3 | U6: 21000 | V6: CG2
C7: =IF(AND(J4=2,K4=1),Q6,IF(AND(J4=2,K4=2),R6,IF(AND(J4=2,K4=3),P6,"-"))) -> - | N7: Mais Crédito Equalização de Juros FUNDEQ | O7: 1.69 | P7: 0 | Q7: 0 | R7: 0 | S7: 24 | T7: 3 | U7: 21000 | V7: NÃO
C8: =IF(AND(J4=3,K4=1),Q7,IF(AND(J4=3,K4=2),R7,IF(AND(J4=3,K4=3),P7,"-"))) -> - | N8: GoiásFomento Giro - VIP IMCF | O8: 1.9 | P8: 0 | Q8: 1.47 | R8: =Q8 -> 1.47 | S8: 36 | T8: 3 | U8: 300000
C9: =IF(AND(J4=4,K4=1),Q8,IF(AND(J4=4,K4=2),R8,IF(AND(J4=4,K4=3),P8,"-"))) -> - | N9: GoiásFomento Giro Consorciado | O9: 1.9 | P9: 0 | Q9: 1.47 | R9: =Q9 -> 1.47 | S9: 36 | T9: 3 | U9: 300000
C10: =IF(AND(J4=5,K4=1),Q9,IF(AND(J4=5,K4=2),R9,IF(AND(J4=5,K4=3),P9,"-"))) -> - | N10: GoiásFomento (GIRO)Tecnologia/PQF-IEL/Turismo/FarmaDrogas/ Contabilistas | O10: 2.05 | P10: 0 | Q10: 1.58 | R10: =Q10 -> 1.58 | S10: 36 | T10: 3 | U10: 300000
C11: =IF(AND(J4=6,K4=1),Q10,IF(AND(J4=6,K4=2),R10,IF(AND(J4=6,K4=3),P10,"-"))) -> - | N11: GoiásFomento Microcrédito Produtivo | O11: 1.82 | P11: 1.5 | Q11: 1.5 | R11: =Q11 -> 1.5 | S11: 36 | T11: 3 | U11: 21000
C12: =IF(AND(J4=7,K4=1),Q11,IF(AND(J4=7,K4=2),R11,IF(AND(J4=7,K4=3),P11,"-"))) -> -
K13: ASSAT1
A14: INFORMAÇÕES | I14: =IF(B15<=5000,IF(AND(B15<=5000,J21=TRUE),D15,0),0.0169) -> 0.0169
A15: VALOR FINANCIADO | B15: 5000 | C15: TAXA NOMINAL | D15: =IF(J4=1,O5,IF(J4=2,O6,IF(J4=3,O7,IF(J4=4,O8,IF(J4=5,O9,IF(J4=6,O10,IF(J4=7,O11)))))))/100 -> 0.0169 | F15: =IF(B15<=3000,50,IF(B15<=21000,IF(B15*0.03<=420,B15*0.03,420),IF(B15<=100000,B15*0.02,2000+B15*0.005))) -> 150 | I15: =IF(B15<=3000,50,IF(B15<=21000,IF(B15*0.03<=420,B15*0.03,420),IF(B15<=100000,B15*0.02,2000+B15*0.005))) -> 150 | J15: 4
A16: CARÊNCIA | B16: 6 | C16: TAXA COM BÔNUS | D16: =IF(B15<=5000,IF(AND(B15<=5000,J21=TRUE),D15,0),0.0169) -> 0.0169 | F16: =AF24 -> 42.9065 | I16: =IF(B15*0.03<=420,B15*0.03,420) -> 150 | J16: 1 | AP16: 36
A17: PRAZO TOTAL | B17: 36 | C17: DATA DA PROPOSTA | D17: =TODAY() -> 46240 | F17: =IF(B15>5000,IF(B15>5000,IF(K4=1,(B15*E19*0.001*B17),IF(K4=2,(F19*0.001*B17),IF(K4=3,0,""))),0),IF(J21=TRUE,IF(K4=1,(B15*E19*0.001*B17),IF(K4=2,(F19*0.001*B17),IF(K4=3,0,""))),0)) -> 180 | J17: Descontado | L17: FALSE
A18: OPÇÕES DE GARANTIA | J18: Financiado
A19: RENDA PARA AVAL | B19: =IF(LARGE(F23:F241,1)*3<2424,2424,LARGE(F23:F241,1)*3) -> 2424 | C19: ALIENAÇÃO DE IMÓVEL | D19: =IF(J21=TRUE,(B15-F19)*1.5/0.7,B15*1.5/0.7) -> 0 | E19: 1 | F19: =IF(F17<>0,IF(K4=1,(B15*E19),IF(K4=2,B15*E19,IF(K4=3,0,""))),0) -> 5000 | J19: FINANCIADO | L19: TRUE
A20: SIMULAÇÃO DO VALOR DAS PARCELAS | J20: Financiado | AM20: =IRR(AM23:AM47) -> -0.0059870182
A21: PARCELA | B21: AMORTIZAÇÃO | C21: JUROS | D21: VALOR AMORTIZAÇÃO | E21: SALDO DEVEDOR | F21: PARCELA COM BÔNUS | J21: TRUE | AB21: IOF - ACIMA ATÉ 365 DIAS
A22: TOTAL | C22: =SUM(C23:C242) -> 1816.7669 | D22: =SUM(D23:D242) -> 5000 | F22: =SUM(F23:F242) -> 6816.75
A23: 0 | C23: =D16 -> 0.0169 | E23: =IF(AND(AA1=1,AB1=1,J16=1),B15,IF(AND(AA1=1,AB1=1,J16=2),B15+F17,IF(AND(AA1=1,AB1=2,J16=1),B15+F16,IF(AND(AA1=1,AB1=2,J16=3),B15+F16,IF(AND(AA1=2,AB1=1,J16=1),B15+F15,IF(AND(AA1=2,AB1=1,J16=2),B15+F15+F17,IF(AND(AA1=2,AB1=2,J16=2),B15+F17+F16+F15,IF(AND(AA1=2,AB1=2,J16=3),B15+F15+F16,IF(AND(AA1=2,AB1=2,J16=1),B15+F15+F16,IF(AND(AA1=1,AB1=2,J16=2),B15+F16+F17, IF(AND(AA1=1,AB1=1,J16=3),B15))))))))))) -> 5000 | AM23: =-B15 -> -5000
A24: =IF(A23<B$17,A23+1,"") -> 1 | B24: =IF(A24="","",IF(A24<=B$16,"carência","amortização")) -> carência | C24: =IF(B24="","",E23*$C$23) -> 84.5 | D24: =IF(C24="","",IF(A24<=B$16,0,B$15/(B$17-B$16))) -> 0 | E24: =IF(F24="","",E23-D24) -> 5000 | F24: =IF(D24="","",D24+C24) -> 84.5 | AB24: IOF | AC24: 0.0038 | AE24: =AC27*AC24 -> 19 | AF24: =IF(L19=FALSE,0,IF(AND(AH25=TRUE,B15<=30000),AE24+AE26,AE24+AE25)) -> 42.9065 | AM24: =F24 -> 84.5
A25: =IF(A24<B$17,A24+1,"") -> 2 | B25: =IF(A25="","",IF(A25<=B$16,"carência","amortização")) -> carência | C25: =IF(B25="","",E24*$C$23) -> 84.5 | D25: =IF(C25="","",IF(A25<=B$16,0,B$15/(B$17-B$16))) -> 0 | E25: =IF(F25="","",E24-D25) -> 5000 | F25: =IF(D25="","",D25+C25) -> 84.5 | AB25: ALÍQUOTA | AC25: 4.1e-05 | AE25: =SUM(AG30:AG83) -> 71.545 | AH25: TRUE | AM25: =F25 -> 84.5
A26: =IF(A25<B$17,A25+1,"") -> 3 | B26: =IF(A26="","",IF(A26<=B$16,"carência","amortização")) -> carência | C26: =IF(B26="","",E25*$C$23) -> 84.5 | D26: =IF(C26="","",IF(A26<=B$16,0,B$15/(B$17-B$16))) -> 0 | E26: =IF(F26="","",E25-D26) -> 5000 | F26: =IF(D26="","",D26+C26) -> 84.5 | AB26: ALÍQUOTA SIMPLES | AC26: =0.00137/100 -> 1.37e-05 | AE26: =SUM(AH30:AH308) -> 23.9065 | AM26: =F26 -> 84.5
A27: =IF(A26<B$17,A26+1,"") -> 4 | B27: =IF(A27="","",IF(A27<=B$16,"carência","amortização")) -> carência | C27: =IF(B27="","",E26*$C$23) -> 84.5 | D27: =IF(C27="","",IF(A27<=B$16,0,B$15/(B$17-B$16))) -> 0 | E27: =IF(F27="","",E26-D27) -> 5000 | F27: =IF(D27="","",D27+C27) -> 84.5 | AB27: LIBERAÇÃO | AC27: =B15 -> 5000 | AM27: =F27 -> 84.5 | AP27: =F27/0.3 -> 281.66667 | AQ27: =AP27/0.2 -> 1408.3333 | AS27: =F27/0.2 -> 422.5 | AU27: 81000
A28: =IF(A27<B$17,A27+1,"") -> 5 | B28: =IF(A28="","",IF(A28<=B$16,"carência","amortização")) -> carência | C28: =IF(B28="","",E27*$C$23) -> 84.5 | D28: =IF(C28="","",IF(A28<=B$16,0,B$15/(B$17-B$16))) -> 0 | E28: =IF(F28="","",E27-D28) -> 5000 | F28: =IF(D28="","",D28+C28) -> 84.5 | AG28: IOF NORMAL | AH28: IOF SIMPLES | AM28: =F28 -> 84.5 | AU28: =AU27/12 -> 6750
A29: =IF(A28<B$17,A28+1,"") -> 6 | B29: =IF(A29="","",IF(A29<=B$16,"carência","amortização")) -> carência | C29: =IF(B29="","",E28*$C$23) -> 84.5 | D29: =IF(C29="","",IF(A29<=B$16,0,B$15/(B$17-B$16))) -> 0 | E29: =IF(F29="","",E28-D29) -> 5000 | F29: =IF(D29="","",D29+C29) -> 84.5 | AA29: 0 | AB29: =D17 -> 46240 | AC29: =IF(AB29="","",AC27) -> 5000 | AD29: =IF(AA29="","",IF(AA29<=B$16,0,B$15/(B$17-B$16))) -> 0 | AM29: =F29 -> 84.5 | AU29: =F27/AU28 -> 0.012518519
A30: =IF(A29<B$17,A29+1,"") -> 7 | B30: =IF(A30="","",IF(A30<=B$16,"carência","amortização")) -> amortização | C30: =IF(B30="","",E29*$C$23) -> 84.5 | D30: =IF(C30="","",IF(A30<=B$16,0,B$15/(B$17-B$16))) -> 166.66667 | E30: =IF(F30="","",E29-D30) -> 4833.3333 | F30: =IF(D30="","",D30+C30) -> 251.16667 | AA30: =IF(AA29<B$17,AA29+1,"") -> 1 | AB30: =IF(AA30="","",AB29+30) -> 46270 | AC30: =IF(AB30="","",IF(AA30<=B$16,AC29,AC29-AD30)) -> 5000 | AD30: =IF(AA30="","",IF(AA30<=B$16,0,B$15/(B$17-B$16))) -> 0 | AE30: =IF(AD30="","",AB30-AB29) -> 30 | AF30: =IF(AE30="","",AB30-AB$29) -> 30 | AG30: =IF(AF30="","",IF(AF30<365,AF30*AC$25*AD30,365*AD30*AC$25)) -> 0 | AH30: =IF(AF30="","",IF(AF30<365,AF30*AC$26*AD30,365*AD30*AC$26)) -> 0 | AM30: =F30 -> 251.16667 | AN30: =F30*12 -> 3014
A31: =IF(A30<B$17,A30+1,"") -> 8 | B31: =IF(A31="","",IF(A31<=B$16,"carência","amortização")) -> amortização | C31: =IF(B31="","",E30*$C$23) -> 81.683333 | D31: =IF(C31="","",IF(A31<=B$16,0,B$15/(B$17-B$16))) -> 166.66667 | E31: =IF(F31="","",E30-D31) -> 4666.6667 | F31: =IF(D31="","",D31+C31) -> 248.35 | AA31: =IF(AA30<B$17,AA30+1,"") -> 2 | AB31: =IF(AA31="","",AB30+30) -> 46300 | AC31: =IF(AB31="","",IF(AA31<=B$16,AC30,AC30-AD31)) -> 5000 | AD31: =IF(AA31="","",IF(AA31<=B$16,0,B$15/(B$17-B$16))) -> 0 | AE31: =IF(AD31="","",AB31-AB30) -> 30 | AF31: =IF(AE31="","",AB31-AB$29) -> 60 | AG31: =IF(AF31="","",IF(AF31<365,AF31*AC$25*AD31,365*AD31*AC$25)) -> 0 | AH31: =IF(AF31="","",IF(AF31<365,AF31*AC$26*AD31,365*AD31*AC$26)) -> 0 | AM31: =F31 -> 248.35 | AU31: =AU28*0.1 -> 675
A32: =IF(A31<B$17,A31+1,"") -> 9 | B32: =IF(A32="","",IF(A32<=B$16,"carência","amortização")) -> amortização | C32: =IF(B32="","",E31*$C$23) -> 78.866667 | D32: =IF(C32="","",IF(A32<=B$16,0,B$15/(B$17-B$16))) -> 166.66667 | E32: =IF(F32="","",E31-D32) -> 4500 | F32: =IF(D32="","",D32+C32) -> 245.53333 | AA32: =IF(AA31<B$17,AA31+1,"") -> 3 | AB32: =IF(AA32="","",AB31+30) -> 46330 | AC32: =IF(AB32="","",IF(AA32<=B$16,AC31,AC31-AD32)) -> 5000 | AD32: =IF(AA32="","",IF(AA32<=B$16,0,B$15/(B$17-B$16))) -> 0 | AE32: =IF(AD32="","",AB32-AB31) -> 30 | AF32: =IF(AE32="","",AB32-AB$29) -> 90 | AG32: =IF(AF32="","",IF(AF32<365,AF32*AC$25*AD32,365*AD32*AC$25)) -> 0 | AH32: =IF(AF32="","",IF(AF32<365,AF32*AC$26*AD32,365*AD32*AC$26)) -> 0 | AM32: =F32 -> 245.53333
A33: =IF(A32<B$17,A32+1,"") -> 10 | B33: =IF(A33="","",IF(A33<=B$16,"carência","amortização")) -> amortização | C33: =IF(B33="","",E32*$C$23) -> 76.05 | D33: =IF(C33="","",IF(A33<=B$16,0,B$15/(B$17-B$16))) -> 166.66667 | E33: =IF(F33="","",E32-D33) -> 4333.3333 | F33: =IF(D33="","",D33+C33) -> 242.71667 | AA33: =IF(AA32<B$17,AA32+1,"") -> 4 | AB33: =IF(AA33="","",AB32+30) -> 46360 | AC33: =IF(AB33="","",IF(AA33<=B$16,AC32,AC32-AD33)) -> 5000 | AD33: =IF(AA33="","",IF(AA33<=B$16,0,B$15/(B$17-B$16))) -> 0 | AE33: =IF(AD33="","",AB33-AB32) -> 30 | AF33: =IF(AE33="","",AB33-AB$29) -> 120 | AG33: =IF(AF33="","",IF(AF33<365,AF33*AC$25*AD33,365*AD33*AC$25)) -> 0 | AH33: =IF(AF33="","",IF(AF33<365,AF33*AC$26*AD33,365*AD33*AC$26)) -> 0 | AM33: =F33 -> 242.71667
A34: =IF(A33<B$17,A33+1,"") -> 11 | B34: =IF(A34="","",IF(A34<=B$16,"carência","amortização")) -> amortização | C34: =IF(B34="","",E33*$C$23) -> 73.233333 | D34: =IF(C34="","",IF(A34<=B$16,0,B$15/(B$17-B$16))) -> 166.66667 | E34: =IF(F34="","",E33-D34) -> 4166.6667 | F34: =IF(D34="","",D34+C34) -> 239.9 | AA34: =IF(AA33<B$17,AA33+1,"") -> 5 | AB34: =IF(AA34="","",AB33+30) -> 46390 | AC34: =IF(AB34="","",IF(AA34<=B$16,AC33,AC33-AD34)) -> 5000 | AD34: =IF(AA34="","",IF(AA34<=B$16,0,B$15/(B$17-B$16))) -> 0 | AE34: =IF(AD34="","",AB34-AB33) -> 30 | AF34: =IF(AE34="","",AB34-AB$29) -> 150 | AG34: =IF(AF34="","",IF(AF34<365,AF34*AC$25*AD34,365*AD34*AC$25)) -> 0 | AH34: =IF(AF34="","",IF(AF34<365,AF34*AC$26*AD34,365*AD34*AC$26)) -> 0 | AM34: =F34 -> 239.9
A35: =IF(A34<B$17,A34+1,"") -> 12 | B35: =IF(A35="","",IF(A35<=B$16,"carência","amortização")) -> amortização | C35: =IF(B35="","",E34*$C$23) -> 70.416667 | D35: =IF(C35="","",IF(A35<=B$16,0,B$15/(B$17-B$16))) -> 166.66667 | E35: =IF(F35="","",E34-D35) -> 4000 | F35: =IF(D35="","",D35+C35) -> 237.08333 | AA35: =IF(AA34<B$17,AA34+1,"") -> 6 | AB35: =IF(AA35="","",AB34+30) -> 46420 | AC35: =IF(AB35="","",IF(AA35<=B$16,AC34,AC34-AD35)) -> 5000 | AD35: =IF(AA35="","",IF(AA35<=B$16,0,B$15/(B$17-B$16))) -> 0 | AE35: =IF(AD35="","",AB35-AB34) -> 30 | AF35: =IF(AE35="","",AB35-AB$29) -> 180 | AG35: =IF(AF35="","",IF(AF35<365,AF35*AC$25*AD35,365*AD35*AC$25)) -> 0 | AH35: =IF(AF35="","",IF(AF35<365,AF35*AC$26*AD35,365*AD35*AC$26)) -> 0 | AM35: =F35 -> 237.08333 | AN35: =SUM(F24:F35) -> 1971.75 | AO35: =LARGE(F24:F35,1) -> 251.16667
A36: =IF(A35<B$17,A35+1,"") -> 13 | B36: =IF(A36="","",IF(A36<=B$16,"carência","amortização")) -> amortização | C36: =IF(B36="","",E35*$C$23) -> 67.6 | D36: =IF(C36="","",IF(A36<=B$16,0,E$23/(B$17-B$16))) -> 166.66667 | E36: =IF(F36="","",E35-D36) -> 3833.3333 | F36: =IF(D36="","",D36+C36) -> 234.26667 | AA36: =IF(AA35<B$17,AA35+1,"") -> 7 | AB36: =IF(AA36="","",AB35+30) -> 46450 | AC36: =IF(AB36="","",IF(AA36<=B$16,AC35,AC35-AD36)) -> 4833.3333 | AD36: =IF(AA36="","",IF(AA36<=B$16,0,B$15/(B$17-B$16))) -> 166.66667 | AE36: =IF(AD36="","",AB36-AB35) -> 30 | AF36: =IF(AE36="","",AB36-AB$29) -> 210 | AG36: =IF(AF36="","",IF(AF36<365,AF36*AC$25*AD36,365*AD36*AC$25)) -> 1.435 | AH36: =IF(AF36="","",IF(AF36<365,AF36*AC$26*AD36,365*AD36*AC$26)) -> 0.4795 | AM36: =F36 -> 234.26667
A37: =IF(A36<B$17,A36+1,"") -> 14 | B37: =IF(A37="","",IF(A37<=B$16,"carência","amortização")) -> amortização | C37: =IF(B37="","",E36*$C$23) -> 64.783333 | D37: =IF(C37="","",IF(A37<=B$16,0,E$23/(B$17-B$16))) -> 166.66667 | E37: =IF(F37="","",E36-D37) -> 3666.6667 | F37: =IF(D37="","",D37+C37) -> 231.45 | AA37: =IF(AA36<B$17,AA36+1,"") -> 8 | AB37: =IF(AA37="","",AB36+30) -> 46480 | AC37: =IF(AB37="","",IF(AA37<=B$16,AC36,AC36-AD37)) -> 4666.6667 | AD37: =IF(AA37="","",IF(AA37<=B$16,0,B$15/(B$17-B$16))) -> 166.66667 | AE37: =IF(AD37="","",AB37-AB36) -> 30 | AF37: =IF(AE37="","",AB37-AB$29) -> 240 | AG37: =IF(AF37="","",IF(AF37<365,AF37*AC$25*AD37,365*AD37*AC$25)) -> 1.64 | AH37: =IF(AF37="","",IF(AF37<365,AF37*AC$26*AD37,365*AD37*AC$26)) -> 0.548 | AM37: =F37 -> 231.45
A38: =IF(A37<B$17,A37+1,"") -> 15 | B38: =IF(A38="","",IF(A38<=B$16,"carência","amortização")) -> amortização | C38: =IF(B38="","",E37*$C$23) -> 61.966667 | D38: =IF(C38="","",IF(A38<=B$16,0,E$23/(B$17-B$16))) -> 166.66667 | E38: =IF(F38="","",E37-D38) -> 3500 | F38: =IF(D38="","",D38+C38) -> 228.63333 | AA38: =IF(AA37<B$17,AA37+1,"") -> 9 | AB38: =IF(AA38="","",AB37+30) -> 46510 | AC38: =IF(AB38="","",IF(AA38<=B$16,AC37,AC37-AD38)) -> 4500 | AD38: =IF(AA38="","",IF(AA38<=B$16,0,B$15/(B$17-B$16))) -> 166.66667 | AE38: =IF(AD38="","",AB38-AB37) -> 30 | AF38: =IF(AE38="","",AB38-AB$29) -> 270 | AG38: =IF(AF38="","",IF(AF38<365,AF38*AC$25*AD38,365*AD38*AC$25)) -> 1.845 | AH38: =IF(AF38="","",IF(AF38<365,AF38*AC$26*AD38,365*AD38*AC$26)) -> 0.6165 | AM38: =F38 -> 228.63333
A39: =IF(A38<B$17,A38+1,"") -> 16 | B39: =IF(A39="","",IF(A39<=B$16,"carência","amortização")) -> amortização | C39: =IF(B39="","",E38*$C$23) -> 59.15 | D39: =IF(C39="","",IF(A39<=B$16,0,E$23/(B$17-B$16))) -> 166.66667 | E39: =IF(F39="","",E38-D39) -> 3333.3333 | F39: =IF(D39="","",D39+C39) -> 225.81667 | AA39: =IF(AA38<B$17,AA38+1,"") -> 10 | AB39: =IF(AA39="","",AB38+30) -> 46540 | AC39: =IF(AB39="","",IF(AA39<=B$16,AC38,AC38-AD39)) -> 4333.3333 | AD39: =IF(AA39="","",IF(AA39<=B$16,0,B$15/(B$17-B$16))) -> 166.66667 | AE39: =IF(AD39="","",AB39-AB38) -> 30 | AF39: =IF(AE39="","",AB39-AB$29) -> 300 | AG39: =IF(AF39="","",IF(AF39<365,AF39*AC$25*AD39,365*AD39*AC$25)) -> 2.05 | AH39: =IF(AF39="","",IF(AF39<365,AF39*AC$26*AD39,365*AD39*AC$26)) -> 0.685 | AM39: =F39 -> 225.81667
A40: =IF(A39<B$17,A39+1,"") -> 17 | B40: =IF(A40="","",IF(A40<=B$16,"carência","amortização")) -> amortização | C40: =IF(B40="","",E39*$C$23) -> 56.333333 | D40: =IF(C40="","",IF(A40<=B$16,0,E$23/(B$17-B$16))) -> 166.66667 | E40: =IF(F40="","",E39-D40) -> 3166.6667 | F40: =IF(D40="","",D40+C40) -> 223 | AA40: =IF(AA39<B$17,AA39+1,"") -> 11 | AB40: =IF(AA40="","",AB39+30) -> 46570 | AC40: =IF(AB40="","",IF(AA40<=B$16,AC39,AC39-AD40)) -> 4166.6667 | AD40: =IF(AA40="","",IF(AA40<=B$16,0,B$15/(B$17-B$16))) -> 166.66667 | AE40: =IF(AD40="","",AB40-AB39) -> 30 | AF40: =IF(AE40="","",AB40-AB$29) -> 330 | AG40: =IF(AF40="","",IF(AF40<365,AF40*AC$25*AD40,365*AD40*AC$25)) -> 2.255 | AH40: =IF(AF40="","",IF(AF40<365,AF40*AC$26*AD40,365*AD40*AC$26)) -> 0.7535 | AM40: =F40 -> 223
A41: =IF(A40<B$17,A40+1,"") -> 18 | B41: =IF(A41="","",IF(A41<=B$16,"carência","amortização")) -> amortização | C41: =IF(B41="","",E40*$C$23) -> 53.516667 | D41: =IF(C41="","",IF(A41<=B$16,0,E$23/(B$17-B$16))) -> 166.66667 | E41: =IF(F41="","",E40-D41) -> 3000 | F41: =IF(D41="","",D41+C41) -> 220.18333 | AA41: =IF(AA40<B$17,AA40+1,"") -> 12 | AB41: =IF(AA41="","",AB40+30) -> 46600 | AC41: =IF(AB41="","",IF(AA41<=B$16,AC40,AC40-AD41)) -> 4000 | AD41: =IF(AA41="","",IF(AA41<=B$16,0,B$15/(B$17-B$16))) -> 166.66667 | AE41: =IF(AD41="","",AB41-AB40) -> 30 | AF41: =IF(AE41="","",AB41-AB$29) -> 360 | AG41: =IF(AF41="","",IF(AF41<365,AF41*AC$25*AD41,365*AD41*AC$25)) -> 2.46 | AH41: =IF(AF41="","",IF(AF41<365,AF41*AC$26*AD41,365*AD41*AC$26)) -> 0.822 | AM41: =F41 -> 220.18333
A42: =IF(A41<B$17,A41+1,"") -> 19 | B42: =IF(A42="","",IF(A42<=B$16,"carência","amortização")) -> amortização | C42: =IF(B42="","",E41*$C$23) -> 50.7 | D42: =IF(C42="","",IF(A42<=B$16,0,E$23/(B$17-B$16))) -> 166.66667 | E42: =IF(F42="","",E41-D42) -> 2833.3333 | F42: =IF(D42="","",D42+C42) -> 217.36667 | AA42: =IF(AA41<B$17,AA41+1,"") -> 13 | AB42: =IF(AA42="","",AB41+30) -> 46630 | AC42: =IF(AA42="","",IF(AB42<=B$16,AC27,AC41-AD42)) -> 3833.3333 | AD42: =IF(AA42="","",IF(AA42<=B$16,0,B$15/(B$17-B$16))) -> 166.66667 | AE42: =IF(AD42="","",AB42-AB41) -> 30 | AF42: =IF(AE42="","",AB42-AB$29) -> 390 | AG42: =IF(AF42="","",IF(AF42<365,AF42*AC$25*AD42,365*AD42*AC$25)) -> 2.4941667 | AH42: =IF(AF42="","",IF(AF42<365,AF42*AC$26*AD42,365*AD42*AC$26)) -> 0.83341667 | AM42: =F42 -> 217.36667
A43: =IF(A42<B$17,A42+1,"") -> 20 | B43: =IF(A43="","",IF(A43<=B$16,"carência","amortização")) -> amortização | C43: =IF(B43="","",E42*$C$23) -> 47.883333 | D43: =IF(C43="","",IF(A43<=B$16,0,E$23/(B$17-B$16))) -> 166.66667 | E43: =IF(F43="","",E42-D43) -> 2666.6667 | F43: =IF(D43="","",D43+C43) -> 214.55 | AA43: =IF(AA42<B$17,AA42+1,"") -> 14 | AB43: =IF(AA43="","",AB42+30) -> 46660 | AC43: =IF(AB43="","",IF(AA43<=B$16,AC42,AC42-AD43)) -> 3666.6667 | AD43: =IF(AA43="","",IF(AA43<=B$16,0,B$15/(B$17-B$16))) -> 166.66667 | AE43: =IF(AD43="","",AB43-AB42) -> 30 | AF43: =IF(AE43="","",AB43-AB$29) -> 420 | AG43: =IF(AF43="","",IF(AF43<365,AF43*AC$25*AD43,365*AD43*AC$25)) -> 2.4941667 | AH43: =IF(AF43="","",IF(AF43<365,AF43*AC$26*AD43,365*AD43*AC$26)) -> 0.83341667 | AM43: =F43 -> 214.55
A44: =IF(A43<B$17,A43+1,"") -> 21 | B44: =IF(A44="","",IF(A44<=B$16,"carência","amortização")) -> amortização | C44: =IF(B44="","",E43*$C$23) -> 45.066667 | D44: =IF(C44="","",IF(A44<=B$16,0,E$23/(B$17-B$16))) -> 166.66667 | E44: =IF(F44="","",E43-D44) -> 2500 | F44: =IF(D44="","",D44+C44) -> 211.73333 | AA44: =IF(AA43<B$17,AA43+1,"") -> 15 | AB44: =IF(AA44="","",AB43+30) -> 46690 | AC44: =IF(AB44="","",IF(AA44<=B$16,AC43,AC43-AD44)) -> 3500 | AD44: =IF(AA44="","",IF(AA44<=B$16,0,B$15/(B$17-B$16))) -> 166.66667 | AE44: =IF(AD44="","",AB44-AB43) -> 30 | AF44: =IF(AE44="","",AB44-AB$29) -> 450 | AG44: =IF(AF44="","",IF(AF44<365,AF44*AC$25*AD44,365*AD44*AC$25)) -> 2.4941667 | AH44: =IF(AF44="","",IF(AF44<365,AF44*AC$26*AD44,365*AD44*AC$26)) -> 0.83341667 | AM44: =F44 -> 211.73333
A45: =IF(A44<B$17,A44+1,"") -> 22 | B45: =IF(A45="","",IF(A45<=B$16,"carência","amortização")) -> amortização | C45: =IF(B45="","",E44*$C$23) -> 42.25 | D45: =IF(C45="","",IF(A45<=B$16,0,E$23/(B$17-B$16))) -> 166.66667 | E45: =IF(F45="","",E44-D45) -> 2333.3333 | F45: =IF(D45="","",D45+C45) -> 208.91667 | AA45: =IF(AA44<B$17,AA44+1,"") -> 16 | AB45: =IF(AA45="","",AB44+30) -> 46720 | AC45: =IF(AB45="","",IF(AA45<=B$16,AC44,AC44-AD45)) -> 3333.3333 | AD45: =IF(AA45="","",IF(AA45<=B$16,0,B$15/(B$17-B$16))) -> 166.66667 | AE45: =IF(AD45="","",AB45-AB44) -> 30 | AF45: =IF(AE45="","",AB45-AB$29) -> 480 | AG45: =IF(AF45="","",IF(AF45<365,AF45*AC$25*AD45,365*AD45*AC$25)) -> 2.4941667 | AH45: =IF(AF45="","",IF(AF45<365,AF45*AC$26*AD45,365*AD45*AC$26)) -> 0.83341667 | AM45: =F45 -> 208.91667
A46: =IF(A45<B$17,A45+1,"") -> 23 | B46: =IF(A46="","",IF(A46<=B$16,"carência","amortização")) -> amortização | C46: =IF(B46="","",E45*$C$23) -> 39.433333 | D46: =IF(C46="","",IF(A46<=B$16,0,E$23/(B$17-B$16))) -> 166.66667 | E46: =IF(F46="","",E45-D46) -> 2166.6667 | F46: =IF(D46="","",D46+C46) -> 206.1 | AA46: =IF(AA45<B$17,AA45+1,"") -> 17 | AB46: =IF(AA46="","",AB45+30) -> 46750 | AC46: =IF(AB46="","",IF(AA46<=B$16,AC45,AC45-AD46)) -> 3166.6667 | AD46: =IF(AA46="","",IF(AA46<=B$16,0,B$15/(B$17-B$16))) -> 166.66667 | AE46: =IF(AD46="","",AB46-AB45) -> 30 | AF46: =IF(AE46="","",AB46-AB$29) -> 510 | AG46: =IF(AF46="","",IF(AF46<365,AF46*AC$25*AD46,365*AD46*AC$25)) -> 2.4941667 | AH46: =IF(AF46="","",IF(AF46<365,AF46*AC$26*AD46,365*AD46*AC$26)) -> 0.83341667 | AM46: =F46 -> 206.1
A47: =IF(A46<B$17,A46+1,"") -> 24 | B47: =IF(A47="","",IF(A47<=B$16,"carência","amortização")) -> amortização | C47: =IF(B47="","",E46*$C$23) -> 36.616667 | D47: =IF(C47="","",IF(A47<=B$16,0,E$23/(B$17-B$16))) -> 166.66667 | E47: =IF(F47="","",E46-D47) -> 2000 | F47: =IF(D47="","",D47+C47) -> 203.28333 | AA47: =IF(AA46<B$17,AA46+1,"") -> 18 | AB47: =IF(AA47="","",AB46+30) -> 46780 | AC47: =IF(AB47="","",IF(AA47<=B$16,AC46,AC46-AD47)) -> 3000 | AD47: =IF(AA47="","",IF(AA47<=B$16,0,B$15/(B$17-B$16))) -> 166.66667 | AE47: =IF(AD47="","",AB47-AB46) -> 30 | AF47: =IF(AE47="","",AB47-AB$29) -> 540 | AG47: =IF(AF47="","",IF(AF47<365,AF47*AC$25*AD47,365*AD47*AC$25)) -> 2.4941667 | AH47: =IF(AF47="","",IF(AF47<365,AF47*AC$26*AD47,365*AD47*AC$26)) -> 0.83341667 | AM47: =F47 -> 203.28333 | AN47: =SUM(F36:F47) -> 2625.3 | AO47: =LARGE(F36:F47,1) -> 234.26667
A48: =IF(A47<B$17,A47+1,"") -> 25 | B48: =IF(A48="","",IF(A48<=B$16,"carência","amortização")) -> amortização | C48: =IF(B48="","",E47*$C$23) -> 33.8 | D48: =IF(C48="","",IF(A48<=B$16,0,E$23/(B$17-B$16))) -> 166.66667 | E48: =IF(F48="","",E47-D48) -> 1833.3333 | F48: =IF(D48="","",D48+C48) -> 200.46667 | AA48: =IF(AA47<B$17,AA47+1,"") -> 19 | AB48: =IF(AA48="","",AB47+30) -> 46810 | AC48: =IF(AB48="","",IF(AA48<=B$16,AC47,AC47-AD48)) -> 2833.3333 | AD48: =IF(AA48="","",IF(AA48<=B$16,0,B$15/(B$17-B$16))) -> 166.66667 | AE48: =IF(AD48="","",AB48-AB47) -> 30 | AF48: =IF(AE48="","",AB48-AB$29) -> 570 | AG48: =IF(AF48="","",IF(AF48<365,AF48*AC$25*AD48,365*AD48*AC$25)) -> 2.4941667 | AH48: =IF(AF48="","",IF(AF48<365,AF48*AC$26*AD48,365*AD48*AC$26)) -> 0.83341667
A49: =IF(A48<B$17,A48+1,"") -> 26 | B49: =IF(A49="","",IF(A49<=B$16,"carência","amortização")) -> amortização | C49: =IF(B49="","",E48*$C$23) -> 30.983333 | D49: =IF(C49="","",IF(A49<=B$16,0,E$23/(B$17-B$16))) -> 166.66667 | E49: =IF(F49="","",E48-D49) -> 1666.6667 | F49: =IF(D49="","",D49+C49) -> 197.65 | AA49: =IF(AA48<B$17,AA48+1,"") -> 20 | AB49: =IF(AA49="","",AB48+30) -> 46840 | AC49: =IF(AB49="","",IF(AA49<=B$16,AC48,AC48-AD49)) -> 2666.6667 | AD49: =IF(AA49="","",IF(AA49<=B$16,0,B$15/(B$17-B$16))) -> 166.66667 | AE49: =IF(AD49="","",AB49-AB48) -> 30 | AF49: =IF(AE49="","",AB49-AB$29) -> 600 | AG49: =IF(AF49="","",IF(AF49<365,AF49*AC$25*AD49,365*AD49*AC$25)) -> 2.4941667 | AH49: =IF(AF49="","",IF(AF49<365,AF49*AC$26*AD49,365*AD49*AC$26)) -> 0.83341667
A50: =IF(A49<B$17,A49+1,"") -> 27 | B50: =IF(A50="","",IF(A50<=B$16,"carência","amortização")) -> amortização | C50: =IF(B50="","",E49*$C$23) -> 28.166667 | D50: =IF(C50="","",IF(A50<=B$16,0,E$23/(B$17-B$16))) -> 166.66667 | E50: =IF(F50="","",E49-D50) -> 1500 | F50: =IF(D50="","",D50+C50) -> 194.83333 | AA50: =IF(AA49<B$17,AA49+1,"") -> 21 | AB50: =IF(AA50="","",AB49+30) -> 46870 | AC50: =IF(AB50="","",IF(AA50<=B$16,AC49,AC49-AD50)) -> 2500 | AD50: =IF(AA50="","",IF(AA50<=B$16,0,B$15/(B$17-B$16))) -> 166.66667 | AE50: =IF(AD50="","",AB50-AB49) -> 30 | AF50: =IF(AE50="","",AB50-AB$29) -> 630 | AG50: =IF(AF50="","",IF(AF50<365,AF50*AC$25*AD50,365*AD50*AC$25)) -> 2.4941667 | AH50: =IF(AF50="","",IF(AF50<365,AF50*AC$26*AD50,365*AD50*AC$26)) -> 0.83341667
A51: =IF(A50<B$17,A50+1,"") -> 28 | B51: =IF(A51="","",IF(A51<=B$16,"carência","amortização")) -> amortização | C51: =IF(B51="","",E50*$C$23) -> 25.35 | D51: =IF(C51="","",IF(A51<=B$16,0,E$23/(B$17-B$16))) -> 166.66667 | E51: =IF(F51="","",E50-D51) -> 1333.3333 | F51: =IF(D51="","",D51+C51) -> 192.01667 | AA51: =IF(AA50<B$17,AA50+1,"") -> 22 | AB51: =IF(AA51="","",AB50+30) -> 46900 | AC51: =IF(AB51="","",IF(AA51<=B$16,AC50,AC50-AD51)) -> 2333.3333 | AD51: =IF(AA51="","",IF(AA51<=B$16,0,B$15/(B$17-B$16))) -> 166.66667 | AE51: =IF(AD51="","",AB51-AB50) -> 30 | AF51: =IF(AE51="","",AB51-AB$29) -> 660 | AG51: =IF(AF51="","",IF(AF51<365,AF51*AC$25*AD51,365*AD51*AC$25)) -> 2.4941667 | AH51: =IF(AF51="","",IF(AF51<365,AF51*AC$26*AD51,365*AD51*AC$26)) -> 0.83341667
A52: =IF(A51<B$17,A51+1,"") -> 29 | B52: =IF(A52="","",IF(A52<=B$16,"carência","amortização")) -> amortização | C52: =IF(B52="","",E51*$C$23) -> 22.533333 | D52: =IF(C52="","",IF(A52<=B$16,0,E$23/(B$17-B$16))) -> 166.66667 | E52: =IF(F52="","",E51-D52) -> 1166.6667 | F52: =IF(D52="","",D52+C52) -> 189.2 | AA52: =IF(AA51<B$17,AA51+1,"") -> 23 | AB52: =IF(AA52="","",AB51+30) -> 46930 | AC52: =IF(AB52="","",IF(AA52<=B$16,AC51,AC51-AD52)) -> 2166.6667 | AD52: =IF(AA52="","",IF(AA52<=B$16,0,B$15/(B$17-B$16))) -> 166.66667 | AE52: =IF(AD52="","",AB52-AB51) -> 30 | AF52: =IF(AE52="","",AB52-AB$29) -> 690 | AG52: =IF(AF52="","",IF(AF52<365,AF52*AC$25*AD52,365*AD52*AC$25)) -> 2.4941667 | AH52: =IF(AF52="","",IF(AF52<365,AF52*AC$26*AD52,365*AD52*AC$26)) -> 0.83341667
A53: =IF(A52<B$17,A52+1,"") -> 30 | B53: =IF(A53="","",IF(A53<=B$16,"carência","amortização")) -> amortização | C53: =IF(B53="","",E52*$C$23) -> 19.716667 | D53: =IF(C53="","",IF(A53<=B$16,0,E$23/(B$17-B$16))) -> 166.66667 | E53: =IF(F53="","",E52-D53) -> 1000 | F53: =IF(D53="","",D53+C53) -> 186.38333 | AA53: =IF(AA52<B$17,AA52+1,"") -> 24 | AB53: =IF(AA53="","",AB52+30) -> 46960 | AC53: =IF(AB53="","",IF(AA53<=B$16,AC52,AC52-AD53)) -> 2000 | AD53: =IF(AA53="","",IF(AA53<=B$16,0,B$15/(B$17-B$16))) -> 166.66667 | AE53: =IF(AD53="","",AB53-AB52) -> 30 | AF53: =IF(AE53="","",AB53-AB$29) -> 720 | AG53: =IF(AF53="","",IF(AF53<365,AF53*AC$25*AD53,365*AD53*AC$25)) -> 2.4941667 | AH53: =IF(AF53="","",IF(AF53<365,AF53*AC$26*AD53,365*AD53*AC$26)) -> 0.83341667
A54: =IF(A53<B$17,A53+1,"") -> 31 | B54: =IF(A54="","",IF(A54<=B$16,"carência","amortização")) -> amortização | C54: =IF(B54="","",E53*$C$23) -> 16.9 | D54: =IF(C54="","",IF(A54<=B$16,0,E$23/(B$17-B$16))) -> 166.66667 | E54: =IF(F54="","",E53-D54) -> 833.33333 | F54: =IF(D54="","",D54+C54) -> 183.56667 | AA54: =IF(AA53<B$17,AA53+1,"") -> 25 | AB54: =IF(AA54="","",AB53+30) -> 46990 | AC54: =IF(AB54="","",IF(AA54<=B$16,AC53,AC53-AD54)) -> 1833.3333 | AD54: =IF(AA54="","",IF(AA54<=B$16,0,B$15/(B$17-B$16))) -> 166.66667 | AE54: =IF(AD54="","",AB54-AB53) -> 30 | AF54: =IF(AE54="","",AB54-AB$29) -> 750 | AG54: =IF(AF54="","",IF(AF54<365,AF54*AC$25*AD54,365*AD54*AC$25)) -> 2.4941667 | AH54: =IF(AF54="","",IF(AF54<365,AF54*AC$26*AD54,365*AD54*AC$26)) -> 0.83341667
A55: =IF(A54<B$17,A54+1,"") -> 32 | B55: =IF(A55="","",IF(A55<=B$16,"carência","amortização")) -> amortização | C55: =IF(B55="","",E54*$C$23) -> 14.083333 | D55: =IF(C55="","",IF(A55<=B$16,0,E$23/(B$17-B$16))) -> 166.66667 | E55: =IF(F55="","",E54-D55) -> 666.66667 | F55: =IF(D55="","",D55+C55) -> 180.75 | AA55: =IF(AA54<B$17,AA54+1,"") -> 26 | AB55: =IF(AA55="","",AB54+30) -> 47020 | AC55: =IF(AB55="","",IF(AA55<=B$16,AC54,AC54-AD55)) -> 1666.6667 | AD55: =IF(AA55="","",IF(AA55<=B$16,0,B$15/(B$17-B$16))) -> 166.66667 | AE55: =IF(AD55="","",AB55-AB54) -> 30 | AF55: =IF(AE55="","",AB55-AB$29) -> 780 | AG55: =IF(AF55="","",IF(AF55<365,AF55*AC$25*AD55,365*AD55*AC$25)) -> 2.4941667 | AH55: =IF(AF55="","",IF(AF55<365,AF55*AC$26*AD55,365*AD55*AC$26)) -> 0.83341667
A56: =IF(A55<B$17,A55+1,"") -> 33 | B56: =IF(A56="","",IF(A56<=B$16,"carência","amortização")) -> amortização | C56: =IF(B56="","",E55*$C$23) -> 11.266667 | D56: =IF(C56="","",IF(A56<=B$16,0,E$23/(B$17-B$16))) -> 166.66667 | E56: =IF(F56="","",E55-D56) -> 500 | F56: =IF(D56="","",D56+C56) -> 177.93333 | AA56: =IF(AA55<B$17,AA55+1,"") -> 27 | AB56: =IF(AA56="","",AB55+30) -> 47050 | AC56: =IF(AB56="","",IF(AA56<=B$16,AC55,AC55-AD56)) -> 1500 | AD56: =IF(AA56="","",IF(AA56<=B$16,0,B$15/(B$17-B$16))) -> 166.66667 | AE56: =IF(AD56="","",AB56-AB55) -> 30 | AF56: =IF(AE56="","",AB56-AB$29) -> 810 | AG56: =IF(AF56="","",IF(AF56<365,AF56*AC$25*AD56,365*AD56*AC$25)) -> 2.4941667 | AH56: =IF(AF56="","",IF(AF56<365,AF56*AC$26*AD56,365*AD56*AC$26)) -> 0.83341667
A57: =IF(A56<B$17,A56+1,"") -> 34 | B57: =IF(A57="","",IF(A57<=B$16,"carência","amortização")) -> amortização | C57: =IF(B57="","",E56*$C$23) -> 8.45 | D57: =IF(C57="","",IF(A57<=B$16,0,E$23/(B$17-B$16))) -> 166.66667 | E57: =IF(F57="","",E56-D57) -> 333.33333 | F57: =IF(D57="","",D57+C57) -> 175.11667 | AA57: =IF(AA56<B$17,AA56+1,"") -> 28 | AB57: =IF(AA57="","",AB56+30) -> 47080 | AC57: =IF(AB57="","",IF(AA57<=B$16,AC56,AC56-AD57)) -> 1333.3333 | AD57: =IF(AA57="","",IF(AA57<=B$16,0,B$15/(B$17-B$16))) -> 166.66667 | AE57: =IF(AD57="","",AB57-AB56) -> 30 | AF57: =IF(AE57="","",AB57-AB$29) -> 840 | AG57: =IF(AF57="","",IF(AF57<365,AF57*AC$25*AD57,365*AD57*AC$25)) -> 2.4941667 | AH57: =IF(AF57="","",IF(AF57<365,AF57*AC$26*AD57,365*AD57*AC$26)) -> 0.83341667
A58: =IF(A57<B$17,A57+1,"") -> 35 | B58: =IF(A58="","",IF(A58<=B$16,"carência","amortização")) -> amortização | C58: =IF(B58="","",E57*$C$23) -> 5.6333333 | D58: =IF(C58="","",IF(A58<=B$16,0,E$23/(B$17-B$16))) -> 166.66667 | E58: =IF(F58="","",E57-D58) -> 166.66667 | F58: =IF(D58="","",D58+C58) -> 172.3 | AA58: =IF(AA57<B$17,AA57+1,"") -> 29 | AB58: =IF(AA58="","",AB57+30) -> 47110 | AC58: =IF(AB58="","",IF(AA58<=B$16,AC57,AC57-AD58)) -> 1166.6667 | AD58: =IF(AA58="","",IF(AA58<=B$16,0,B$15/(B$17-B$16))) -> 166.66667 | AE58: =IF(AD58="","",AB58-AB57) -> 30 | AF58: =IF(AE58="","",AB58-AB$29) -> 870 | AG58: =IF(AF58="","",IF(AF58<365,AF58*AC$25*AD58,365*AD58*AC$25)) -> 2.4941667 | AH58: =IF(AF58="","",IF(AF58<365,AF58*AC$26*AD58,365*AD58*AC$26)) -> 0.83341667
A59: =IF(A58<B$17,A58+1,"") -> 36 | B59: =IF(A59="","",IF(A59<=B$16,"carência","amortização")) -> amortização | C59: =IF(B59="","",E58*$C$23) -> 2.8166667 | D59: =IF(C59="","",IF(A59<=B$16,0,E$23/(B$17-B$16))) -> 166.66667 | E59: =IF(F59="","",E58-D59) -> 5.6843419e-14 | F59: =IF(D59="","",D59+C59) -> 169.48333 | AA59: =IF(AA58<B$17,AA58+1,"") -> 30 | AB59: =IF(AA59="","",AB58+30) -> 47140 | AC59: =IF(AB59="","",IF(AA59<=B$16,AC58,AC58-AD59)) -> 1000 | AD59: =IF(AA59="","",IF(AA59<=B$16,0,B$15/(B$17-B$16))) -> 166.66667 | AE59: =IF(AD59="","",AB59-AB58) -> 30 | AF59: =IF(AE59="","",AB59-AB$29) -> 900 | AG59: =IF(AF59="","",IF(AF59<365,AF59*AC$25*AD59,365*AD59*AC$25)) -> 2.4941667 | AH59: =IF(AF59="","",IF(AF59<365,AF59*AC$26*AD59,365*AD59*AC$26)) -> 0.83341667 | AN59: =SUM(F48:F59) -> 2219.7 | AO59: =LARGE(F48:F59,1) -> 200.46667
A60: =IF(A59<B$17,A59+1,"") | B60: =IF(A60="","",IF(A60<=B$16,"carência","amortização")) | C60: =IF(B60="","",E59*$C$23) | D60: =IF(C60="","",IF(A60<=B$16,0,E$23/(B$17-B$16))) | E60: =IF(F60="","",E59-D60) | F60: =IF(D60="","",D60+C60) | AA60: =IF(AA59<B$17,AA59+1,"") -> 31 | AB60: =IF(AA60="","",AB59+30) -> 47170 | AC60: =IF(AB60="","",IF(AA60<=B$16,AC59,AC59-AD60)) -> 833.33333 | AD60: =IF(AA60="","",IF(AA60<=B$16,0,B$15/(B$17-B$16))) -> 166.66667 | AE60: =IF(AD60="","",AB60-AB59) -> 30 | AF60: =IF(AE60="","",AB60-AB$29) -> 930 | AG60: =IF(AF60="","",IF(AF60<365,AF60*AC$25*AD60,365*AD60*AC$25)) -> 2.4941667 | AH60: =IF(AF60="","",IF(AF60<365,AF60*AC$26*AD60,365*AD60*AC$26)) -> 0.83341667
A61: =IF(A60<B$17,A60+1,"") | B61: =IF(A61="","",IF(A61<=B$16,"carência","amortização")) | C61: =IF(B61="","",E60*$C$23) | D61: =IF(C61="","",IF(A61<=B$16,0,E$23/(B$17-B$16))) | E61: =IF(F61="","",E60-D61) | F61: =IF(D61="","",D61+C61) | AA61: =IF(AA60<B$17,AA60+1,"") -> 32 | AB61: =IF(AA61="","",AB60+30) -> 47200 | AC61: =IF(AB61="","",IF(AA61<=B$16,AC60,AC60-AD61)) -> 666.66667 | AD61: =IF(AA61="","",IF(AA61<=B$16,0,B$15/(B$17-B$16))) -> 166.66667 | AE61: =IF(AD61="","",AB61-AB60) -> 30 | AF61: =IF(AE61="","",AB61-AB$29) -> 960 | AG61: =IF(AF61="","",IF(AF61<365,AF61*AC$25*AD61,365*AD61*AC$25)) -> 2.4941667 | AH61: =IF(AF61="","",IF(AF61<365,AF61*AC$26*AD61,365*AD61*AC$26)) -> 0.83341667
A62: =IF(A61<B$17,A61+1,"") | B62: =IF(A62="","",IF(A62<=B$16,"carência","amortização")) | C62: =IF(B62="","",E61*$C$23) | D62: =IF(C62="","",IF(A62<=B$16,0,E$23/(B$17-B$16))) | E62: =IF(F62="","",E61-D62) | F62: =IF(D62="","",D62+C62) | AA62: =IF(AA61<B$17,AA61+1,"") -> 33 | AB62: =IF(AA62="","",AB61+30) -> 47230 | AC62: =IF(AB62="","",IF(AA62<=B$16,AC61,AC61-AD62)) -> 500 | AD62: =IF(AA62="","",IF(AA62<=B$16,0,B$15/(B$17-B$16))) -> 166.66667 | AE62: =IF(AD62="","",AB62-AB61) -> 30 | AF62: =IF(AE62="","",AB62-AB$29) -> 990 | AG62: =IF(AF62="","",IF(AF62<365,AF62*AC$25*AD62,365*AD62*AC$25)) -> 2.4941667 | AH62: =IF(AF62="","",IF(AF62<365,AF62*AC$26*AD62,365*AD62*AC$26)) -> 0.83341667
A63: =IF(A62<B$17,A62+1,"") | B63: =IF(A63="","",IF(A63<=B$16,"carência","amortização")) | C63: =IF(B63="","",E62*$C$23) | D63: =IF(C63="","",IF(A63<=B$16,0,E$23/(B$17-B$16))) | E63: =IF(F63="","",E62-D63) | F63: =IF(D63="","",D63+C63) | AA63: =IF(AA62<B$17,AA62+1,"") -> 34 | AB63: =IF(AA63="","",AB62+30) -> 47260 | AC63: =IF(AB63="","",IF(AA63<=B$16,AC62,AC62-AD63)) -> 333.33333 | AD63: =IF(AA63="","",IF(AA63<=B$16,0,B$15/(B$17-B$16))) -> 166.66667 | AE63: =IF(AD63="","",AB63-AB62) -> 30 | AF63: =IF(AE63="","",AB63-AB$29) -> 1020 | AG63: =IF(AF63="","",IF(AF63<365,AF63*AC$25*AD63,365*AD63*AC$25)) -> 2.4941667 | AH63: =IF(AF63="","",IF(AF63<365,AF63*AC$26*AD63,365*AD63*AC$26)) -> 0.83341667
A64: =IF(A63<B$17,A63+1,"") | B64: =IF(A64="","",IF(A64<=B$16,"carência","amortização")) | C64: =IF(B64="","",E63*$C$23) | D64: =IF(C64="","",IF(A64<=B$16,0,E$23/(B$17-B$16))) | E64: =IF(F64="","",E63-D64) | F64: =IF(D64="","",D64+C64) | AA64: =IF(AA63<B$17,AA63+1,"") -> 35 | AB64: =IF(AA64="","",AB63+30) -> 47290 | AC64: =IF(AB64="","",IF(AA64<=B$16,AC63,AC63-AD64)) -> 166.66667 | AD64: =IF(AA64="","",IF(AA64<=B$16,0,B$15/(B$17-B$16))) -> 166.66667 | AE64: =IF(AD64="","",AB64-AB63) -> 30 | AF64: =IF(AE64="","",AB64-AB$29) -> 1050 | AG64: =IF(AF64="","",IF(AF64<365,AF64*AC$25*AD64,365*AD64*AC$25)) -> 2.4941667 | AH64: =IF(AF64="","",IF(AF64<365,AF64*AC$26*AD64,365*AD64*AC$26)) -> 0.83341667
A65: =IF(A64<B$17,A64+1,"") | B65: =IF(A65="","",IF(A65<=B$16,"carência","amortização")) | C65: =IF(B65="","",E64*$C$23) | D65: =IF(C65="","",IF(A65<=B$16,0,E$23/(B$17-B$16))) | E65: =IF(F65="","",E64-D65) | F65: =IF(D65="","",D65+C65) | AA65: =IF(AA64<B$17,AA64+1,"") -> 36 | AB65: =IF(AA65="","",AB64+30) -> 47320 | AC65: =IF(AB65="","",IF(AA65<=B$16,AC64,AC64-AD65)) -> 5.6843419e-14 | AD65: =IF(AA65="","",IF(AA65<=B$16,0,B$15/(B$17-B$16))) -> 166.66667 | AE65: =IF(AD65="","",AB65-AB64) -> 30 | AF65: =IF(AE65="","",AB65-AB$29) -> 1080 | AG65: =IF(AF65="","",IF(AF65<365,AF65*AC$25*AD65,365*AD65*AC$25)) -> 2.4941667 | AH65: =IF(AF65="","",IF(AF65<365,AF65*AC$26*AD65,365*AD65*AC$26)) -> 0.83341667
A66: =IF(A65<B$17,A65+1,"") | B66: =IF(A66="","",IF(A66<=B$16,"carência","amortização")) | C66: =IF(B66="","",E65*$C$23) | D66: =IF(C66="","",IF(A66<=B$16,0,E$23/(B$17-B$16))) | E66: =IF(F66="","",E65-D66) | F66: =IF(D66="","",D66+C66) | AA66: =IF(AA65<B$17,AA65+1,"") | AB66: =IF(AA66="","",AB65+30) | AC66: =IF(AB66="","",IF(AA66<=B$16,AC65,AC65-AD66)) | AD66: =IF(AA66="","",IF(AA66<=B$16,0,B$15/(B$17-B$16))) | AE66: =IF(AD66="","",AB66-AB65) | AF66: =IF(AE66="","",AB66-AB$29) | AG66: =IF(AF66="","",IF(AF66<365,AF66*AC$25*AD66,365*AD66*AC$25)) | AH66: =IF(AF66="","",IF(AF66<365,AF66*AC$26*AD66,365*AD66*AC$26))
A67: =IF(A66<B$17,A66+1,"") | B67: =IF(A67="","",IF(A67<=B$16,"carência","amortização")) | C67: =IF(B67="","",E66*$C$23) | D67: =IF(C67="","",IF(A67<=B$16,0,E$23/(B$17-B$16))) | E67: =IF(F67="","",E66-D67) | F67: =IF(D67="","",D67+C67) | AA67: =IF(AA66<B$17,AA66+1,"") | AB67: =IF(AA67="","",AB66+30) | AC67: =IF(AB67="","",IF(AA67<=B$16,AC66,AC66-AD67)) | AD67: =IF(AA67="","",IF(AA67<=B$16,0,B$15/(B$17-B$16))) | AE67: =IF(AD67="","",AB67-AB66) | AF67: =IF(AE67="","",AB67-AB$29) | AG67: =IF(AF67="","",IF(AF67<365,AF67*AC$25*AD67,365*AD67*AC$25)) | AH67: =IF(AF67="","",IF(AF67<365,AF67*AC$26*AD67,365*AD67*AC$26))
A68: =IF(A67<B$17,A67+1,"") | B68: =IF(A68="","",IF(A68<=B$16,"carência","amortização")) | C68: =IF(B68="","",E67*$C$23) | D68: =IF(C68="","",IF(A68<=B$16,0,E$23/(B$17-B$16))) | E68: =IF(F68="","",E67-D68) | F68: =IF(D68="","",D68+C68) | AA68: =IF(AA67<B$17,AA67+1,"") | AB68: =IF(AA68="","",AB67+30) | AC68: =IF(AB68="","",IF(AA68<=B$16,AC67,AC67-AD68)) | AD68: =IF(AA68="","",IF(AA68<=B$16,0,B$15/(B$17-B$16))) | AE68: =IF(AD68="","",AB68-AB67) | AF68: =IF(AE68="","",AB68-AB$29) | AG68: =IF(AF68="","",IF(AF68<365,AF68*AC$25*AD68,365*AD68*AC$25)) | AH68: =IF(AF68="","",IF(AF68<365,AF68*AC$26*AD68,365*AD68*AC$26))
A69: =IF(A68<B$17,A68+1,"") | B69: =IF(A69="","",IF(A69<=B$16,"carência","amortização")) | C69: =IF(B69="","",E68*$C$23) | D69: =IF(C69="","",IF(A69<=B$16,0,E$23/(B$17-B$16))) | E69: =IF(F69="","",E68-D69) | F69: =IF(D69="","",D69+C69) | AA69: =IF(AA68<B$17,AA68+1,"") | AB69: =IF(AA69="","",AB68+30) | AC69: =IF(AB69="","",IF(AA69<=B$16,AC68,AC68-AD69)) | AD69: =IF(AA69="","",IF(AA69<=B$16,0,B$15/(B$17-B$16))) | AE69: =IF(AD69="","",AB69-AB68) | AF69: =IF(AE69="","",AB69-AB$29) | AG69: =IF(AF69="","",IF(AF69<365,AF69*AC$25*AD69,365*AD69*AC$25)) | AH69: =IF(AF69="","",IF(AF69<365,AF69*AC$26*AD69,365*AD69*AC$26))
A70: =IF(A69<B$17,A69+1,"") | B70: =IF(A70="","",IF(A70<=B$16,"carência","amortização")) | C70: =IF(B70="","",E69*$C$23) | D70: =IF(C70="","",IF(A70<=B$16,0,E$23/(B$17-B$16))) | E70: =IF(F70="","",E69-D70) | F70: =IF(D70="","",D70+C70) | AA70: =IF(AA69<B$17,AA69+1,"") | AB70: =IF(AA70="","",AB69+30) | AC70: =IF(AB70="","",IF(AA70<=B$16,AC69,AC69-AD70)) | AD70: =IF(AA70="","",IF(AA70<=B$16,0,B$15/(B$17-B$16))) | AE70: =IF(AD70="","",AB70-AB69) | AF70: =IF(AE70="","",AB70-AB$29) | AG70: =IF(AF70="","",IF(AF70<365,AF70*AC$25*AD70,365*AD70*AC$25)) | AH70: =IF(AF70="","",IF(AF70<365,AF70*AC$26*AD70,365*AD70*AC$26))
A71: =IF(A70<B$17,A70+1,"") | B71: =IF(A71="","",IF(A71<=B$16,"carência","amortização")) | C71: =IF(B71="","",E70*$C$23) | D71: =IF(C71="","",IF(A71<=B$16,0,E$23/(B$17-B$16))) | E71: =IF(F71="","",E70-D71) | F71: =IF(D71="","",D71+C71) | AA71: =IF(AA70<B$17,AA70+1,"") | AB71: =IF(AA71="","",AB70+30) | AC71: =IF(AB71="","",IF(AA71<=B$16,AC70,AC70-AD71)) | AD71: =IF(AA71="","",IF(AA71<=B$16,0,B$15/(B$17-B$16))) | AE71: =IF(AD71="","",AB71-AB70) | AF71: =IF(AE71="","",AB71-AB$29) | AG71: =IF(AF71="","",IF(AF71<365,AF71*AC$25*AD71,365*AD71*AC$25)) | AH71: =IF(AF71="","",IF(AF71<365,AF71*AC$26*AD71,365*AD71*AC$26))
AA72: =IF(AA71<B$17,AA71+1,"") | AB72: =IF(AA72="","",AB71+30) | AC72: =IF(AB72="","",IF(AA72<=B$16,AC71,AC71-AD72)) | AD72: =IF(AA72="","",IF(AA72<=B$16,0,B$15/(B$17-B$16))) | AE72: =IF(AD72="","",AB72-AB71) | AF72: =IF(AE72="","",AB72-AB$29) | AG72: =IF(AF72="","",IF(AF72<365,AF72*AC$25*AD72,365*AD72*AC$25)) | AH72: =IF(AF72="","",IF(AF72<365,AF72*AC$26*AD72,365*AD72*AC$26))
AA73: =IF(AA72<B$17,AA72+1,"") | AB73: =IF(AA73="","",AB72+30) | AC73: =IF(AB73="","",IF(AA73<=B$16,AC72,AC72-AD73)) | AD73: =IF(AA73="","",IF(AA73<=B$16,0,B$15/(B$17-B$16))) | AE73: =IF(AD73="","",AB73-AB72) | AF73: =IF(AE73="","",AB73-AB$29) | AG73: =IF(AF73="","",IF(AF73<365,AF73*AC$25*AD73,365*AD73*AC$25)) | AH73: =IF(AF73="","",IF(AF73<365,AF73*AC$26*AD73,365*AD73*AC$26))
AA74: =IF(AA73<B$17,AA73+1,"") | AB74: =IF(AA74="","",AB73+30) | AC74: =IF(AB74="","",IF(AA74<=B$16,AC73,AC73-AD74)) | AD74: =IF(AA74="","",IF(AA74<=B$16,0,B$15/(B$17-B$16))) | AE74: =IF(AD74="","",AB74-AB73) | AF74: =IF(AE74="","",AB74-AB$29) | AG74: =IF(AF74="","",IF(AF74<365,AF74*AC$25*AD74,365*AD74*AC$25)) | AH74: =IF(AF74="","",IF(AF74<365,AF74*AC$26*AD74,365*AD74*AC$26))
AA75: =IF(AA74<B$17,AA74+1,"") | AB75: =IF(AA75="","",AB74+30) | AC75: =IF(AB75="","",IF(AA75<=B$16,AC74,AC74-AD75)) | AD75: =IF(AA75="","",IF(AA75<=B$16,0,B$15/(B$17-B$16))) | AE75: =IF(AD75="","",AB75-AB74) | AF75: =IF(AE75="","",AB75-AB$29) | AG75: =IF(AF75="","",IF(AF75<365,AF75*AC$25*AD75,365*AD75*AC$25)) | AH75: =IF(AF75="","",IF(AF75<365,AF75*AC$26*AD75,365*AD75*AC$26))
AA76: =IF(AA75<B$17,AA75+1,"") | AB76: =IF(AA76="","",AB75+30) | AC76: =IF(AB76="","",IF(AA76<=B$16,AC75,AC75-AD76)) | AD76: =IF(AA76="","",IF(AA76<=B$16,0,B$15/(B$17-B$16))) | AE76: =IF(AD76="","",AB76-AB75) | AF76: =IF(AE76="","",AB76-AB$29) | AG76: =IF(AF76="","",IF(AF76<365,AF76*AC$25*AD76,365*AD76*AC$25)) | AH76: =IF(AF76="","",IF(AF76<365,AF76*AC$26*AD76,365*AD76*AC$26))
AA77: =IF(AA76<B$17,AA76+1,"") | AB77: =IF(AA77="","",AB76+30) | AC77: =IF(AB77="","",IF(AA77<=B$16,AC76,AC76-AD77)) | AD77: =IF(AA77="","",IF(AA77<=B$16,0,B$15/(B$17-B$16))) | AE77: =IF(AD77="","",AB77-AB76) | AF77: =IF(AE77="","",AB77-AB$29) | AG77: =IF(AF77="","",IF(AF77<365,AF77*AC$25*AD77,365*AD77*AC$25)) | AH77: =IF(AF77="","",IF(AF77<365,AF77*AC$26*AD77,365*AD77*AC$26))
AA78: =IF(AA77<B$17,AA77+1,"") | AC78: =IF(AB78="","",IF(AA78<=B$16,AC77,AC77-AD78)) | AD78: =IF(AA78="","",IF(AA78<=B$16,0,B$15/(B$17-B$16))) | AF78: =IF(AE78="","",AB78-AB$29) | AG78: =IF(AF78="","",IF(AF78<365,AF78*AC$25*AD78,365*AD78*AC$25)) | AH78: =IF(AF78="","",IF(AF78<365,AF78*AC$26*AD78,365*AD78*AC$26))
AA79: =IF(AA78<B$17,AA78+1,"") | AC79: =IF(AB79="","",IF(AA79<=B$16,AC78,AC78-AD79)) | AD79: =IF(AA79="","",IF(AA79<=B$16,0,B$15/(B$17-B$16))) | AF79: =IF(AE79="","",AB79-AB$29) | AG79: =IF(AF79="","",IF(AF79<365,AF79*AC$25*AD79,365*AD79*AC$25)) | AH79: =IF(AF79="","",IF(AF79<365,AF79*AC$26*AD79,365*AD79*AC$26))
AA80: =IF(AA79<B$17,AA79+1,"") | AC80: =IF(AB80="","",IF(AA80<=B$16,AC79,AC79-AD80)) | AD80: =IF(AA80="","",IF(AA80<=B$16,0,B$15/(B$17-B$16))) | AF80: =IF(AE80="","",AB80-AB$29) | AG80: =IF(AF80="","",IF(AF80<365,AF80*AC$25*AD80,365*AD80*AC$25)) | AH80: =IF(AF80="","",IF(AF80<365,AF80*AC$26*AD80,365*AD80*AC$26))
AA81: =IF(AA80<B$17,AA80+1,"") | AC81: =IF(AB81="","",IF(AA81<=B$16,AC80,AC80-AD81)) | AD81: =IF(AA81="","",IF(AA81<=B$16,0,B$15/(B$17-B$16))) | AF81: =IF(AE81="","",AB81-AB$29) | AG81: =IF(AF81="","",IF(AF81<365,AF81*AC$25*AD81,365*AD81*AC$25)) | AH81: =IF(AF81="","",IF(AF81<365,AF81*AC$26*AD81,365*AD81*AC$26))
AA82: =IF(AA81<B$17,AA81+1,"") | AC82: =IF(AB82="","",IF(AA82<=B$16,AC81,AC81-AD82)) | AD82: =IF(AA82="","",IF(AA82<=B$16,0,B$15/(B$17-B$16))) | AF82: =IF(AE82="","",AB82-AB$29) | AG82: =IF(AF82="","",IF(AF82<365,AF82*AC$25*AD82,365*AD82*AC$25)) | AH82: =IF(AF82="","",IF(AF82<365,AF82*AC$26*AD82,365*AD82*AC$26))
AA83: =IF(AA82<B$17,AA82+1,"") | AC83: =IF(AB83="","",IF(AA83<=B$16,AC82,AC82-AD83)) | AD83: =IF(AA83="","",IF(AA83<=B$16,0,B$15/(B$17-B$16))) | AF83: =IF(AE83="","",AB83-AB$29) | AG83: =IF(AF83="","",IF(AF83<365,AF83*AC$25*AD83,365*AD83*AC$25)) | AH83: =IF(AF83="","",IF(AF83<365,AF83*AC$26*AD83,365*AD83*AC$26))
AA84: =IF(AA83<B$17,AA83+1,"") | AC84: =IF(AB84="","",IF(AA84<=B$16,AC83,AC83-AD84)) | AD84: =IF(AA84="","",IF(AA84<=B$16,0,B$15/(B$17-B$16))) | AF84: =IF(AE84="","",AB84-AB$29) | AG84: =IF(AF84="","",IF(AF84<365,AF84*AC$25*AD84,365*AD84*AC$25)) | AH84: =IF(AF84="","",IF(AF84<365,AF84*AC$26*AD84,365*AD84*AC$26))
AA85: =IF(AA84<B$17,AA84+1,"") | AC85: =IF(AB85="","",IF(AA85<=B$16,AC84,AC84-AD85)) | AD85: =IF(AA85="","",IF(AA85<=B$16,0,B$15/(B$17-B$16))) | AF85: =IF(AE85="","",AB85-AB$29) | AG85: =IF(AF85="","",IF(AF85<365,AF85*AC$25*AD85,365*AD85*AC$25)) | AH85: =IF(AF85="","",IF(AF85<365,AF85*AC$26*AD85,365*AD85*AC$26))
AA86: =IF(AA85<B$17,AA85+1,"") | AC86: =IF(AB86="","",IF(AA86<=B$16,AC85,AC85-AD86)) | AD86: =IF(AA86="","",IF(AA86<=B$16,0,B$15/(B$17-B$16))) | AF86: =IF(AE86="","",AB86-AB$29) | AG86: =IF(AF86="","",IF(AF86<365,AF86*AC$25*AD86,365*AD86*AC$25)) | AH86: =IF(AF86="","",IF(AF86<365,AF86*AC$26*AD86,365*AD86*AC$26))
AA87: =IF(AA86<B$17,AA86+1,"") | AC87: =IF(AB87="","",IF(AA87<=B$16,AC86,AC86-AD87)) | AD87: =IF(AA87="","",IF(AA87<=B$16,0,B$15/(B$17-B$16))) | AF87: =IF(AE87="","",AB87-AB$29) | AG87: =IF(AF87="","",IF(AF87<365,AF87*AC$25*AD87,365*AD87*AC$25)) | AH87: =IF(AF87="","",IF(AF87<365,AF87*AC$26*AD87,365*AD87*AC$26))
AA88: =IF(AA87<B$17,AA87+1,"") | AC88: =IF(AB88="","",IF(AA88<=B$16,AC87,AC87-AD88)) | AD88: =IF(AA88="","",IF(AA88<=B$16,0,B$15/(B$17-B$16))) | AF88: =IF(AE88="","",AB88-AB$29) | AG88: =IF(AF88="","",IF(AF88<365,AF88*AC$25*AD88,365*AD88*AC$25)) | AH88: =IF(AF88="","",IF(AF88<365,AF88*AC$26*AD88,365*AD88*AC$26))
AA89: =IF(AA88<B$17,AA88+1,"") | AC89: =IF(AB89="","",IF(AA89<=B$16,AC88,AC88-AD89)) | AD89: =IF(AA89="","",IF(AA89<=B$16,0,B$15/(B$17-B$16))) | AF89: =IF(AE89="","",AB89-AB$29) | AG89: =IF(AF89="","",IF(AF89<365,AF89*AC$25*AD89,365*AD89*AC$25)) | AH89: =IF(AF89="","",IF(AF89<365,AF89*AC$26*AD89,365*AD89*AC$26))
... AA229: =IF(AA228<B$17,AA228+1,"") | AC229: =IF(AB229="","",IF(AA229<=B$16,AC228,AC228-AD229)) | AD229: =IF(AA229="","",IF(AA229<=B$16,0,B$15/(B$17-B$16))) | AF229: =IF(AE229="","",AB229-AB$29) | AG229: =IF(AF229="","",IF(AF229<365,AF229*AC$25*AD229,365*AD229*AC$25)) | AH229: =IF(AF229="","",IF(AF229<365,AF229*AC$26*AD229,365*AD229*AC$26))
AA230: =IF(AA229<B$17,AA229+1,"") | AC230: =IF(AB230="","",IF(AA230<=B$16,AC229,AC229-AD230)) | AD230: =IF(AA230="","",IF(AA230<=B$16,0,B$15/(B$17-B$16))) | AG230: =IF(AF230="","",IF(AF230<365,AF230*AC$25*AD230,365*AD230*AC$25)) | AH230: =IF(AF230="","",IF(AF230<365,AF230*AC$26*AD230,365*AD230*AC$26))
AA231: =IF(AA230<B$17,AA230+1,"") | AC231: =IF(AB231="","",IF(AA231<=B$16,AC230,AC230-AD231)) | AD231: =IF(AA231="","",IF(AA231<=B$16,0,B$15/(B$17-B$16))) | AG231: =IF(AF231="","",IF(AF231<365,AF231*AC$25*AD231,365*AD231*AC$25)) | AH231: =IF(AF231="","",IF(AF231<365,AF231*AC$26*AD231,365*AD231*AC$26))
AA232: =IF(AA231<B$17,AA231+1,"") | AC232: =IF(AB232="","",IF(AA232<=B$16,AC231,AC231-AD232)) | AD232: =IF(AA232="","",IF(AA232<=B$16,0,B$15/(B$17-B$16))) | AG232: =IF(AF232="","",IF(AF232<365,AF232*AC$25*AD232,365*AD232*AC$25)) | AH232: =IF(AF232="","",IF(AF232<365,AF232*AC$26*AD232,365*AD232*AC$26))
AA233: =IF(AA232<B$17,AA232+1,"") | AC233: =IF(AB233="","",IF(AA233<=B$16,AC232,AC232-AD233)) | AD233: =IF(AA233="","",IF(AA233<=B$16,0,B$15/(B$17-B$16))) | AG233: =IF(AF233="","",IF(AF233<365,AF233*AC$25*AD233,365*AD233*AC$25)) | AH233: =IF(AF233="","",IF(AF233<365,AF233*AC$26*AD233,365*AD233*AC$26))
AA234: =IF(AA233<B$17,AA233+1,"") | AC234: =IF(AB234="","",IF(AA234<=B$16,AC233,AC233-AD234)) | AD234: =IF(AA234="","",IF(AA234<=B$16,0,B$15/(B$17-B$16))) | AG234: =IF(AF234="","",IF(AF234<365,AF234*AC$25*AD234,365*AD234*AC$25)) | AH234: =IF(AF234="","",IF(AF234<365,AF234*AC$26*AD234,365*AD234*AC$26))
AA235: =IF(AA234<B$17,AA234+1,"") | AC235: =IF(AB235="","",E229) | AD235: =IF(AA235="","",IF(AA235<=B$16,0,B$15/(B$17-B$16))) | AG235: =IF(AF235="","",IF(AF235<365,AF235*AC$25*AD235,365*AD235*AC$25)) | AH235: =IF(AF235="","",IF(AF235<365,AF235*AC$26*AD235,365*AD235*AC$26))
AA236: =IF(AA235<B$17,AA235+1,"") | AC236: =IF(AB236="","",E230) | AD236: =IF(AA236="","",IF(AA236<=B$16,0,B$15/(B$17-B$16))) | AG236: =IF(AF236="","",IF(AF236<365,AF236*AC$25*AD236,365*AD236*AC$25)) | AH236: =IF(AF236="","",IF(AF236<365,AF236*AC$26*AD236,365*AD236*AC$26))
AA237: =IF(AA236<B$17,AA236+1,"") | AC237: =IF(AB237="","",E231) | AD237: =IF(AA237="","",IF(AA237<=B$16,0,B$15/(B$17-B$16))) | AG237: =IF(AF237="","",IF(AF237<365,AF237*AC$25*AD237,365*AD237*AC$25)) | AH237: =IF(AF237="","",IF(AF237<365,AF237*AC$26*AD237,365*AD237*AC$26))
AA238: =IF(AA237<B$17,AA237+1,"") | AC238: =IF(AB238="","",E232) | AD238: =IF(AA238="","",IF(AA238<=B$16,0,B$15/(B$17-B$16))) | AG238: =IF(AF238="","",IF(AF238<365,AF238*AC$25*AD238,365*AD238*AC$25)) | AH238: =IF(AF238="","",IF(AF238<365,AF238*AC$26*AD238,365*AD238*AC$26))
AA239: =IF(AA238<B$17,AA238+1,"") | AC239: =IF(AB239="","",E233) | AD239: =IF(AA239="","",IF(AA239<=B$16,0,B$15/(B$17-B$16))) | AG239: =IF(AF239="","",IF(AF239<365,AF239*AC$25*AD239,365*AD239*AC$25)) | AH239: =IF(AF239="","",IF(AF239<365,AF239*AC$26*AD239,365*AD239*AC$26))
...

Sheet Mais Crédito (2)
A1: AGÊNCIA DE FOMENTO DE GOIÁS S/A | AA1: 1 | AB1: 1
A2: IMPORTANTE: Os valores simulados podem variar e estão sujeitos à data de vencimento da parcela e da liberação do crédito; O financiamento e condições são sujeitas à aprovação final da análise de crédito; Valores calculados com base na taxa líquida para quando não há atraso nos pagamentos.
A3: LINHA DE CAPITAL DE GIRO/INVESTIMENTO | AA3: TAC | AB3: IOF
A4: LINHA | J4: 1 | K4: 1 | N4: LINHA | O4: TAXA (a.m.) | P4: TAXA BONUS | Q4: CG1 (a.m.) | R4: CG2 (a.m.) | S4: PRAZO (meses) | T4: CARÊNCIA (até meses) | U4: LIMITE | V4: GARANTIA | AA4: Descontado | AB4: Descontado
N5: Mais Crédito Aval do FUNDEQ | O5: 1.69 | P5: 0 | Q5: 1.69 | R5: =Q5 -> 1.69 | S5: 24 | T5: 3 | U5: 21000 | V5: CG1 | AA5: Financiado | AB5: Financiado
C6: =IF(AND(J4=1,K4=1),Q5,IF(AND(J4=1,K4=2),R5,IF(AND(J4=1,K4=3),P5,"-"))) -> 1.69 | N6: Mais CrédIto com parceria - Juro Zero e Aval | O6: 1.69 | P6: 0 | Q6: 0 | R6: 0 | S6: 24 | T6: 3 | U6: 21000 | V6: CG2
C7: =IF(AND(J4=2,K4=1),Q6,IF(AND(J4=2,K4=2),R6,IF(AND(J4=2,K4=3),P6,"-"))) -> - | N7: Mais Crédito Equalização de Juros FUNDEQ | O7: 1.69 | P7: 0 | Q7: 0 | R7: 0 | S7: 24 | T7: 3 | U7: 21000 | V7: NÃO
C8: =IF(AND(J4=3,K4=1),Q7,IF(AND(J4=3,K4=2),R7,IF(AND(J4=3,K4=3),P7,"-"))) -> - | N8: GoiásFomento Giro - VIP IMCF | O8: 1.9 | P8: 0 | Q8: 1.47 | R8: =Q8 -> 1.47 | S8: 36 | T8: 3 | U8: 300000
C9: =IF(AND(J4=4,K4=1),Q8,IF(AND(J4=4,K4=2),R8,IF(AND(J4=4,K4=3),P8,"-"))) -> - | N9: GoiásFomento Giro Consorciado | O9: 1.9 | P9: 0 | Q9: 1.47 | R9: =Q9 -> 1.47 | S9: 36 | T9: 3 | U9: 300000
C10: =IF(AND(J4=5,K4=1),Q9,IF(AND(J4=5,K4=2),R9,IF(AND(J4=5,K4=3),P9,"-"))) -> - | N10: GoiásFomento (GIRO)Tecnologia/PQF-IEL/Turismo/FarmaDrogas/ Contabilistas | O10: 2.05 | P10: 0 | Q10: 1.58 | R10: =Q10 -> 1.58 | S10: 36 | T10: 3 | U10: 300000
C11: =IF(AND(J4=6,K4=1),Q10,IF(AND(J4=6,K4=2),R10,IF(AND(J4=6,K4=3),P10,"-"))) -> - | N11: GoiásFomento Microcrédito Produtivo | O11: 1.82 | P11: 1.5 | Q11: 1.5 | R11: =Q11 -> 1.5 | S11: 36 | T11: 3 | U11: 21000
C12: =IF(AND(J4=7,K4=1),Q11,IF(AND(J4=7,K4=2),R11,IF(AND(J4=7,K4=3),P11,"-"))) -> -
K13: ASSAT1
A14: INFORMAÇÕES | I14: =IF(B15<=5000,IF(AND(B15<=5000,J21=TRUE),D15,0),0.0169) -> 0.0169
A15: VALOR FINANCIADO | B15: 21000 | C15: TAXA NOMINAL | D15: =IF(J4=1,O5,IF(J4=2,O6,IF(J4=3,O7,IF(J4=4,O8,IF(J4=5,O9,IF(J4=6,O10,IF(J4=7,O11)))))))/100 -> 0.0169 | F15: =IF(B15<=3000,50,IF(B15<=21000,IF(B15*0.03<=420,B15*0.03,420),IF(B15<=100000,B15*0.02,2000+B15*0.005))) -> 420 | I15: =IF(B15<=3000,50,IF(B15<=21000,IF(B15*0.03<=420,B15*0.03,420),IF(B15<=100000,B15*0.02,2000+B15*0.005))) -> 420 | J15: 4
A16: CARÊNCIA | B16: 6 | C16: TAXA COM BÔNUS | D16: =IF(B15<=5000,IF(AND(B15<=5000,J21=TRUE),D15,0),0.0169) -> 0.0169 | F16: =AF24 -> 180.2073 | I16: =IF(B15*0.03<=420,B15*0.03,420) -> 420 | J16: 1 | AP16: 36
A17: PRAZO TOTAL | B17: 36 | C17: DATA DA PROPOSTA | D17: =TODAY() -> 46240 | F17: =IF(B15>5000,IF(B15>5000,IF(K4=1,(B15*E19*0.001*B17),IF(K4=2,(F19*0.001*B17),IF(K4=3,0,""))),0),IF(J21=TRUE,IF(K4=1,(B15*E19*0.001*B17),IF(K4=2,(F19*0.001*B17),IF(K4=3,0,""))),0)) -> 756 | J17: Descontado | L17: FALSE
A18: OPÇÕES DE GARANTIA | J18: Financiado
A19: RENDA PARA AVAL | B19: =IF(LARGE(F23:F241,1)*3<2424,2424,LARGE(F23:F241,1)*3) -> 3164.7 | C19: ALIENAÇÃO DE IMÓVEL | D19: =IF(J21=TRUE,(B15-F19)*1.5/0.7,B15*1.5/0.7) -> 0 | E19: 1 | F19: =IF(F17<>0,IF(K4=1,(B15*E19),IF(K4=2,B15*E19,IF(K4=3,0,""))),0) -> 21000 | J19: FINANCIADO | L19: TRUE
A20: SIMULAÇÃO DO VALOR DAS PARCELAS | J20: Financiado | AM20: =IRR(AM23:AM47) -> -0.0059870182
A21: PARCELA | B21: AMORTIZAÇÃO | C21: JUROS | D21: VALOR AMORTIZAÇÃO | E21: SALDO DEVEDOR | F21: PARCELA COM BÔNUS | J21: TRUE | AB21: IOF - ACIMA ATÉ 365 DIAS
A22: TOTAL | C22: =SUM(C23:C242) -> 7630.3669 | D22: =SUM(D23:D242) -> 21000 | F22: =SUM(F23:F242) -> 28630.35
A23: 0 | C23: =D16 -> 0.0169 | E23: =IF(AND(AA1=1,AB1=1,J16=1),B15,IF(AND(AA1=1,AB1=1,J16=2),B15+F17,IF(AND(AA1=1,AB1=2,J16=1),B15+F16,IF(AND(AA1=1,AB1=2,J16=3),B15+F16,IF(AND(AA1=2,AB1=1,J16=1),B15+F15,IF(AND(AA1=2,AB1=1,J16=2),B15+F15+F17,IF(AND(AA1=2,AB1=2,J16=2),B15+F17+F16+F15,IF(AND(AA1=2,AB1=2,J16=3),B15+F15+F16,IF(AND(AA1=2,AB1=2,J16=1),B15+F15+F16,IF(AND(AA1=1,AB1=2,J16=2),B15+F16+F17, IF(AND(AA1=1,AB1=1,J16=3),B15))))))))))) -> 21000 | AM23: =-B15 -> -21000
A24: =IF(A23<B$17,A23+1,"") -> 1 | B24: =IF(A24="","",IF(A24<=B$16,"carência","amortização")) -> carência | C24: =IF(B24="","",E23*$C$23) -> 354.9 | D24: =IF(C24="","",IF(A24<=B$16,0,B$15/(B$17-B$16))) -> 0 | E24: =IF(F24="","",E23-D24) -> 21000 | F24: =IF(D24="","",D24+C24) -> 354.9 | AB24: IOF | AC24: 0.0038 | AE24: =AC27*AC24 -> 79.8 | AF24: =IF(L19=FALSE,0,IF(AND(AH25=TRUE,B15<=30000),AE24+AE26,AE24+AE25)) -> 180.2073 | AM24: =F24 -> 354.9
A25: =IF(A24<B$17,A24+1,"") -> 2 | B25: =IF(A25="","",IF(A25<=B$16,"carência","amortização")) -> carência | C25: =IF(B25="","",E24*$C$23) -> 354.9 | D25: =IF(C25="","",IF(A25<=B$16,0,B$15/(B$17-B$16))) -> 0 | E25: =IF(F25="","",E24-D25) -> 21000 | F25: =IF(D25="","",D25+C25) -> 354.9 | AB25: ALÍQUOTA | AC25: 4.1e-05 | AE25: =SUM(AG30:AG83) -> 300.489 | AH25: TRUE | AM25: =F25 -> 354.9
A26: =IF(A25<B$17,A25+1,"") -> 3 | B26: =IF(A26="","",IF(A26<=B$16,"carência","amortização")) -> carência | C26: =IF(B26="","",E25*$C$23) -> 354.9 | D26: =IF(C26="","",IF(A26<=B$16,0,B$15/(B$17-B$16))) -> 0 | E26: =IF(F26="","",E25-D26) -> 21000 | F26: =IF(D26="","",D26+C26) -> 354.9 | AB26: ALÍQUOTA SIMPLES | AC26: =0.00137/100 -> 1.37e-05 | AE26: =SUM(AH30:AH308) -> 100.4073 | AM26: =F26 -> 354.9
A27: =IF(A26<B$17,A26+1,"") -> 4 | B27: =IF(A27="","",IF(A27<=B$16,"carência","amortização")) -> carência | C27: =IF(B27="","",E26*$C$23) -> 354.9 | D27: =IF(C27="","",IF(A27<=B$16,0,B$15/(B$17-B$16))) -> 0 | E27: =IF(F27="","",E26-D27) -> 21000 | F27: =IF(D27="","",D27+C27) -> 354.9 | AB27: LIBERAÇÃO | AC27: =B15 -> 21000 | AM27: =F27 -> 354.9 | AP27: =F27/0.3 -> 1183 | AQ27: =AP27/0.2 -> 5915 | AS27: =F27/0.2 -> 1774.5 | AU27: 81000
A28: =IF(A27<B$17,A27+1,"") -> 5 | B28: =IF(A28="","",IF(A28<=B$16,"carência","amortização")) -> carência | C28: =IF(B28="","",E27*$C$23) -> 354.9 | D28: =IF(C28="","",IF(A28<=B$16,0,B$15/(B$17-B$16))) -> 0 | E28: =IF(F28="","",E27-D28) -> 21000 | F28: =IF(D28="","",D28+C28) -> 354.9 | AG28: IOF NORMAL | AH28: IOF SIMPLES | AM28: =F28 -> 354.9 | AU28: =AU27/12 -> 6750
A29: =IF(A28<B$17,A28+1,"") -> 6 | B29: =IF(A29="","",IF(A29<=B$16,"carência","amortização")) -> carência | C29: =IF(B29="","",E28*$C$23) -> 354.9 | D29: =IF(C29="","",IF(A29<=B$16,0,B$15/(B$17-B$16))) -> 0 | E29: =IF(F29="","",E28-D29) -> 21000 | F29: =IF(D29="","",D29+C29) -> 354.9 | AA29: 0 | AB29: =D17 -> 46240 | AC29: =IF(AB29="","",AC27) -> 21000 | AD29: =IF(AA29="","",IF(AA29<=B$16,0,B$15/(B$17-B$16))) -> 0 | AM29: =F29 -> 354.9 | AU29: =F27/AU28 -> 0.052577778
A30: =IF(A29<B$17,A29+1,"") -> 7 | B30: =IF(A30="","",IF(A30<=B$16,"carência","amortização")) -> amortização | C30: =IF(B30="","",E29*$C$23) -> 354.9 | D30: =IF(C30="","",IF(A30<=B$16,0,B$15/(B$17-B$16))) -> 700 | E30: =IF(F30="","",E29-D30) -> 20300 | F30: =IF(D30="","",D30+C30) -> 1054.9 | AA30: =IF(AA29<B$17,AA29+1,"") -> 1 | AB30: =IF(AA30="","",AB29+30) -> 46270 | AC30: =IF(AB30="","",IF(AA30<=B$16,AC29,AC29-AD30)) -> 21000 | AD30: =IF(AA30="","",IF(AA30<=B$16,0,B$15/(B$17-B$16))) -> 0 | AE30: =IF(AD30="","",AB30-AB29) -> 30 | AF30: =IF(AE30="","",AB30-AB$29) -> 30 | AG30: =IF(AF30="","",IF(AF30<365,AF30*AC$25*AD30,365*AD30*AC$25)) -> 0 | AH30: =IF(AF30="","",IF(AF30<365,AF30*AC$26*AD30,365*AD30*AC$26)) -> 0 | AM30: =F30 -> 1054.9 | AN30: =F30*12 -> 12658.8
A31: =IF(A30<B$17,A30+1,"") -> 8 | B31: =IF(A31="","",IF(A31<=B$16,"carência","amortização")) -> amortização | C31: =IF(B31="","",E30*$C$23) -> 343.07 | D31: =IF(C31="","",IF(A31<=B$16,0,B$15/(B$17-B$16))) -> 700 | E31: =IF(F31="","",E30-D31) -> 19600 | F31: =IF(D31="","",D31+C31) -> 1043.07 | AA31: =IF(AA30<B$17,AA30+1,"") -> 2 | AB31: =IF(AA31="","",AB30+30) -> 46300 | AC31: =IF(AB31="","",IF(AA31<=B$16,AC30,AC30-AD31)) -> 21000 | AD31: =IF(AA31="","",IF(AA31<=B$16,0,B$15/(B$17-B$16))) -> 0 | AE31: =IF(AD31="","",AB31-AB30) -> 30 | AF31: =IF(AE31="","",AB31-AB$29) -> 60 | AG31: =IF(AF31="","",IF(AF31<365,AF31*AC$25*AD31,365*AD31*AC$25)) -> 0 | AH31: =IF(AF31="","",IF(AF31<365,AF31*AC$26*AD31,365*AD31*AC$26)) -> 0 | AM31: =F31 -> 1043.07 | AU31: =AU28*0.1 -> 675
A32: =IF(A31<B$17,A31+1,"") -> 9 | B32: =IF(A32="","",IF(A32<=B$16,"carência","amortização")) -> amortização | C32: =IF(B32="","",E31*$C$23) -> 331.24 | D32: =IF(C32="","",IF(A32<=B$16,0,B$15/(B$17-B$16))) -> 700 | E32: =IF(F32="","",E31-D32) -> 18900 | F32: =IF(D32="","",D32+C32) -> 1031.24 | AA32: =IF(AA31<B$17,AA31+1,"") -> 3 | AB32: =IF(AA32="","",AB31+30) -> 46330 | AC32: =IF(AB32="","",IF(AA32<=B$16,AC31,AC31-AD32)) -> 21000 | AD32: =IF(AA32="","",IF(AA32<=B$16,0,B$15/(B$17-B$16))) -> 0 | AE32: =IF(AD32="","",AB32-AB31) -> 30 | AF32: =IF(AE32="","",AB32-AB$29) -> 90 | AG32: =IF(AF32="","",IF(AF32<365,AF32*AC$25*AD32,365*AD32*AC$25)) -> 0 | AH32: =IF(AF32="","",IF(AF32<365,AF32*AC$26*AD32,365*AD32*AC$26)) -> 0 | AM32: =F32 -> 1031.24
A33: =IF(A32<B$17,A32+1,"") -> 10 | B33: =IF(A33="","",IF(A33<=B$16,"carência","amortização")) -> amortização | C33: =IF(B33="","",E32*$C$23) -> 319.41 | D33: =IF(C33="","",IF(A33<=B$16,0,B$15/(B$17-B$16))) -> 700 | E33: =IF(F33="","",E32-D33) -> 18200 | F33: =IF(D33="","",D33+C33) -> 1019.41 | AA33: =IF(AA32<B$17,AA32+1,"") -> 4 | AB33: =IF(AA33="","",AB32+30) -> 46360 | AC33: =IF(AB33="","",IF(AA33<=B$16,AC32,AC32-AD33)) -> 21000 | AD33: =IF(AA33="","",IF(AA33<=B$16,0,B$15/(B$17-B$16))) -> 0 | AE33: =IF(AD33="","",AB33-AB32) -> 30 | AF33: =IF(AE33="","",AB33-AB$29) -> 120 | AG33: =IF(AF33="","",IF(AF33<365,AF33*AC$25*AD33,365*AD33*AC$25)) -> 0 | AH33: =IF(AF33="","",IF(AF33<365,AF33*AC$26*AD33,365*AD33*AC$26)) -> 0 | AM33: =F33 -> 1019.41
A34: =IF(A33<B$17,A33+1,"") -> 11 | B34: =IF(A34="","",IF(A34<=B$16,"carência","amortização")) -> amortização | C34: =IF(B34="","",E33*$C$23) -> 307.58 | D34: =IF(C34="","",IF(A34<=B$16,0,B$15/(B$17-B$16))) -> 700 | E34: =IF(F34="","",E33-D34) -> 17500 | F34: =IF(D34="","",D34+C34) -> 1007.58 | AA34: =IF(AA33<B$17,AA33+1,"") -> 5 | AB34: =IF(AA34="","",AB33+30) -> 46390 | AC34: =IF(AB34="","",IF(AA34<=B$16,AC33,AC33-AD34)) -> 21000 | AD34: =IF(AA34="","",IF(AA34<=B$16,0,B$15/(B$17-B$16))) -> 0 | AE34: =IF(AD34="","",AB34-AB33) -> 30 | AF34: =IF(AE34="","",AB34-AB$29) -> 150 | AG34: =IF(AF34="","",IF(AF34<365,AF34*AC$25*AD34,365*AD34*AC$25)) -> 0 | AH34: =IF(AF34="","",IF(AF34<365,AF34*AC$26*AD34,365*AD34*AC$26)) -> 0 | AM34: =F34 -> 1007.58
A35: =IF(A34<B$17,A34+1,"") -> 12 | B35: =IF(A35="","",IF(A35<=B$16,"carência","amortização")) -> amortização | C35: =IF(B35="","",E34*$C$23) -> 295.75 | D35: =IF(C35="","",IF(A35<=B$16,0,B$15/(B$17-B$16))) -> 700 | E35: =IF(F35="","",E34-D35) -> 16800 | F35: =IF(D35="","",D35+C35) -> 995.75 | AA35: =IF(AA34<B$17,AA34+1,"") -> 6 | AB35: =IF(AA35="","",AB34+30) -> 46420 | AC35: =IF(AB35="","",IF(AA35<=B$16,AC34,AC34-AD35)) -> 21000 | AD35: =IF(AA35="","",IF(AA35<=B$16,0,B$15/(B$17-B$16))) -> 0 | AE35: =IF(AD35="","",AB35-AB34) -> 30 | AF35: =IF(AE35="","",AB35-AB$29) -> 180 | AG35: =IF(AF35="","",IF(AF35<365,AF35*AC$25*AD35,365*AD35*AC$25)) -> 0 | AH35: =IF(AF35="","",IF(AF35<365,AF35*AC$26*AD35,365*AD35*AC$26)) -> 0 | AM35: =F35 -> 995.75 | AN35: =SUM(F24:F35) -> 8281.35 | AO35: =LARGE(F24:F35,1) -> 1054.9
A36: =IF(A35<B$17,A35+1,"") -> 13 | B36: =IF(A36="","",IF(A36<=B$16,"carência","amortização")) -> amortização | C36: =IF(B36="","",E35*$C$23) -> 283.92 | D36: =IF(C36="","",IF(A36<=B$16,0,E$23/(B$17-B$16))) -> 700 | E36: =IF(F36="","",E35-D36) -> 16100 | F36: =IF(D36="","",D36+C36) -> 983.92 | AA36: =IF(AA35<B$17,AA35+1,"") -> 7 | AB36: =IF(AA36="","",AB35+30) -> 46450 | AC36: =IF(AB36="","",IF(AA36<=B$16,AC35,AC35-AD36)) -> 20300 | AD36: =IF(AA36="","",IF(AA36<=B$16,0,B$15/(B$17-B$16))) -> 700 | AE36: =IF(AD36="","",AB36-AB35) -> 30 | AF36: =IF(AE36="","",AB36-AB$29) -> 210 | AG36: =IF(AF36="","",IF(AF36<365,AF36*AC$25*AD36,365*AD36*AC$25)) -> 6.027 | AH36: =IF(AF36="","",IF(AF36<365,AF36*AC$26*AD36,365*AD36*AC$26)) -> 2.0139 | AM36: =F36 -> 983.92
A37: =IF(A36<B$17,A36+1,"") -> 14 | B37: =IF(A37="","",IF(A37<=B$16,"carência","amortização")) -> amortização | C37: =IF(B37="","",E36*$C$23) -> 272.09 | D37: =IF(C37="","",IF(A37<=B$16,0,E$23/(B$17-B$16))) -> 700 | E37: =IF(F37="","",E36-D37) -> 15400 | F37: =IF(D37="","",D37+C37) -> 972.09 | AA37: =IF(AA36<B$17,AA36+1,"") -> 8 | AB37: =IF(AA37="","",AB36+30) -> 46480 | AC37: =IF(AB37="","",IF(AA37<=B$16,AC36,AC36-AD37)) -> 19600 | AD37: =IF(AA37="","",IF(AA37<=B$16,0,B$15/(B$17-B$16))) -> 700 | AE37: =IF(AD37="","",AB37-AB36) -> 30 | AF37: =IF(AE37="","",AB37-AB$29) -> 240 | AG37: =IF(AF37="","",IF(AF37<365,AF37*AC$25*AD37,365*AD37*AC$25)) -> 6.888 | AH37: =IF(AF37="","",IF(AF37<365,AF37*AC$26*AD37,365*AD37*AC$26)) -> 2.3016 | AM37: =F37 -> 972.09
A38: =IF(A37<B$17,A37+1,"") -> 15 | B38: =IF(A38="","",IF(A38<=B$16,"carência","amortização")) -> amortização | C38: =IF(B38="","",E37*$C$23) -> 260.26 | D38: =IF(C38="","",IF(A38<=B$16,0,E$23/(B$17-B$16))) -> 700 | E38: =IF(F38="","",E37-D38) -> 14700 | F38: =IF(D38="","",D38+C38) -> 960.26 | AA38: =IF(AA37<B$17,AA37+1,"") -> 9 | AB38: =IF(AA38="","",AB37+30) -> 46510 | AC38: =IF(AB38="","",IF(AA38<=B$16,AC37,AC37-AD38)) -> 18900 | AD38: =IF(AA38="","",IF(AA38<=B$16,0,B$15/(B$17-B$16))) -> 700 | AE38: =IF(AD38="","",AB38-AB37) -> 30 | AF38: =IF(AE38="","",AB38-AB$29) -> 270 | AG38: =IF(AF38="","",IF(AF38<365,AF38*AC$25*AD38,365*AD38*AC$25)) -> 7.749 | AH38: =IF(AF38="","",IF(AF38<365,AF38*AC$26*AD38,365*AD38*AC$26)) -> 2.5893 | AM38: =F38 -> 960.26
A39: =IF(A38<B$17,A38+1,"") -> 16 | B39: =IF(A39="","",IF(A39<=B$16,"carência","amortização")) -> amortização | C39: =IF(B39="","",E38*$C$23) -> 248.43 | D39: =IF(C39="","",IF(A39<=B$16,0,E$23/(B$17-B$16))) -> 700 | E39: =IF(F39="","",E38-D39) -> 14000 | F39: =IF(D39="","",D39+C39) -> 948.43 | AA39: =IF(AA38<B$17,AA38+1,"") -> 10 | AB39: =IF(AA39="","",AB38+30) -> 46540 | AC39: =IF(AB39="","",IF(AA39<=B$16,AC38,AC38-AD39)) -> 18200 | AD39: =IF(AA39="","",IF(AA39<=B$16,0,B$15/(B$17-B$16))) -> 700 | AE39: =IF(AD39="","",AB39-AB38) -> 30 | AF39: =IF(AE39="","",AB39-AB$29) -> 300 | AG39: =IF(AF39="","",IF(AF39<365,AF39*AC$25*AD39,365*AD39*AC$25)) -> 8.61 | AH39: =IF(AF39="","",IF(AF39<365,AF39*AC$26*AD39,365*AD39*AC$26)) -> 2.877 | AM39: =F39 -> 948.43
A40: =IF(A39<B$17,A39+1,"") -> 17 | B40: =IF(A40="","",IF(A40<=B$16,"carência","amortização")) -> amortização | C40: =IF(B40="","",E39*$C$23) -> 236.6 | D40: =IF(C40="","",IF(A40<=B$16,0,E$23/(B$17-B$16))) -> 700 | E40: =IF(F40="","",E39-D40) -> 13300 | F40: =IF(D40="","",D40+C40) -> 936.6 | AA40: =IF(AA39<B$17,AA39+1,"") -> 11 | AB40: =IF(AA40="","",AB39+30) -> 46570 | AC40: =IF(AB40="","",IF(AA40<=B$16,AC39,AC39-AD40)) -> 17500 | AD40: =IF(AA40="","",IF(AA40<=B$16,0,B$15/(B$17-B$16))) -> 700 | AE40: =IF(AD40="","",AB40-AB39) -> 30 | AF40: =IF(AE40="","",AB40-AB$29) -> 330 | AG40: =IF(AF40="","",IF(AF40<365,AF40*AC$25*AD40,365*AD40*AC$25)) -> 9.471 | AH40: =IF(AF40="","",IF(AF40<365,AF40*AC$26*AD40,365*AD40*AC$26)) -> 3.1647 | AM40: =F40 -> 936.6
A41: =IF(A40<B$17,A40+1,"") -> 18 | B41: =IF(A41="","",IF(A41<=B$16,"carência","amortização")) -> amortização | C41: =IF(B41="","",E40*$C$23) -> 224.77 | D41: =IF(C41="","",IF(A41<=B$16,0,E$23/(B$17-B$16))) -> 700 | E41: =IF(F41="","",E40-D41) -> 12600 | F41: =IF(D41="","",D41+C41) -> 924.77 | AA41: =IF(AA40<B$17,AA40+1,"") -> 12 | AB41: =IF(AA41="","",AB40+30) -> 46600 | AC41: =IF(AB41="","",IF(AA41<=B$16,AC40,AC40-AD41)) -> 16800 | AD41: =IF(AA41="","",IF(AA41<=B$16,0,B$15/(B$17-B$16))) -> 700 | AE41: =IF(AD41="","",AB41-AB40) -> 30 | AF41: =IF(AE41="","",AB41-AB$29) -> 360 | AG41: =IF(AF41="","",IF(AF41<365,AF41*AC$25*AD41,365*AD41*AC$25)) -> 10.332 | AH41: =IF(AF41="","",IF(AF41<365,AF41*AC$26*AD41,365*AD41*AC$26)) -> 3.4524 | AM41: =F41 -> 924.77
A42: =IF(A41<B$17,A41+1,"") -> 19 | B42: =IF(A42="","",IF(A42<=B$16,"carência","amortização")) -> amortização | C42: =IF(B42="","",E41*$C$23) -> 212.94 | D42: =IF(C42="","",IF(A42<=B$16,0,E$23/(B$17-B$16))) -> 700 | E42: =IF(F42="","",E41-D42) -> 11900 | F42: =IF(D42="","",D42+C42) -> 912.94 | AA42: =IF(AA41<B$17,AA41+1,"") -> 13 | AB42: =IF(AA42="","",AB41+30) -> 46630 | AC42: =IF(AA42="","",IF(AB42<=B$16,AC27,AC41-AD42)) -> 16100 | AD42: =IF(AA42="","",IF(AA42<=B$16,0,B$15/(B$17-B$16))) -> 700 | AE42: =IF(AD42="","",AB42-AB41) -> 30 | AF42: =IF(AE42="","",AB42-AB$29) -> 390 | AG42: =IF(AF42="","",IF(AF42<365,AF42*AC$25*AD42,365*AD42*AC$25)) -> 10.4755 | AH42: =IF(AF42="","",IF(AF42<365,AF42*AC$26*AD42,365*AD42*AC$26)) -> 3.50035 | AM42: =F42 -> 912.94
A43: =IF(A42<B$17,A42+1,"") -> 20 | B43: =IF(A43="","",IF(A43<=B$16,"carência","amortização")) -> amortização | C43: =IF(B43="","",E42*$C$23) -> 201.11 | D43: =IF(C43="","",IF(A43<=B$16,0,E$23/(B$17-B$16))) -> 700 | E43: =IF(F43="","",E42-D43) -> 11200 | F43: =IF(D43="","",D43+C43) -> 901.11 | AA43: =IF(AA42<B$17,AA42+1,"") -> 14 | AB43: =IF(AA43="","",AB42+30) -> 46660 | AC43: =IF(AB43="","",IF(AA43<=B$16,AC42,AC42-AD43)) -> 15400 | AD43: =IF(AA43="","",IF(AA43<=B$16,0,B$15/(B$17-B$16))) -> 700 | AE43: =IF(AD43="","",AB43-AB42) -> 30 | AF43: =IF(AE43="","",AB43-AB$29) -> 420 | AG43: =IF(AF43="","",IF(AF43<365,AF43*AC$25*AD43,365*AD43*AC$25)) -> 10.4755 | AH43: =IF(AF43="","",IF(AF43<365,AF43*AC$26*AD43,365*AD43*AC$26)) -> 3.50035 | AM43: =F43 -> 901.11
A44: =IF(A43<B$17,A43+1,"") -> 21 | B44: =IF(A44="","",IF(A44<=B$16,"carência","amortização")) -> amortização | C44: =IF(B44="","",E43*$C$23) -> 189.28 | D44: =IF(C44="","",IF(A44<=B$16,0,E$23/(B$17-B$16))) -> 700 | E44: =IF(F44="","",E43-D44) -> 10500 | F44: =IF(D44="","",D44+C44) -> 889.28 | AA44: =IF(AA43<B$17,AA43+1,"") -> 15 | AB44: =IF(AA44="","",AB43+30) -> 46690 | AC44: =IF(AB44="","",IF(AA44<=B$16,AC43,AC43-AD44)) -> 14700 | AD44: =IF(AA44="","",IF(AA44<=B$16,0,B$15/(B$17-B$16))) -> 700 | AE44: =IF(AD44="","",AB44-AB43) -> 30 | AF44: =IF(AE44="","",AB44-AB$29) -> 450 | AG44: =IF(AF44="","",IF(AF44<365,AF44*AC$25*AD44,365*AD44*AC$25)) -> 10.4755 | AH44: =IF(AF44="","",IF(AF44<365,AF44*AC$26*AD44,365*AD44*AC$26)) -> 3.50035 | AM44: =F44 -> 889.28
A45: =IF(A44<B$17,A44+1,"") -> 22 | B45: =IF(A45="","",IF(A45<=B$16,"carência","amortização")) -> amortização | C45: =IF(B45="","",E44*$C$23) -> 177.45 | D45: =IF(C45="","",IF(A45<=B$16,0,E$23/(B$17-B$16))) -> 700 | E45: =IF(F45="","",E44-D45) -> 9800 | F45: =IF(D45="","",D45+C45) -> 877.45 | AA45: =IF(AA44<B$17,AA44+1,"") -> 16 | AB45: =IF(AA45="","",AB44+30) -> 46720 | AC45: =IF(AB45="","",IF(AA45<=B$16,AC44,AC44-AD45)) -> 14000 | AD45: =IF(AA45="","",IF(AA45<=B$16,0,B$15/(B$17-B$16))) -> 700 | AE45: =IF(AD45="","",AB45-AB44) -> 30 | AF45: =IF(AE45="","",AB45-AB$29) -> 480 | AG45: =IF(AF45="","",IF(AF45<365,AF45*AC$25*AD45,365*AD45*AC$25)) -> 10.4755 | AH45: =IF(AF45="","",IF(AF45<365,AF45*AC$26*AD45,365*AD45*AC$26)) -> 3.50035 | AM45: =F45 -> 877.45
A46: =IF(A45<B$17,A45+1,"") -> 23 | B46: =IF(A46="","",IF(A46<=B$16,"carência","amortização")) -> amortização | C46: =IF(B46="","",E45*$C$23) -> 165.62 | D46: =IF(C46="","",IF(A46<=B$16,0,E$23/(B$17-B$16))) -> 700 | E46: =IF(F46="","",E45-D46) -> 9100 | F46: =IF(D46="","",D46+C46) -> 865.62 | AA46: =IF(AA45<B$17,AA45+1,"") -> 17 | AB46: =IF(AA46="","",AB45+30) -> 46750 | AC46: =IF(AB46="","",IF(AA46<=B$16,AC45,AC45-AD46)) -> 13300 | AD46: =IF(AA46="","",IF(AA46<=B$16,0,B$15/(B$17-B$16))) -> 700 | AE46: =IF(AD46="","",AB46-AB45) -> 30 | AF46: =IF(AE46="","",AB46-AB$29) -> 510 | AG46: =IF(AF46="","",IF(AF46<365,AF46*AC$25*AD46,365*AD46*AC$25)) -> 10.4755 | AH46: =IF(AF46="","",IF(AF46<365,AF46*AC$26*AD46,365*AD46*AC$26)) -> 3.50035 | AM46: =F46 -> 865.62
A47: =IF(A46<B$17,A46+1,"") -> 24 | B47: =IF(A47="","",IF(A47<=B$16,"carência","amortização")) -> amortização | C47: =IF(B47="","",E46*$C$23) -> 153.79 | D47: =IF(C47="","",IF(A47<=B$16,0,E$23/(B$17-B$16))) -> 700 | E47: =IF(F47="","",E46-D47) -> 8400 | F47: =IF(D47="","",D47+C47) -> 853.79 | AA47: =IF(AA46<B$17,AA46+1,"") -> 18 | AB47: =IF(AA47="","",AB46+30) -> 46780 | AC47: =IF(AB47="","",IF(AA47<=B$16,AC46,AC46-AD47)) -> 12600 | AD47: =IF(AA47="","",IF(AA47<=B$16,0,B$15/(B$17-B$16))) -> 700 | AE47: =IF(AD47="","",AB47-AB46) -> 30 | AF47: =IF(AE47="","",AB47-AB$29) -> 540 | AG47: =IF(AF47="","",IF(AF47<365,AF47*AC$25*AD47,365*AD47*AC$25)) -> 10.4755 | AH47: =IF(AF47="","",IF(AF47<365,AF47*AC$26*AD47,365*AD47*AC$26)) -> 3.50035 | AM47: =F47 -> 853.79 | AN47: =SUM(F36:F47) -> 11026.26 | AO47: =LARGE(F36:F47,1) -> 983.92
A48: =IF(A47<B$17,A47+1,"") -> 25 | B48: =IF(A48="","",IF(A48<=B$16,"carência","amortização")) -> amortização | C48: =IF(B48="","",E47*$C$23) -> 141.96 | D48: =IF(C48="","",IF(A48<=B$16,0,E$23/(B$17-B$16))) -> 700 | E48: =IF(F48="","",E47-D48) -> 7700 | F48: =IF(D48="","",D48+C48) -> 841.96 | AA48: =IF(AA47<B$17,AA47+1,"") -> 19 | AB48: =IF(AA48="","",AB47+30) -> 46810 | AC48: =IF(AB48="","",IF(AA48<=B$16,AC47,AC47-AD48)) -> 11900 | AD48: =IF(AA48="","",IF(AA48<=B$16,0,B$15/(B$17-B$16))) -> 700 | AE48: =IF(AD48="","",AB48-AB47) -> 30 | AF48: =IF(AE48="","",AB48-AB$29) -> 570 | AG48: =IF(AF48="","",IF(AF48<365,AF48*AC$25*AD48,365*AD48*AC$25)) -> 10.4755 | AH48: =IF(AF48="","",IF(AF48<365,AF48*AC$26*AD48,365*AD48*AC$26)) -> 3.50035
A49: =IF(A48<B$17,A48+1,"") -> 26 | B49: =IF(A49="","",IF(A49<=B$16,"carência","amortização")) -> amortização | C49: =IF(B49="","",E48*$C$23) -> 130.13 | D49: =IF(C49="","",IF(A49<=B$16,0,E$23/(B$17-B$16))) -> 700 | E49: =IF(F49="","",E48-D49) -> 7000 | F49: =IF(D49="","",D49+C49) -> 830.13 | AA49: =IF(AA48<B$17,AA48+1,"") -> 20 | AB49: =IF(AA49="","",AB48+30) -> 46840 | AC49: =IF(AB49="","",IF(AA49<=B$16,AC48,AC48-AD49)) -> 11200 | AD49: =IF(AA49="","",IF(AA49<=B$16,0,B$15/(B$17-B$16))) -> 700 | AE49: =IF(AD49="","",AB49-AB48) -> 30 | AF49: =IF(AE49="","",AB49-AB$29) -> 600 | AG49: =IF(AF49="","",IF(AF49<365,AF49*AC$25*AD49,365*AD49*AC$25)) -> 10.4755 | AH49: =IF(AF49="","",IF(AF49<365,AF49*AC$26*AD49,365*AD49*AC$26)) -> 3.50035
A50: =IF(A49<B$17,A49+1,"") -> 27 | B50: =IF(A50="","",IF(A50<=B$16,"carência","amortização")) -> amortização | C50: =IF(B50="","",E49*$C$23) -> 118.3 | D50: =IF(C50="","",IF(A50<=B$16,0,E$23/(B$17-B$16))) -> 700 | E50: =IF(F50="","",E49-D50) -> 6300 | F50: =IF(D50="","",D50+C50) -> 818.3 | AA50: =IF(AA49<B$17,AA49+1,"") -> 21 | AB50: =IF(AA50="","",AB49+30) -> 46870 | AC50: =IF(AB50="","",IF(AA50<=B$16,AC49,AC49-AD50)) -> 10500 | AD50: =IF(AA50="","",IF(AA50<=B$16,0,B$15/(B$17-B$16))) -> 700 | AE50: =IF(AD50="","",AB50-AB49) -> 30 | AF50: =IF(AE50="","",AB50-AB$29) -> 630 | AG50: =IF(AF50="","",IF(AF50<365,AF50*AC$25*AD50,365*AD50*AC$25)) -> 10.4755 | AH50: =IF(AF50="","",IF(AF50<365,AF50*AC$26*AD50,365*AD50*AC$26)) -> 3.50035
A51: =IF(A50<B$17,A50+1,"") -> 28 | B51: =IF(A51="","",IF(A51<=B$16,"carência","amortização")) -> amortização | C51: =IF(B51="","",E50*$C$23) -> 106.47 | D51: =IF(C51="","",IF(A51<=B$16,0,E$23/(B$17-B$16))) -> 700 | E51: =IF(F51="","",E50-D51) -> 5600 | F51: =IF(D51="","",D51+C51) -> 806.47 | AA51: =IF(AA50<B$17,AA50+1,"") -> 22 | AB51: =IF(AA51="","",AB50+30) -> 46900 | AC51: =IF(AB51="","",IF(AA51<=B$16,AC50,AC50-AD51)) -> 9800 | AD51: =IF(AA51="","",IF(AA51<=B$16,0,B$15/(B$17-B$16))) -> 700 | AE51: =IF(AD51="","",AB51-AB50) -> 30 | AF51: =IF(AE51="","",AB51-AB$29) -> 660 | AG51: =IF(AF51="","",IF(AF51<365,AF51*AC$25*AD51,365*AD51*AC$25)) -> 10.4755 | AH51: =IF(AF51="","",IF(AF51<365,AF51*AC$26*AD51,365*AD51*AC$26)) -> 3.50035
A52: =IF(A51<B$17,A51+1,"") -> 29 | B52: =IF(A52="","",IF(A52<=B$16,"carência","amortização")) -> amortização | C52: =IF(B52="","",E51*$C$23) -> 94.64 | D52: =IF(C52="","",IF(A52<=B$16,0,E$23/(B$17-B$16))) -> 700 | E52: =IF(F52="","",E51-D52) -> 4900 | F52: =IF(D52="","",D52+C52) -> 794.64 | AA52: =IF(AA51<B$17,AA51+1,"") -> 23 | AB52: =IF(AA52="","",AB51+30) -> 46930 | AC52: =IF(AB52="","",IF(AA52<=B$16,AC51,AC51-AD52)) -> 9100 | AD52: =IF(AA52="","",IF(AA52<=B$16,0,B$15/(B$17-B$16))) -> 700 | AE52: =IF(AD52="","",AB52-AB51) -> 30 | AF52: =IF(AE52="","",AB52-AB$29) -> 690 | AG52: =IF(AF52="","",IF(AF52<365,AF52*AC$25*AD52,365*AD52*AC$25)) -> 10.4755 | AH52: =IF(AF52="","",IF(AF52<365,AF52*AC$26*AD52,365*AD52*AC$26)) -> 3.50035
A53: =IF(A52<B$17,A52+1,"") -> 30 | B53: =IF(A53="","",IF(A53<=B$16,"carência","amortização")) -> amortização | C53: =IF(B53="","",E52*$C$23) -> 82.81 | D53: =IF(C53="","",IF(A53<=B$16,0,E$23/(B$17-B$16))) -> 700 | E53: =IF(F53="","",E52-D53) -> 4200 | F53: =IF(D53="","",D53+C53) -> 782.81 | AA53: =IF(AA52<B$17,AA52+1,"") -> 24 | AB53: =IF(AA53="","",AB52+30) -> 46960 | AC53: =IF(AB53="","",IF(AA53<=B$16,AC52,AC52-AD53)) -> 8400 | AD53: =IF(AA53="","",IF(AA53<=B$16,0,B$15/(B$17-B$16))) -> 700 | AE53: =IF(AD53="","",AB53-AB52) -> 30 | AF53: =IF(AE53="","",AB53-AB$29) -> 720 | AG53: =IF(AF53="","",IF(AF53<365,AF53*AC$25*AD53,365*AD53*AC$25)) -> 10.4755 | AH53: =IF(AF53="","",IF(AF53<365,AF53*AC$26*AD53,365*AD53*AC$26)) -> 3.50035
A54: =IF(A53<B$17,A53+1,"") -> 31 | B54: =IF(A54="","",IF(A54<=B$16,"carência","amortização")) -> amortização | C54: =IF(B54="","",E53*$C$23) -> 70.98 | D54: =IF(C54="","",IF(A54<=B$16,0,E$23/(B$17-B$16))) -> 700 | E54: =IF(F54="","",E53-D54) -> 3500 | F54: =IF(D54="","",D54+C54) -> 770.98 | AA54: =IF(AA53<B$17,AA53+1,"") -> 25 | AB54: =IF(AA54="","",AB53+30) -> 46990 | AC54: =IF(AB54="","",IF(AA54<=B$16,AC53,AC53-AD54)) -> 7700 | AD54: =IF(AA54="","",IF(AA54<=B$16,0,B$15/(B$17-B$16))) -> 700 | AE54: =IF(AD54="","",AB54-AB53) -> 30 | AF54: =IF(AE54="","",AB54-AB$29) -> 750 | AG54: =IF(AF54="","",IF(AF54<365,AF54*AC$25*AD54,365*AD54*AC$25)) -> 10.4755 | AH54: =IF(AF54="","",IF(AF54<365,AF54*AC$26*AD54,365*AD54*AC$26)) -> 3.50035
A55: =IF(A54<B$17,A54+1,"") -> 32 | B55: =IF(A55="","",IF(A55<=B$16,"carência","amortização")) -> amortização | C55: =IF(B55="","",E54*$C$23) -> 59.15 | D55: =IF(C55="","",IF(A55<=B$16,0,E$23/(B$17-B$16))) -> 700 | E55: =IF(F55="","",E54-D55) -> 2800 | F55: =IF(D55="","",D55+C55) -> 759.15 | AA55: =IF(AA54<B$17,AA54+1,"") -> 26 | AB55: =IF(AA55="","",AB54+30) -> 47020 | AC55: =IF(AB55="","",IF(AA55<=B$16,AC54,AC54-AD55)) -> 7000 | AD55: =IF(AA55="","",IF(AA55<=B$16,0,B$15/(B$17-B$16))) -> 700 | AE55: =IF(AD55="","",AB55-AB54) -> 30 | AF55: =IF(AE55="","",AB55-AB$29) -> 780 | AG55: =IF(AF55="","",IF(AF55<365,AF55*AC$25*AD55,365*AD55*AC$25)) -> 10.4755 | AH55: =IF(AF55="","",IF(AF55<365,AF55*AC$26*AD55,365*AD55*AC$26)) -> 3.50035
A56: =IF(A55<B$17,A55+1,"") -> 33 | B56: =IF(A56="","",IF(A56<=B$16,"carência","amortização")) -> amortização | C56: =IF(B56="","",E55*$C$23) -> 47.32 | D56: =IF(C56="","",IF(A56<=B$16,0,E$23/(B$17-B$16))) -> 700 | E56: =IF(F56="","",E55-D56) -> 2100 | F56: =IF(D56="","",D56+C56) -> 747.32 | AA56: =IF(AA55<B$17,AA55+1,"") -> 27 | AB56: =IF(AA56="","",AB55+30) -> 47050 | AC56: =IF(AB56="","",IF(AA56<=B$16,AC55,AC55-AD56)) -> 6300 | AD56: =IF(AA56="","",IF(AA56<=B$16,0,B$15/(B$17-B$16))) -> 700 | AE56: =IF(AD56="","",AB56-AB55) -> 30 | AF56: =IF(AE56="","",AB56-AB$29) -> 810 | AG56: =IF(AF56="","",IF(AF56<365,AF56*AC$25*AD56,365*AD56*AC$25)) -> 10.4755 | AH56: =IF(AF56="","",IF(AF56<365,AF56*AC$26*AD56,365*AD56*AC$26)) -> 3.50035
A57: =IF(A56<B$17,A56+1,"") -> 34 | B57: =IF(A57="","",IF(A57<=B$16,"carência","amortização")) -> amortização | C57: =IF(B57="","",E56*$C$23) -> 35.49 | D57: =IF(C57="","",IF(A57<=B$16,0,E$23/(B$17-B$16))) -> 700 | E57: =IF(F57="","",E56-D57) -> 1400 | F57: =IF(D57="","",D57+C57) -> 735.49 | AA57: =IF(AA56<B$17,AA56+1,"") -> 28 | AB57: =IF(AA57="","",AB56+30) -> 47080 | AC57: =IF(AB57="","",IF(AA57<=B$16,AC56,AC56-AD57)) -> 5600 | AD57: =IF(AA57="","",IF(AA57<=B$16,0,B$15/(B$17-B$16))) -> 700 | AE57: =IF(AD57="","",AB57-AB56) -> 30 | AF57: =IF(AE57="","",AB57-AB$29) -> 840 | AG57: =IF(AF57="","",IF(AF57<365,AF57*AC$25*AD57,365*AD57*AC$25)) -> 10.4755 | AH57: =IF(AF57="","",IF(AF57<365,AF57*AC$26*AD57,365*AD57*AC$26)) -> 3.50035
A58: =IF(A57<B$17,A57+1,"") -> 35 | B58: =IF(A58="","",IF(A58<=B$16,"carência","amortização")) -> amortização | C58: =IF(B58="","",E57*$C$23) -> 23.66 | D58: =IF(C58="","",IF(A58<=B$16,0,E$23/(B$17-B$16))) -> 700 | E58: =IF(F58="","",E57-D58) -> 700 | F58: =IF(D58="","",D58+C58) -> 723.66 | AA58: =IF(AA57<B$17,AA57+1,"") -> 29 | AB58: =IF(AA58="","",AB57+30) -> 47110 | AC58: =IF(AB58="","",IF(AA58<=B$16,AC57,AC57-AD58)) -> 4900 | AD58: =IF(AA58="","",IF(AA58<=B$16,0,B$15/(B$17-B$16))) -> 700 | AE58: =IF(AD58="","",AB58-AB57) -> 30 | AF58: =IF(AE58="","",AB58-AB$29) -> 870 | AG58: =IF(AF58="","",IF(AF58<365,AF58*AC$25*AD58,365*AD58*AC$25)) -> 10.4755 | AH58: =IF(AF58="","",IF(AF58<365,AF58*AC$26*AD58,365*AD58*AC$26)) -> 3.50035
A59: =IF(A58<B$17,A58+1,"") -> 36 | B59: =IF(A59="","",IF(A59<=B$16,"carência","amortização")) -> amortização | C59: =IF(B59="","",E58*$C$23) -> 11.83 | D59: =IF(C59="","",IF(A59<=B$16,0,E$23/(B$17-B$16))) -> 700 | E59: =IF(F59="","",E58-D59) -> 0 | F59: =IF(D59="","",D59+C59) -> 711.83 | AA59: =IF(AA58<B$17,AA58+1,"") -> 30 | AB59: =IF(AA59="","",AB58+30) -> 47140 | AC59: =IF(AB59="","",IF(AA59<=B$16,AC58,AC58-AD59)) -> 4200 | AD59: =IF(AA59="","",IF(AA59<=B$16,0,B$15/(B$17-B$16))) -> 700 | AE59: =IF(AD59="","",AB59-AB58) -> 30 | AF59: =IF(AE59="","",AB59-AB$29) -> 900 | AG59: =IF(AF59="","",IF(AF59<365,AF59*AC$25*AD59,365*AD59*AC$25)) -> 10.4755 | AH59: =IF(AF59="","",IF(AF59<365,AF59*AC$26*AD59,365*AD59*AC$26)) -> 3.50035 | AN59: =SUM(F48:F59) -> 9322.74 | AO59: =LARGE(F48:F59,1) -> 841.96
A60: =IF(A59<B$17,A59+1,"") | B60: =IF(A60="","",IF(A60<=B$16,"carência","amortização")) | C60: =IF(B60="","",E59*$C$23) | D60: =IF(C60="","",IF(A60<=B$16,0,E$23/(B$17-B$16))) | E60: =IF(F60="","",E59-D60) | F60: =IF(D60="","",D60+C60) | AA60: =IF(AA59<B$17,AA59+1,"") -> 31 | AB60: =IF(AA60="","",AB59+30) -> 47170 | AC60: =IF(AB60="","",IF(AA60<=B$16,AC59,AC59-AD60)) -> 3500 | AD60: =IF(AA60="","",IF(AA60<=B$16,0,B$15/(B$17-B$16))) -> 700 | AE60: =IF(AD60="","",AB60-AB59) -> 30 | AF60: =IF(AE60="","",AB60-AB$29) -> 930 | AG60: =IF(AF60="","",IF(AF60<365,AF60*AC$25*AD60,365*AD60*AC$25)) -> 10.4755 | AH60: =IF(AF60="","",IF(AF60<365,AF60*AC$26*AD60,365*AD60*AC$26)) -> 3.50035
A61: =IF(A60<B$17,A60+1,"") | B61: =IF(A61="","",IF(A61<=B$16,"carência","amortização")) | C61: =IF(B61="","",E60*$C$23) | D61: =IF(C61="","",IF(A61<=B$16,0,E$23/(B$17-B$16))) | E61: =IF(F61="","",E60-D61) | F61: =IF(D61="","",D61+C61) | AA61: =IF(AA60<B$17,AA60+1,"") -> 32 | AB61: =IF(AA61="","",AB60+30) -> 47200 | AC61: =IF(AB61="","",IF(AA61<=B$16,AC60,AC60-AD61)) -> 2800 | AD61: =IF(AA61="","",IF(AA61<=B$16,0,B$15/(B$17-B$16))) -> 700 | AE61: =IF(AD61="","",AB61-AB60) -> 30 | AF61: =IF(AE61="","",AB61-AB$29) -> 960 | AG61: =IF(AF61="","",IF(AF61<365,AF61*AC$25*AD61,365*AD61*AC$25)) -> 10.4755 | AH61: =IF(AF61="","",IF(AF61<365,AF61*AC$26*AD61,365*AD61*AC$26)) -> 3.50035
A62: =IF(A61<B$17,A61+1,"") | B62: =IF(A62="","",IF(A62<=B$16,"carência","amortização")) | C62: =IF(B62="","",E61*$C$23) | D62: =IF(C62="","",IF(A62<=B$16,0,E$23/(B$17-B$16))) | E62: =IF(F62="","",E61-D62) | F62: =IF(D62="","",D62+C62) | AA62: =IF(AA61<B$17,AA61+1,"") -> 33 | AB62: =IF(AA62="","",AB61+30) -> 47230 | AC62: =IF(AB62="","",IF(AA62<=B$16,AC61,AC61-AD62)) -> 2100 | AD62: =IF(AA62="","",IF(AA62<=B$16,0,B$15/(B$17-B$16))) -> 700 | AE62: =IF(AD62="","",AB62-AB61) -> 30 | AF62: =IF(AE62="","",AB62-AB$29) -> 990 | AG62: =IF(AF62="","",IF(AF62<365,AF62*AC$25*AD62,365*AD62*AC$25)) -> 10.4755 | AH62: =IF(AF62="","",IF(AF62<365,AF62*AC$26*AD62,365*AD62*AC$26)) -> 3.50035
A63: =IF(A62<B$17,A62+1,"") | B63: =IF(A63="","",IF(A63<=B$16,"carência","amortização")) | C63: =IF(B63="","",E62*$C$23) | D63: =IF(C63="","",IF(A63<=B$16,0,E$23/(B$17-B$16))) | E63: =IF(F63="","",E62-D63) | F63: =IF(D63="","",D63+C63) | AA63: =IF(AA62<B$17,AA62+1,"") -> 34 | AB63: =IF(AA63="","",AB62+30) -> 47260 | AC63: =IF(AB63="","",IF(AA63<=B$16,AC62,AC62-AD63)) -> 1400 | AD63: =IF(AA63="","",IF(AA63<=B$16,0,B$15/(B$17-B$16))) -> 700 | AE63: =IF(AD63="","",AB63-AB62) -> 30 | AF63: =IF(AE63="","",AB63-AB$29) -> 1020 | AG63: =IF(AF63="","",IF(AF63<365,AF63*AC$25*AD63,365*AD63*AC$25)) -> 10.4755 | AH63: =IF(AF63="","",IF(AF63<365,AF63*AC$26*AD63,365*AD63*AC$26)) -> 3.50035
A64: =IF(A63<B$17,A63+1,"") | B64: =IF(A64="","",IF(A64<=B$16,"carência","amortização")) | C64: =IF(B64="","",E63*$C$23) | D64: =IF(C64="","",IF(A64<=B$16,0,E$23/(B$17-B$16))) | E64: =IF(F64="","",E63-D64) | F64: =IF(D64="","",D64+C64) | AA64: =IF(AA63<B$17,AA63+1,"") -> 35 | AB64: =IF(AA64="","",AB63+30) -> 47290 | AC64: =IF(AB64="","",IF(AA64<=B$16,AC63,AC63-AD64)) -> 700 | AD64: =IF(AA64="","",IF(AA64<=B$16,0,B$15/(B$17-B$16))) -> 700 | AE64: =IF(AD64="","",AB64-AB63) -> 30 | AF64: =IF(AE64="","",AB64-AB$29) -> 1050 | AG64: =IF(AF64="","",IF(AF64<365,AF64*AC$25*AD64,365*AD64*AC$25)) -> 10.4755 | AH64: =IF(AF64="","",IF(AF64<365,AF64*AC$26*AD64,365*AD64*AC$26)) -> 3.50035
A65: =IF(A64<B$17,A64+1,"") | B65: =IF(A65="","",IF(A65<=B$16,"carência","amortização")) | C65: =IF(B65="","",E64*$C$23) | D65: =IF(C65="","",IF(A65<=B$16,0,E$23/(B$17-B$16))) | E65: =IF(F65="","",E64-D65) | F65: =IF(D65="","",D65+C65) | AA65: =IF(AA64<B$17,AA64+1,"") -> 36 | AB65: =IF(AA65="","",AB64+30) -> 47320 | AC65: =IF(AB65="","",IF(AA65<=B$16,AC64,AC64-AD65)) -> 0 | AD65: =IF(AA65="","",IF(AA65<=B$16,0,B$15/(B$17-B$16))) -> 700 | AE65: =IF(AD65="","",AB65-AB64) -> 30 | AF65: =IF(AE65="","",AB65-AB$29) -> 1080 | AG65: =IF(AF65="","",IF(AF65<365,AF65*AC$25*AD65,365*AD65*AC$25)) -> 10.4755 | AH65: =IF(AF65="","",IF(AF65<365,AF65*AC$26*AD65,365*AD65*AC$26)) -> 3.50035
A66: =IF(A65<B$17,A65+1,"") | B66: =IF(A66="","",IF(A66<=B$16,"carência","amortização")) | C66: =IF(B66="","",E65*$C$23) | D66: =IF(C66="","",IF(A66<=B$16,0,E$23/(B$17-B$16))) | E66: =IF(F66="","",E65-D66) | F66: =IF(D66="","",D66+C66) | AA66: =IF(AA65<B$17,AA65+1,"") | AB66: =IF(AA66="","",AB65+30) | AC66: =IF(AB66="","",IF(AA66<=B$16,AC65,AC65-AD66)) | AD66: =IF(AA66="","",IF(AA66<=B$16,0,B$15/(B$17-B$16))) | AE66: =IF(AD66="","",AB66-AB65) | AF66: =IF(AE66="","",AB66-AB$29) | AG66: =IF(AF66="","",IF(AF66<365,AF66*AC$25*AD66,365*AD66*AC$25)) | AH66: =IF(AF66="","",IF(AF66<365,AF66*AC$26*AD66,365*AD66*AC$26))
A67: =IF(A66<B$17,A66+1,"") | B67: =IF(A67="","",IF(A67<=B$16,"carência","amortização")) | C67: =IF(B67="","",E66*$C$23) | D67: =IF(C67="","",IF(A67<=B$16,0,E$23/(B$17-B$16))) | E67: =IF(F67="","",E66-D67) | F67: =IF(D67="","",D67+C67) | AA67: =IF(AA66<B$17,AA66+1,"") | AB67: =IF(AA67="","",AB66+30) | AC67: =IF(AB67="","",IF(AA67<=B$16,AC66,AC66-AD67)) | AD67: =IF(AA67="","",IF(AA67<=B$16,0,B$15/(B$17-B$16))) | AE67: =IF(AD67="","",AB67-AB66) | AF67: =IF(AE67="","",AB67-AB$29) | AG67: =IF(AF67="","",IF(AF67<365,AF67*AC$25*AD67,365*AD67*AC$25)) | AH67: =IF(AF67="","",IF(AF67<365,AF67*AC$26*AD67,365*AD67*AC$26))
A68: =IF(A67<B$17,A67+1,"") | B68: =IF(A68="","",IF(A68<=B$16,"carência","amortização")) | C68: =IF(B68="","",E67*$C$23) | D68: =IF(C68="","",IF(A68<=B$16,0,E$23/(B$17-B$16))) | E68: =IF(F68="","",E67-D68) | F68: =IF(D68="","",D68+C68) | AA68: =IF(AA67<B$17,AA67+1,"") | AB68: =IF(AA68="","",AB67+30) | AC68: =IF(AB68="","",IF(AA68<=B$16,AC67,AC67-AD68)) | AD68: =IF(AA68="","",IF(AA68<=B$16,0,B$15/(B$17-B$16))) | AE68: =IF(AD68="","",AB68-AB67) | AF68: =IF(AE68="","",AB68-AB$29) | AG68: =IF(AF68="","",IF(AF68<365,AF68*AC$25*AD68,365*AD68*AC$25)) | AH68: =IF(AF68="","",IF(AF68<365,AF68*AC$26*AD68,365*AD68*AC$26))
A69: =IF(A68<B$17,A68+1,"") | B69: =IF(A69="","",IF(A69<=B$16,"carência","amortização")) | C69: =IF(B69="","",E68*$C$23) | D69: =IF(C69="","",IF(A69<=B$16,0,E$23/(B$17-B$16))) | E69: =IF(F69="","",E68-D69) | F69: =IF(D69="","",D69+C69) | AA69: =IF(AA68<B$17,AA68+1,"") | AB69: =IF(AA69="","",AB68+30) | AC69: =IF(AB69="","",IF(AA69<=B$16,AC68,AC68-AD69)) | AD69: =IF(AA69="","",IF(AA69<=B$16,0,B$15/(B$17-B$16))) | AE69: =IF(AD69="","",AB69-AB68) | AF69: =IF(AE69="","",AB69-AB$29) | AG69: =IF(AF69="","",IF(AF69<365,AF69*AC$25*AD69,365*AD69*AC$25)) | AH69: =IF(AF69="","",IF(AF69<365,AF69*AC$26*AD69,365*AD69*AC$26))
A70: =IF(A69<B$17,A69+1,"") | B70: =IF(A70="","",IF(A70<=B$16,"carência","amortização")) | C70: =IF(B70="","",E69*$C$23) | D70: =IF(C70="","",IF(A70<=B$16,0,E$23/(B$17-B$16))) | E70: =IF(F70="","",E69-D70) | F70: =IF(D70="","",D70+C70) | AA70: =IF(AA69<B$17,AA69+1,"") | AB70: =IF(AA70="","",AB69+30) | AC70: =IF(AB70="","",IF(AA70<=B$16,AC69,AC69-AD70)) | AD70: =IF(AA70="","",IF(AA70<=B$16,0,B$15/(B$17-B$16))) | AE70: =IF(AD70="","",AB70-AB69) | AF70: =IF(AE70="","",AB70-AB$29) | AG70: =IF(AF70="","",IF(AF70<365,AF70*AC$25*AD70,365*AD70*AC$25)) | AH70: =IF(AF70="","",IF(AF70<365,AF70*AC$26*AD70,365*AD70*AC$26))
A71: =IF(A70<B$17,A70+1,"") | B71: =IF(A71="","",IF(A71<=B$16,"carência","amortização")) | C71: =IF(B71="","",E70*$C$23) | D71: =IF(C71="","",IF(A71<=B$16,0,E$23/(B$17-B$16))) | E71: =IF(F71="","",E70-D71) | F71: =IF(D71="","",D71+C71) | AA71: =IF(AA70<B$17,AA70+1,"") | AB71: =IF(AA71="","",AB70+30) | AC71: =IF(AB71="","",IF(AA71<=B$16,AC70,AC70-AD71)) | AD71: =IF(AA71="","",IF(AA71<=B$16,0,B$15/(B$17-B$16))) | AE71: =IF(AD71="","",AB71-AB70) | AF71: =IF(AE71="","",AB71-AB$29) | AG71: =IF(AF71="","",IF(AF71<365,AF71*AC$25*AD71,365*AD71*AC$25)) | AH71: =IF(AF71="","",IF(AF71<365,AF71*AC$26*AD71,365*AD71*AC$26))
AA72: =IF(AA71<B$17,AA71+1,"") | AB72: =IF(AA72="","",AB71+30) | AC72: =IF(AB72="","",IF(AA72<=B$16,AC71,AC71-AD72)) | AD72: =IF(AA72="","",IF(AA72<=B$16,0,B$15/(B$17-B$16))) | AE72: =IF(AD72="","",AB72-AB71) | AF72: =IF(AE72="","",AB72-AB$29) | AG72: =IF(AF72="","",IF(AF72<365,AF72*AC$25*AD72,365*AD72*AC$25)) | AH72: =IF(AF72="","",IF(AF72<365,AF72*AC$26*AD72,365*AD72*AC$26))
AA73: =IF(AA72<B$17,AA72+1,"") | AB73: =IF(AA73="","",AB72+30) | AC73: =IF(AB73="","",IF(AA73<=B$16,AC72,AC72-AD73)) | AD73: =IF(AA73="","",IF(AA73<=B$16,0,B$15/(B$17-B$16))) | AE73: =IF(AD73="","",AB73-AB72) | AF73: =IF(AE73="","",AB73-AB$29) | AG73: =IF(AF73="","",IF(AF73<365,AF73*AC$25*AD73,365*AD73*AC$25)) | AH73: =IF(AF73="","",IF(AF73<365,AF73*AC$26*AD73,365*AD73*AC$26))
AA74: =IF(AA73<B$17,AA73+1,"") | AB74: =IF(AA74="","",AB73+30) | AC74: =IF(AB74="","",IF(AA74<=B$16,AC73,AC73-AD74)) | AD74: =IF(AA74="","",IF(AA74<=B$16,0,B$15/(B$17-B$16))) | AE74: =IF(AD74="","",AB74-AB73) | AF74: =IF(AE74="","",AB74-AB$29) | AG74: =IF(AF74="","",IF(AF74<365,AF74*AC$25*AD74,365*AD74*AC$25)) | AH74: =IF(AF74="","",IF(AF74<365,AF74*AC$26*AD74,365*AD74*AC$26))
AA75: =IF(AA74<B$17,AA74+1,"") | AB75: =IF(AA75="","",AB74+30) | AC75: =IF(AB75="","",IF(AA75<=B$16,AC74,AC74-AD75)) | AD75: =IF(AA75="","",IF(AA75<=B$16,0,B$15/(B$17-B$16))) | AE75: =IF(AD75="","",AB75-AB74) | AF75: =IF(AE75="","",AB75-AB$29) | AG75: =IF(AF75="","",IF(AF75<365,AF75*AC$25*AD75,365*AD75*AC$25)) | AH75: =IF(AF75="","",IF(AF75<365,AF75*AC$26*AD75,365*AD75*AC$26))
AA76: =IF(AA75<B$17,AA75+1,"") | AB76: =IF(AA76="","",AB75+30) | AC76: =IF(AB76="","",IF(AA76<=B$16,AC75,AC75-AD76)) | AD76: =IF(AA76="","",IF(AA76<=B$16,0,B$15/(B$17-B$16))) | AE76: =IF(AD76="","",AB76-AB75) | AF76: =IF(AE76="","",AB76-AB$29) | AG76: =IF(AF76="","",IF(AF76<365,AF76*AC$25*AD76,365*AD76*AC$25)) | AH76: =IF(AF76="","",IF(AF76<365,AF76*AC$26*AD76,365*AD76*AC$26))
AA77: =IF(AA76<B$17,AA76+1,"") | AB77: =IF(AA77="","",AB76+30) | AC77: =IF(AB77="","",IF(AA77<=B$16,AC76,AC76-AD77)) | AD77: =IF(AA77="","",IF(AA77<=B$16,0,B$15/(B$17-B$16))) | AE77: =IF(AD77="","",AB77-AB76) | AF77: =IF(AE77="","",AB77-AB$29) | AG77: =IF(AF77="","",IF(AF77<365,AF77*AC$25*AD77,365*AD77*AC$25)) | AH77: =IF(AF77="","",IF(AF77<365,AF77*AC$26*AD77,365*AD77*AC$26))
AA78: =IF(AA77<B$17,AA77+1,"") | AC78: =IF(AB78="","",IF(AA78<=B$16,AC77,AC77-AD78)) | AD78: =IF(AA78="","",IF(AA78<=B$16,0,B$15/(B$17-B$16))) | AF78: =IF(AE78="","",AB78-AB$29) | AG78: =IF(AF78="","",IF(AF78<365,AF78*AC$25*AD78,365*AD78*AC$25)) | AH78: =IF(AF78="","",IF(AF78<365,AF78*AC$26*AD78,365*AD78*AC$26))
AA79: =IF(AA78<B$17,AA78+1,"") | AC79: =IF(AB79="","",IF(AA79<=B$16,AC78,AC78-AD79)) | AD79: =IF(AA79="","",IF(AA79<=B$16,0,B$15/(B$17-B$16))) | AF79: =IF(AE79="","",AB79-AB$29) | AG79: =IF(AF79="","",IF(AF79<365,AF79*AC$25*AD79,365*AD79*AC$25)) | AH79: =IF(AF79="","",IF(AF79<365,AF79*AC$26*AD79,365*AD79*AC$26))
AA80: =IF(AA79<B$17,AA79+1,"") | AC80: =IF(AB80="","",IF(AA80<=B$16,AC79,AC79-AD80)) | AD80: =IF(AA80="","",IF(AA80<=B$16,0,B$15/(B$17-B$16))) | AF80: =IF(AE80="","",AB80-AB$29) | AG80: =IF(AF80="","",IF(AF80<365,AF80*AC$25*AD80,365*AD80*AC$25)) | AH80: =IF(AF80="","",IF(AF80<365,AF80*AC$26*AD80,365*AD80*AC$26))
AA81: =IF(AA80<B$17,AA80+1,"") | AC81: =IF(AB81="","",IF(AA81<=B$16,AC80,AC80-AD81)) | AD81: =IF(AA81="","",IF(AA81<=B$16,0,B$15/(B$17-B$16))) | AF81: =IF(AE81="","",AB81-AB$29) | AG81: =IF(AF81="","",IF(AF81<365,AF81*AC$25*AD81,365*AD81*AC$25)) | AH81: =IF(AF81="","",IF(AF81<365,AF81*AC$26*AD81,365*AD81*AC$26))
AA82: =IF(AA81<B$17,AA81+1,"") | AC82: =IF(AB82="","",IF(AA82<=B$16,AC81,AC81-AD82)) | AD82: =IF(AA82="","",IF(AA82<=B$16,0,B$15/(B$17-B$16))) | AF82: =IF(AE82="","",AB82-AB$29) | AG82: =IF(AF82="","",IF(AF82<365,AF82*AC$25*AD82,365*AD82*AC$25)) | AH82: =IF(AF82="","",IF(AF82<365,AF82*AC$26*AD82,365*AD82*AC$26))
AA83: =IF(AA82<B$17,AA82+1,"") | AC83: =IF(AB83="","",IF(AA83<=B$16,AC82,AC82-AD83)) | AD83: =IF(AA83="","",IF(AA83<=B$16,0,B$15/(B$17-B$16))) | AF83: =IF(AE83="","",AB83-AB$29) | AG83: =IF(AF83="","",IF(AF83<365,AF83*AC$25*AD83,365*AD83*AC$25)) | AH83: =IF(AF83="","",IF(AF83<365,AF83*AC$26*AD83,365*AD83*AC$26))
AA84: =IF(AA83<B$17,AA83+1,"") | AC84: =IF(AB84="","",IF(AA84<=B$16,AC83,AC83-AD84)) | AD84: =IF(AA84="","",IF(AA84<=B$16,0,B$15/(B$17-B$16))) | AF84: =IF(AE84="","",AB84-AB$29) | AG84: =IF(AF84="","",IF(AF84<365,AF84*AC$25*AD84,365*AD84*AC$25)) | AH84: =IF(AF84="","",IF(AF84<365,AF84*AC$26*AD84,365*AD84*AC$26))
AA85: =IF(AA84<B$17,AA84+1,"") | AC85: =IF(AB85="","",IF(AA85<=B$16,AC84,AC84-AD85)) | AD85: =IF(AA85="","",IF(AA85<=B$16,0,B$15/(B$17-B$16))) | AF85: =IF(AE85="","",AB85-AB$29) | AG85: =IF(AF85="","",IF(AF85<365,AF85*AC$25*AD85,365*AD85*AC$25)) | AH85: =IF(AF85="","",IF(AF85<365,AF85*AC$26*AD85,365*AD85*AC$26))
AA86: =IF(AA85<B$17,AA85+1,"") | AC86: =IF(AB86="","",IF(AA86<=B$16,AC85,AC85-AD86)) | AD86: =IF(AA86="","",IF(AA86<=B$16,0,B$15/(B$17-B$16))) | AF86: =IF(AE86="","",AB86-AB$29) | AG86: =IF(AF86="","",IF(AF86<365,AF86*AC$25*AD86,365*AD86*AC$25)) | AH86: =IF(AF86="","",IF(AF86<365,AF86*AC$26*AD86,365*AD86*AC$26))
AA87: =IF(AA86<B$17,AA86+1,"") | AC87: =IF(AB87="","",IF(AA87<=B$16,AC86,AC86-AD87)) | AD87: =IF(AA87="","",IF(AA87<=B$16,0,B$15/(B$17-B$16))) | AF87: =IF(AE87="","",AB87-AB$29) | AG87: =IF(AF87="","",IF(AF87<365,AF87*AC$25*AD87,365*AD87*AC$25)) | AH87: =IF(AF87="","",IF(AF87<365,AF87*AC$26*AD87,365*AD87*AC$26))
AA88: =IF(AA87<B$17,AA87+1,"") | AC88: =IF(AB88="","",IF(AA88<=B$16,AC87,AC87-AD88)) | AD88: =IF(AA88="","",IF(AA88<=B$16,0,B$15/(B$17-B$16))) | AF88: =IF(AE88="","",AB88-AB$29) | AG88: =IF(AF88="","",IF(AF88<365,AF88*AC$25*AD88,365*AD88*AC$25)) | AH88: =IF(AF88="","",IF(AF88<365,AF88*AC$26*AD88,365*AD88*AC$26))
AA89: =IF(AA88<B$17,AA88+1,"") | AC89: =IF(AB89="","",IF(AA89<=B$16,AC88,AC88-AD89)) | AD89: =IF(AA89="","",IF(AA89<=B$16,0,B$15/(B$17-B$16))) | AF89: =IF(AE89="","",AB89-AB$29) | AG89: =IF(AF89="","",IF(AF89<365,AF89*AC$25*AD89,365*AD89*AC$25)) | AH89: =IF(AF89="","",IF(AF89<365,AF89*AC$26*AD89,365*AD89*AC$26))
... AA229: =IF(AA228<B$17,AA228+1,"") | AC229: =IF(AB229="","",IF(AA229<=B$16,AC228,AC228-AD229)) | AD229: =IF(AA229="","",IF(AA229<=B$16,0,B$15/(B$17-B$16))) | AF229: =IF(AE229="","",AB229-AB$29) | AG229: =IF(AF229="","",IF(AF229<365,AF229*AC$25*AD229,365*AD229*AC$25)) | AH229: =IF(AF229="","",IF(AF229<365,AF229*AC$26*AD229,365*AD229*AC$26))
AA230: =IF(AA229<B$17,AA229+1,"") | AC230: =IF(AB230="","",IF(AA230<=B$16,AC229,AC229-AD230)) | AD230: =IF(AA230="","",IF(AA230<=B$16,0,B$15/(B$17-B$16))) | AG230: =IF(AF230="","",IF(AF230<365,AF230*AC$25*AD230,365*AD230*AC$25)) | AH230: =IF(AF230="","",IF(AF230<365,AF230*AC$26*AD230,365*AD230*AC$26))
AA231: =IF(AA230<B$17,AA230+1,"") | AC231: =IF(AB231="","",IF(AA231<=B$16,AC230,AC230-AD231)) | AD231: =IF(AA231="","",IF(AA231<=B$16,0,B$15/(B$17-B$16))) | AG231: =IF(AF231="","",IF(AF231<365,AF231*AC$25*AD231,365*AD231*AC$25)) | AH231: =IF(AF231="","",IF(AF231<365,AF231*AC$26*AD231,365*AD231*AC$26))
AA232: =IF(AA231<B$17,AA231+1,"") | AC232: =IF(AB232="","",IF(AA232<=B$16,AC231,AC231-AD232)) | AD232: =IF(AA232="","",IF(AA232<=B$16,0,B$15/(B$17-B$16))) | AG232: =IF(AF232="","",IF(AF232<365,AF232*AC$25*AD232,365*AD232*AC$25)) | AH232: =IF(AF232="","",IF(AF232<365,AF232*AC$26*AD232,365*AD232*AC$26))
AA233: =IF(AA232<B$17,AA232+1,"") | AC233: =IF(AB233="","",IF(AA233<=B$16,AC232,AC232-AD233)) | AD233: =IF(AA233="","",IF(AA233<=B$16,0,B$15/(B$17-B$16))) | AG233: =IF(AF233="","",IF(AF233<365,AF233*AC$25*AD233,365*AD233*AC$25)) | AH233: =IF(AF233="","",IF(AF233<365,AF233*AC$26*AD233,365*AD233*AC$26))
AA234: =IF(AA233<B$17,AA233+1,"") | AC234: =IF(AB234="","",IF(AA234<=B$16,AC233,AC233-AD234)) | AD234: =IF(AA234="","",IF(AA234<=B$16,0,B$15/(B$17-B$16))) | AG234: =IF(AF234="","",IF(AF234<365,AF234*AC$25*AD234,365*AD234*AC$25)) | AH234: =IF(AF234="","",IF(AF234<365,AF234*AC$26*AD234,365*AD234*AC$26))
AA235: =IF(AA234<B$17,AA234+1,"") | AC235: =IF(AB235="","",E229) | AD235: =IF(AA235="","",IF(AA235<=B$16,0,B$15/(B$17-B$16))) | AG235: =IF(AF235="","",IF(AF235<365,AF235*AC$25*AD235,365*AD235*AC$25)) | AH235: =IF(AF235="","",IF(AF235<365,AF235*AC$26*AD235,365*AD235*AC$26))
AA236: =IF(AA235<B$17,AA235+1,"") | AC236: =IF(AB236="","",E230) | AD236: =IF(AA236="","",IF(AA236<=B$16,0,B$15/(B$17-B$16))) | AG236: =IF(AF236="","",IF(AF236<365,AF236*AC$25*AD236,365*AD236*AC$25)) | AH236: =IF(AF236="","",IF(AF236<365,AF236*AC$26*AD236,365*AD236*AC$26))
AA237: =IF(AA236<B$17,AA236+1,"") | AC237: =IF(AB237="","",E231) | AD237: =IF(AA237="","",IF(AA237<=B$16,0,B$15/(B$17-B$16))) | AG237: =IF(AF237="","",IF(AF237<365,AF237*AC$25*AD237,365*AD237*AC$25)) | AH237: =IF(AF237="","",IF(AF237<365,AF237*AC$26*AD237,365*AD237*AC$26))
AA238: =IF(AA237<B$17,AA237+1,"") | AC238: =IF(AB238="","",E232) | AD238: =IF(AA238="","",IF(AA238<=B$16,0,B$15/(B$17-B$16))) | AG238: =IF(AF238="","",IF(AF238<365,AF238*AC$25*AD238,365*AD238*AC$25)) | AH238: =IF(AF238="","",IF(AF238<365,AF238*AC$26*AD238,365*AD238*AC$26))
AA239: =IF(AA238<B$17,AA238+1,"") | AC239: =IF(AB239="","",E233) | AD239: =IF(AA239="","",IF(AA239<=B$16,0,B$15/(B$17-B$16))) | AG239: =IF(AF239="","",IF(AF239<365,AF239*AC$25*AD239,365*AD239*AC$25)) | AH239: =IF(AF239="","",IF(AF239<365,AF239*AC$26*AD239,365*AD239*AC$26))
...

Sheet Linhas Transportes
A1: AGÊNCIA DE FOMENTO DE GOIÁS S/A | AA1: 2 | AB1: 2
A2: IMPORTANTE: Os valores simulados podem variar e estão sujeitos à data de vencimento da parcela e da liberação do crédito; O financiamento e condições são sujeitas à aprovação final da análise de crédito; Valores calculados com base na taxa líquida para quando não há atraso nos pagamentos.
A3: LINHA DE INVESTIMENTO | AA3: TAC | AB3: IOF
A4: LINHA | J4: 1 | K4: 1 | N4: LINHA | O4: TAXA (a.m.) | P4: TAXA BONUS | Q4: CG1 (a.m.) | R4: CG2 (a.m.) | S4: PRAZO (meses) | T4: CARÊNCIA (até meses) | U4: LIMITE | V4: GARANTIA | AA4: Descontado | AB4: Descontado
N5: GoiásFomento Taxi | O5: 0.0206 | P5: 0.0165 | Q5: =P5 -> 0.0165 | R5: =Q5 -> 0.0165 | S5: 60 | T5: 3 | U5: 90000 | V5: Sim | AA5: Financiado | AB5: Financiado
C6: =IF(AND(J4=1,K4=1),Q5,IF(AND(J4=1,K4=2),R5,IF(AND(J4=1,K4=3),P5,"-"))) -> 0.0165 | N6: GoiásFomento Mototaxi | O6: =O5 -> 0.0206 | P6: =P5 -> 0.0165 | Q6: =Q5 -> 0.0165 | R6: =R5 -> 0.0165 | S6: 60 | T6: 3 | U6: 14000 | V6: Não
C7: =IF(AND(J4=2,K4=1),Q6,IF(AND(J4=2,K4=2),R6,IF(AND(J4=2,K4=3),P6,"-"))) -> - | N7: GoiásFomento Transporte Escolar | O7: =O6 -> 0.0206 | P7: =P6 -> 0.0165 | Q7: =Q6 -> 0.0165 | R7: =R6 -> 0.0165 | S7: 60 | T7: 3 | U7: 150000
C8: =IF(AND(J4=3,K4=1),Q7,IF(AND(J4=3,K4=2),R7,IF(AND(J4=3,K4=3),P7,"-"))) -> - | N8: Goiás Fomento TransGás | O8: =O7 -> 0.0206 | P8: =P7 -> 0.0165 | Q8: =Q7 -> 0.0165 | R8: =R7 -> 0.0165 | S8: 60 | T8: 3 | U8: 40000
C9: =IF(AND(J4=4,K4=1),Q8,IF(AND(J4=4,K4=2),R8,IF(AND(J4=4,K4=3),P8,"-"))) -> - | N9: GoiásFomento Feirantes | O9: =O8 -> 0.0206 | P9: =P8 -> 0.0165 | Q9: =Q8 -> 0.0165 | R9: =R8 -> 0.0165 | S9: 60 | T9: 3 | U9: 200000
C10: =IF(AND(J4=5,K4=1),Q9,IF(AND(J4=5,K4=2),R9,IF(AND(J4=5,K4=3),P9,"-"))) -> - | O10: 0.0183 | P10: 0.0146 | Q10: =P10 -> 0.0146 | R10: =Q10 -> 0.0146 | S10: 60 | T10: 3 | U10: 0
C11: =IF(AND(J4=6,K4=1),Q10,IF(AND(J4=6,K4=2),R10,IF(AND(J4=6,K4=3),P10,"-"))) -> - | O11: 0.0183 | P11: 0.0146 | Q11: =P11 -> 0.0146 | R11: =Q11 -> 0.0146 | S11: 60 | T11: 3 | U11: 0
C12: =IF(AND(J4=7,K4=1),Q11,IF(AND(J4=7,K4=2),R11,IF(AND(J4=7,K4=3),P11,"-"))) -> - | O12: 0.0183 | P12: 0.0146 | Q12: =P12 -> 0.0146 | R12: =Q12 -> 0.0146 | S12: 60 | T12: 3 | U12: 21000
C13: =IF(AND(J4=8,K4=1),Q12,IF(AND(J4=8,K4=2),R12,IF(AND(J4=8,K4=3),P12,"-"))) -> -
A14: INFORMAÇÕES
A15: VALOR FINANCIADO | B15: 44000 | C15: TAXA NOMINAL | D15: =IF(J4=1,O5,IF(J4=2,O6,IF(J4=3,O7,IF(J4=4,O8,IF(J4=5,O9,IF(J4=6,O10,IF(J4=7,O11,IF(J4=8,O12)))))))) -> 0.0206 | F15: =IF(B15<=3000,50,IF(B15<=21000,IF(B15*0.03<=420,B15*0.03,420),IF(B15<=100000,B15*0.02,2000+B15*0.005))) -> 880 | J15: 4
A16: CARÊNCIA | B16: 0 | C16: TAXA COM BÔNUS | D16: =LARGE(C6:C13,1) -> 0.0165 | F16: =AF24 -> 723.43333 | J16: 2
A17: PRAZO TOTAL | B17: 36 | C17: DATA DA PROPOSTA | D17: =TODAY() -> 46240 | F17: =IF(J21=TRUE,IF(K4=1,(B15*E19*0.001*B17),IF(K4=2,(F19*0.001*B17),IF(K4=3,0,""))),0) -> 0 | J17: Descontado | L17: FALSE
A18: OPÇÕES DE GARANTIA | J18: Financiado
A19: RENDA PARA AVAL | B19: =IF(LARGE(F23:F241,1)*3<2424,2424,LARGE(F23:F241,1)*3) -> 5924.0366 | C19: ALIENAÇÃO DE IMÓVEL | D19: =IF(J21=TRUE,(B15-F19)*1.5/0.7,B15*1.5/0.7) -> 94285.714 | E19: 0.8 | F19: =IF(J21=TRUE,IF(K4=1,(B15*E19),IF(K4=2,B15*E19,IF(K4=3,0,""))),0) -> 0 | J19: FINANCIADO | L19: TRUE
A20: SIMULAÇÃO DO VALOR DAS PARCELAS | J20: Financiado
A21: PARCELA | B21: AMORTIZAÇÃO | C21: JUROS | D21: VALOR AMORTIZAÇÃO | E21: SALDO DEVEDOR | F21: PARCELA COM BÔNUS | J21: FALSE | AB21: IOF - ACIMA ATÉ 365 DIAS
A22: TOTAL | C22: =SUM(C23:C242) -> 14180.622 | D22: =SUM(D23:D242) -> 45068.956 | F22: =SUM(F23:F242) -> 59249.561
A23: 0 | C23: =D16 -> 0.0165 | E23: =IF(AND(AA1=1,AB1=1,J16=1),B15,IF(AND(AA1=1,AB1=1,J16=2),B15+F17,IF(AND(AA1=1,AB1=2,J16=1),B15+F16,IF(AND(AA1=1,AB1=2,J16=3),B15+F16,IF(AND(AA1=2,AB1=1,J16=1),B15+F15,IF(AND(AA1=2,AB1=1,J16=2),B15+F15+F17,IF(AND(AA1=2,AB1=2,J16=2),B15+F17+F16+F15,IF(AND(AA1=2,AB1=2,J16=3),B15+F15+F16,IF(AND(AA1=2,AB1=2,J16=1),B15+F15+F16,IF(AND(AA1=1,AB1=2,J16=2),B15+F16+F17, IF(AND(AA1=1,AB1=1,J16=3),B15))))))))))) -> 45603.433
A24: =IF(A23<B$17,A23+1,"") -> 1 | B24: =IF(A24="","",IF(A24<=B$16,"carência","amortização")) -> amortização | C24: =IF(B24="","",E23*$C$23) -> 752.45665 | D24: =IF(C24="","",IF(A24<=B$16,0,B$15/(B$17-B$16))) -> 1222.2222 | E24: =IF(F24="","",E23-D24) -> 44381.211 | F24: =IF(D24="","",D24+C24) -> 1974.6789 | AB24: IOF | AC24: 0.0038 | AE24: =AC27*AC24 -> 167.2 | AF24: =IF(L19=FALSE,0,IF(AND(AH25=TRUE,B15<=30000),AE24+AE26,AE24+AE25)) -> 723.43333
